Workbook
Name data: #REF!
Name data: #REF!
Name data: #REF!
Name data: #REF!
Name data: #REF!
Name data: #REF!
Name data: #REF!
Name data: #REF!
Name data: #REF!

Sheet لوحة الربحية
A1: لوحة الربحية والتكلفة – مشروع سبارك
A2: نسخة إدارية قابلة للتحديث – جميع القيم بالريال السعودي، والمصروفات الإضافية تُسجل في ورقة «المصروفات الإضافية».
A5: قيمة العقد الأصلية | B5: =6493121.74 -> 6493121.7 | D5: قراءة سريعة
A6: أوامر التغيير | B6: =27918 -> 27918 | D6: نسبة الإنجاز التعاقدية | E6: =IFERROR(B8/B7,0) -> 0.89523428
A7: قيمة العقد المعدلة | B7: =B5+B6 -> 6521039.7 | D7: نسبة التكلفة المباشرة من قيمة الأعمال | E7: =IFERROR(B11/B8,0) -> 0.67354787
A8: قيمة الأعمال المنجزة | B8: =summary!K44 -> 5837858.3 | D8: نقطة الانتباه | E8: أدخل المصروفات غير المباشرة أولاً بأول
A9: تكلفة المواد المباشرة | B9: ='ملخص التكاليف'!B37 -> 3104507 | D9: النتيجة الحالية | E9: الربح الصافي يتغير تلقائياً بعد تسجيل المصروفات
A10: تكلفة العمالة المباشرة | B10: ='ملخص التكاليف'!C37 -> 827570
A11: إجمالي التكلفة المباشرة | B11: ='ملخص التكاليف'!D37 -> 3932077
A12: الربح الفعلي حسب Profit | B12: ='ملخص التكاليف'!G37 -> 2483848.9 | D12: البند | E12: القيمة
A13: المصروفات الإضافية | B13: ='ملخص التكاليف'!B52 -> 549500 | D13: قيمة الأعمال المنجزة | E13: =B8 -> 5837858.3
A14: الربح الصافي بعد المصروفات الإضافية | B14: =B12-B13 -> 1934348.9 | D14: التكلفة المباشرة | E14: =B11 -> 3932077
A15: هامش الربح الصافي | B15: =IFERROR(B14/B8,0) -> 0.33134563 | D15: الربح قبل المصروفات | E15: =B12 -> 2483848.9
D16: المصروفات الإضافية | E16: =B13 -> 549500
D17: الربح بعد المصروفات | E17: =E15-E16 -> 1934348.9

Sheet INVOICE NO 14
AA3: Affordable House Co.
AA4: CONTRACTORS PAYMENT CERTIFICATE
N7: Interim Advance Payment | AT7: Interim Progress Payment | BZ7: Interim Exchange of Retention
N9: Final Pay and Release of Retention
B11: Contract No. | J11: : | K11: C/AHC/PD/C070/2024 | BF11: Contractor's Payment Certificate No. | CC11: : | CD11: 14
B12: Consultant | J12: : | K12: شركة المسكن الميسر | BS12: Certificate Date | CC12: : | CD12: 46026
B13: Contractor | J13: : | K13: مؤسسة أسس السلامة لأجهزة السلامة | BS13: Valuation Date | CC13: :
B14: Project Title | J14: : | K14: عقد تنفيذ اعمال إنذار ومكافحة الحريق للمباني وغرف المضخات بالمرحلة الاول PHASE 1مجمع سكن العمال (ECODAN) في مدينة الملك سلمان للطاقة
B17: Original Contract Value | AR17: SR | AU17: القيمة الأصلية للعقد | CF17: 6493121.7
AU18: أمر تغيير رقم (1) | CF18: 27918
AU20: قيمة الدفعة المقدمة | CF20: =CF17*0.1 -> 649312.17
B21: Revised Contract Value | AR21: SR | AU21: اجمالي قيمة العقد | CF21: =CF17+CF18 -> 6521039.7
B23: Description | BJ23: Cumulative To Date (SR) | BV23: Cumulative Previous (SR) | CH23: This Payment (SR)
B24: Deserved against Original Contract and Variation Order:
B25: دفعة أولى صرفت مسبقاً | BI25: 0.1 | BJ25: 649312.17 | BV25: 649312.17 | CH25: 0
B26: قيمة الاعمال المنجزة حتى تاريخه | BI26: =BJ26/CF21 -> 0.89523428 | BJ26: =BV26+CH26 -> 5837858.3 | BV26: =summary!I44 -> 4918609.4 | CH26: =summary!J44 -> 919248.94
B27: أمر تغيير رقم (1) | BJ27: 27918 | BV27: 27918
B31: Total Gross Certified | BG31: =BI26+BI25 -> 0.99523428 | BJ31: =SUM(BJ24:BU30) -> 6515088.5 | BV31: =SUM(BV24:CG30) -> 5595839.5 | CH31: =SUM(CH25:CS30) -> 919248.94
B32: Deductions:
B34: On Hold - Best Performance =10% | BJ34: =BV34+CH34 -> 651508.85 | BV34: =BV31*0.1 -> 559583.95 | CH34: =CH31*0.1 -> 91924.894
B35: قيمة غرامة التاخير طبقا للعقد في زون 1 | BJ35: =BV35+CH35 -> 42781.6 | BV35: 42781.6 | CH35: 0
B36: استرداد خصم الاستشاري | BJ36: =BV36+CH36 -> -2037.22 | BV36: -2037.22 | CH36: 0
B38: Total Deductions | BJ38: =SUM(BJ33:BU37) -> 692253.23 | BV38: =SUM(BV33:CG37) -> 600328.33 | CH38: =SUM(CH33:CS37) -> 91924.894
B40: AMOUNT CERTIFIED THIS PAYMENT CERTIFICATE | BJ40: =BJ31-BJ38 -> 5822835.2 | BV40: =BV31-BV38 -> 4995511.2 | CH40: =CH31-CH38 -> 827324.04
B41: مائة وإثنان الفا وخمسمائة وخمسة وتسعون ريالا وست وأربعون هللة لا غير
B44: إقرار: إن المقاول يقر بأن قيمة الأعمال الواردة أعلاه في المستخلص هي كل ما لديه من مستحقات لدى شركة المسكن الميسر حتى تاريخ المستخلص، وعلى هذا يوقع
B46: Submitted by Contractor | R46: : | AD46: (مؤسسة أسس السلامة لأجهزة السلامة) | BJ46: Stamp:
J49: Project Manager
B51: Reviewed by consultant | R51: : | AD51: (مكتب التأثير للاستشارات الهندسية IMPACT) | BJ51: Stamp:
J54: Resident Engineer
B56: Certified for Payment by Project Manager | AB56: : | AD56: (شركة المسكن الميسر Affordable House)
D59: Project Manager/ Client Representative | BI59: Acting / Projects Dept. Director
B61: Approved for Payment by Client | W61: : | AD61: (شركة المسكن الميسر Affordable House)
BI64: Acting/CEO

Sheet summary
A7: PAY ITEM NO. | B7: DESCRIPTION OF ITEM | F7: PREVIOUS PRICE (SR) EXCL. VAT | G7: CURRENT PRICE (SR) EXCL. VAT | H7: EXTENDED PRICE (SR) EXCL. VAT | I7: 90% OF PREVIOUS Amount | J7: 90% OF Current Amount | K7: 90% OF CUMULATIVE (10% ADV. PAYMENT)
A10: JUN-T1 | B10: SUB-TOTAL ITEM NO. B1-21 00 00 | C10: xxx | D10: xxx | E10: xxx | F10: 730383.57 | G10: ='JUN-T1'!J39 -> 29111.882 | H10: =G10+F10 -> 759495.45 | I10: =0.9*F10 -> 657345.21 | J10: =0.9*G10 -> 26200.694 | K10: =0.9*H10 -> 683545.91
A11: JUN-T2 | B11: SUB-TOTAL ITEM NO. B2-21 00 00 | C11: xxx | D11: xxx | E11: xxx | F11: 291679.97 | G11: ='JUN-T2'!J39 -> 6391.33 | H11: =G11+F11 -> 298071.3 | I11: =0.9*F11 -> 262511.97 | J11: =0.9*G11 -> 5752.197 | K11: =0.9*H11 -> 268264.17
A12: SUPRVSR | B12: SUB-TOTAL ITEM NO. B3-21 00 00 | C12: xxx | D12: xxx | E12: xxx | F12: 431679.7 | G12: =SUPERVISOR!J39 -> 15034.399 | H12: =G12+F12 -> 446714.1 | I12: =0.9*F12 -> 388511.73 | J12: =0.9*G12 -> 13530.959 | K12: =0.9*H12 -> 402042.69
A13: SENIOR | B13: SUB-TOTAL ITEM NO. B4-21 00 00 | C13: xxx | D13: xxx | E13: xxx | F13: 475707.15 | G13: =SENIOR!J39 -> 16490.251 | H13: =G13+F13 -> 492197.4 | I13: =0.9*F13 -> 428136.43 | J13: =0.9*G13 -> 14841.226 | K13: =0.9*H13 -> 442977.66
A14: ISOLATED | B14: SUB-TOTAL ITEM NO. B6-21 00 00 | C14: xxx | D14: xxx | E14: xxx | F14: 106713.7 | G14: =ISOLATED!J39 -> 7644.4488 | H14: =G14+F14 -> 114358.15 | I14: =0.9*F14 -> 96042.331 | J14: =0.9*G14 -> 6880.0039 | K14: =0.9*H14 -> 102922.33
A15: ADMIN | B15: SUB-TOTAL ITEM NO. B7-21 00 00 | C15: xxx | D15: xxx | E15: xxx | F15: 131017.9 | G15: =ADMIN!J27 -> 25772.9 | H15: =G15+F15 -> 156790.8 | I15: =0.9*F15 -> 117916.11 | J15: =0.9*G15 -> 23195.61 | K15: =0.9*H15 -> 141111.72
A16: RECREATN | B16: SUB-TOTAL ITEM NO. B8-21 00 00 | C16: xxx | D16: xxx | E16: xxx | F16: 198733.96 | G16: =RECREATION!J41 -> 36418.286 | H16: =G16+F16 -> 235152.25 | I16: =0.9*F16 -> 178860.57 | J16: =0.9*G16 -> 32776.458 | K16: =0.9*H16 -> 211637.02
A17: SERVICE | B17: SUB-TOTAL ITEM NO. B9-21 00 00 | C17: xxx | D17: xxx | E17: xxx | F17: 428538.46 | G17: =SERVICE!J45 -> 307168.39 | H17: =G17+F17 -> 735706.85 | I17: =0.9*F17 -> 385684.61 | J17: =0.9*G17 -> 276451.55 | K17: =0.9*H17 -> 662136.17
A18: PUMP RM-2 | B18: SUB-TOTAL ITEM NO. B12-21 00 00 | C18: xxx | D18: xxx | E18: xxx | F18: 439932.46 | G18: =PUMP02!J48 -> 101885.29 | H18: =G18+F18 -> 541817.75 | I18: =0.9*F18 -> 395939.21 | J18: =0.9*G18 -> 91696.761 | K18: =0.9*H18 -> 487635.98
A19: JUN-T1 - E | B19: SUB-TOTAL ITEM NO. B1-2800 00 | C19: xxx | D19: xxx | E19: xxx | F19: 699685.54 | G19: ='JUN-T1 E'!I36 -> 122738.66 | H19: =G19+F19 -> 822424.2 | I19: =0.9*F19 -> 629716.99 | J19: =0.9*G19 -> 110464.79 | K19: =0.9*H19 -> 740181.78
A20: JUN-T2 - E | B20: SUB-TOTAL ITEM NO. B2-28 00 00 | C20: xxx | D20: xxx | E20: xxx | F20: 191301.46 | G20: ='JUN-T2 E'!I35 -> 26967.94 | H20: =G20+F20 -> 218269.4 | I20: =0.9*F20 -> 172171.31 | J20: =0.9*G20 -> 24271.146 | K20: =0.9*H20 -> 196442.46
A21: SUPRVSR - E | B21: SUB-TOTAL ITEM NO. B3-28 00 00 | C21: xxx | D21: xxx | E21: xxx | F21: 282927.66 | G21: ='SUPERVISOR -E'!I33 -> 62809.44 | H21: =G21+F21 -> 345737.1 | I21: =0.9*F21 -> 254634.89 | J21: =0.9*G21 -> 56528.496 | K21: =0.9*H21 -> 311163.39
A22: SENIOR - E | B22: SUB-TOTAL ITEM NO. B4-28 00 00 | C22: xxx | D22: xxx | E22: xxx | F22: 361496.21 | G22: ='SENIOR - E'!J35 -> 45496.395 | H22: =G22+F22 -> 406992.6 | I22: =0.9*F22 -> 325346.58 | J22: =0.9*G22 -> 40946.756 | K22: =0.9*H22 -> 366293.34
A23: ISOLATED - E | B23: SUB-TOTAL ITEM NO. B6-28 00 00 | C23: xxx | D23: xxx | E23: xxx | F23: 105596.24 | G23: ='ISOLATE - E'!I34 -> -11312.237 | H23: =G23+F23 -> 94284 | I23: =0.9*F23 -> 95036.613 | J23: =0.9*G23 -> -10181.013 | K23: =0.9*H23 -> 84855.6
A24: ADMIN - E | B24: SUB-TOTAL ITEM NO. B7-28 00 00 | C24: xxx | D24: xxx | E24: xxx | F24: 67078.41 | G24: ='ADMIN -E'!J35 -> 79168.49 | H24: =G24+F24 -> 146246.9 | I24: =0.9*F24 -> 60370.569 | J24: =0.9*G24 -> 71251.641 | K24: =0.9*H24 -> 131622.21
A25: RECREATN - E | B25: SUB-TOTAL ITEM NO. B8-28 00 00 | C25: xxx | D25: xxx | E25: xxx | F25: 131764.8 | G25: ='RECREATION - E'!J36 -> 18517.3 | H25: =G25+F25 -> 150282.1 | I25: =0.9*F25 -> 118588.32 | J25: =0.9*G25 -> 16665.57 | K25: =0.9*H25 -> 135253.89
A26: SERVICE - E | B26: SUB-TOTAL ITEM NO. B9-28 00 00 | C26: xxx | D26: xxx | E26: xxx | F26: 187954.48 | G26: ='SERVICE - E'!J36 -> 109690.03 | H26: =G26+F26 -> 297644.5 | I26: =0.9*F26 -> 169159.03 | J26: =0.9*G26 -> 98721.023 | K26: =0.9*H26 -> 267880.05
A27: GUARD RM | B27: SUB-TOTAL ITEM NO. B10-28 00 00 | C27: xxx | D27: xxx | E27: xxx | F27: 27603.775 | G27: ='GUARD RM'!I31 -> 18762.225 | H27: =G27+F27 -> 46366 | I27: =0.9*F27 -> 24843.398 | J27: =0.9*G27 -> 16886.002 | K27: =0.9*H27 -> 41729.4
A28: PUMP RM-1 | B28: SUB-TOTAL ITEM NO. B11-28 00 00 | C28: xxx | D28: xxx | E28: xxx | F28: 0 | G28: ='PUMP RM-1'!K19 -> 2910 | H28: =G28+F28 -> 2910 | I28: =0.9*F28 -> 0 | J28: =0.9*G28 -> 2619 | K28: =0.9*H28 -> 2619
A29: PUMP RM-2 | B29: SUB-TOTAL ITEM NO. B12-28 00 00 | C29: xxx | D29: xxx | E29: xxx | F29: 0 | G29: ='PUMP RM-2'!K22 -> 11640 | H29: =G29+F29 -> 11640 | I29: =0.9*F29 -> 0 | J29: =0.9*G29 -> 10476 | K29: =0.9*H29 -> 10476
A30: PUMP RM-3 | B30: SUB-TOTAL ITEM NO. B13-28 00 00 | C30: xxx | D30: xxx | E30: xxx | F30: 0 | G30: ='PUMP RM-3'!J19 -> 2910 | H30: =G30+F30 -> 2910 | I30: =0.9*F30 -> 0 | J30: =0.9*G30 -> 2619 | K30: =0.9*H30 -> 2619
A31: JUN-T1-EXT | B31: SUB-TOTAL ITEM NO. B1-10 00 00 | C31: xxx | D31: xxx | E31: xxx | F31: 76242 | G31: ='JUN-T1-EXT'!J20 -> 0 | H31: =G31+F31 -> 76242 | I31: =0.9*F31 -> 68617.8 | J31: =0.9*G31 -> 0 | K31: =0.9*H31 -> 68617.8
A32: JUN-T2-EXT | B32: SUB-TOTAL ITEM NO. B2-10 00 00 | C32: xxx | D32: xxx | E32: xxx | F32: 11441.65 | G32: ='JUN-T2-EXT'!J20 -> 4175.85 | H32: =G32+F32 -> 15617.5 | I32: =0.9*F32 -> 10297.485 | J32: =0.9*G32 -> 3758.265 | K32: =0.9*H32 -> 14055.75
A33: SUPERVISOR-EXT | B33: SUB-TOTAL ITEM NO. B3-10 00 00 | C33: xxx | D33: xxx | E33: xxx | F33: 19999.225 | G33: ='SUPERVISOR-EXT '!J20 -> 7670.275 | H33: =G33+F33 -> 27669.5 | I33: =0.9*F33 -> 17999.302 | J33: =0.9*G33 -> 6903.2475 | K33: =0.9*H33 -> 24902.55
A34: SENIOR-EXT | B34: SUB-TOTAL ITEM NO. B4-10 00 00 | C34: xxx | D34: xxx | E34: xxx | F34: 15447 | G34: ='SENIOR-EXT'!J15 -> 2500 | H34: =G34+F34 -> 17947 | I34: =0.9*F34 -> 13902.3 | J34: =0.9*G34 -> 2250 | K34: =0.9*H34 -> 16152.3
A35: ISOLATED-EXT | B35: SUB-TOTAL ITEM NO. B6-10 00 00 | C35: xxx | D35: xxx | E35: xxx | F35: 5322.95 | G35: ='ISOLATED-EXT '!J20 -> 2048.05 | H35: =G35+F35 -> 7371 | I35: =0.9*F35 -> 4790.655 | J35: =0.9*G35 -> 1843.245 | K35: =0.9*H35 -> 6633.9
A36: ADMIN-EXT | B36: SUB-TOTAL ITEM NO. B7-10 00 00 | C36: xxx | D36: xxx | E36: xxx | F36: 2863.8 | G36: ='ADMIN-EXT'!J21 -> 2192.2 | H36: =G36+F36 -> 5056 | I36: =0.9*F36 -> 2577.42 | J36: =0.9*G36 -> 1972.98 | K36: =0.9*H36 -> 4550.4
A37: RECREATION-EXT | B37: SUB-TOTAL ITEM NO. B8-10 00 00 | C37: xxx | D37: xxx | E37: xxx | F37: 10628 | G37: ='RECREATION-EXT'!J17 -> 4285 | H37: =G37+F37 -> 14913 | I37: =0.9*F37 -> 9565.2 | J37: =0.9*G37 -> 3856.5 | K37: =0.9*H37 -> 13421.7
A38: SERVICE-EXT | B38: SUB-TOTAL ITEM NO. B9-10 00 00 | C38: xxx | D38: xxx | E38: xxx | F38: 21367.5 | G38: ='SERVICE-EXT'!J22 -> 14557.5 | H38: =G38+F38 -> 35925 | I38: =0.9*F38 -> 19230.75 | J38: =0.9*G38 -> 13101.75 | K38: =0.9*H38 -> 32332.5
A39: GUARD-RM-EXT | B39: SUB-TOTAL ITEM NO. B10-10 00 00 | C39: xxx | D39: xxx | E39: xxx | F39: 434.2 | G39: ='GUARD-RM-EXT'!J14 -> 196.425 | H39: =G39+F39 -> 630.625 | I39: =0.9*F39 -> 390.78 | J39: =0.9*G39 -> 176.7825 | K39: =0.9*H39 -> 567.5625
A40: PUMP-R1-EXT | B40: SUB-TOTAL ITEM NO. B11-10 00 00 | C40: xxx | D40: xxx | E40: xxx | F40: 5761.925 | G40: ='PUMP-R1-EXT'!J16 -> 10631.2 | H40: =G40+F40 -> 16393.125 | I40: =0.9*F40 -> 5185.7325 | J40: =0.9*G40 -> 9568.08 | K40: =0.9*H40 -> 14753.812
A41: PUMP-R21-EXT | B41: SUB-TOTAL ITEM NO. B12-10 00 00 | C41: xxx | D41: xxx | E41: xxx | F41: 465.725 | G41: ='PUMP-R2-EXT'!J15 -> 196.425 | H41: =G41+F41 -> 662.15 | I41: =0.9*F41 -> 419.1525 | J41: =0.9*G41 -> 176.7825 | K41: =0.9*H41 -> 595.935
A42: PUMP-R3-EXT | B42: SUB-TOTAL ITEM NO. B13-10 00 00 | C42: xxx | D42: xxx | E42: xxx | F42: 5352.1 | G42: ='PUMP-R3-EXT'!J16 -> 2844.525 | H42: =G42+F42 -> 8196.625 | I42: =0.9*F42 -> 4816.89 | J42: =0.9*G42 -> 2560.0725 | K42: =0.9*H42 -> 7376.9625
A43: Variance between the total quantities amount and the contract amount | H43: =-59512.64 -> -59512.64 | J43: =H43 -> -59512.64 | K43: =J43 -> -59512.64
B44: TOTAL ESTIMATED CONTRACT PRICE FOR PAY ITEM NO. B1 | C44: xxx | D44: xxx | E44: xxx | F44: =SUM(F9:F43) -> 5465121.5 | G44: =SUM(G9:G43) -> 1087512.9 | H44: =SUM(H9:H43) -> 6493121.7 | I44: =SUM(I9:I43) -> 4918609.4 | J44: =SUM(J10:J43) -> 919248.94 | K44: =SUM(K9:K43) -> 5837858.3
B46: % of Completion | H46: =H44/6493121.74 -> 1
H49: 6493121.7
H50: =H44-H49 -> -0.0049999999
H52: =H43-H50 -> -59512.635

Sheet JUN-T1 E
B4: JUN T1 E
B5: B O Q | E5: THE ACTUAL QTY | H5: AMOUNT (SR)
A6: DESCRIPTION OF ITEM | B6: ESTIMATED QUANTITY | C6: UNIT | D6: UNIT PRICE(SR) EXCL. VAT | E6: Previous QTY | F6: Current QTY | G6: Cumulative QTY | H6: Previous | I6: Current | J6: Cumulative | K6: Percentage | L6: Actual price | M6: Actual Labour charge | N6: Total AP+LC | O6: Profit
A8: DIVISION 28-ELECTRONIC SAFETY AND SECURITY
A9: Supply and installation of IP Fixed cameras, POE+ TCP/IP and IP Indoor fixed mini dome camera-ceiling mounted, including all accessories, testing, commissioning and configuration of the network and other Works as shown on the Contract drawings and specified in the Contract documents.
A10: Fire Detection and Alarm
A11: Fire alarm control panel (FACP)
A12: Supply, installation, testing and commissioning of a microprocessor based, addressable fire alarm control panel, complete with Chassis, 640-Character backlit LCD display, QWERTY programming and control keypad, loop cards, zone and input/output modules, supervisory devices, auxiliary relays, network capability modules, battery, battery charger, printer, internal alarm, interface contacts and all accessories and hardware as shown on the Contract drawings and specified in the Contract documents and to complete the fully functional, operable, reliable and maintainable fire alarm system.
A13: Microprocessor based, addressable FACP,5 loop type | B13: 12 | C13: Ea | D13: 22795 | E13: 10.8 | F13: =B13-E13 -> 1.2 | G13: =E13+F13 -> 12 | H13: =E13*D13 -> 246186 | I13: =F13*D13 -> 27354 | J13: =H13+I13 -> 273540 | K13: =G13/B13 -> 1 | L13: 16900 | M13: 80 | N13: =B13*(L13+M13) -> 203760 | O13: =J13-N13 -> 69780
A14: Power supply unit, batteries and battery chargers | B14: 12 | C14: Ea | D14: 4365 | E14: 0 | F14: =B14-E14 -> 12 | G14: =E14+F14 -> 12 | H14: =E14*D14 -> 0 | I14: =F14*D14 -> 52380 | J14: =H14+I14 -> 52380 | K14: =G14/B14 -> 1 | L14: 0 | M14: 0 | N14: =B14*(L14+M14) -> 0 | O14: =J14-N14 -> 52380
A15: Supply, selection and calculation, installation, testing and commissioning of FACP power supply unit, batteries for at least 24 hours during the normal operations and 15 mins under emergency full loaded condition. Provide separate combination of power Supply and battery enclosure when large batteries are required and not be able embedded inside FACP panel.
A16: Detection and initiation devices
A17: Supply, installation, testing and commissioning of intelligent, addressable type fire alarm detectors and initiating devices as shown on the Contract drawings and specified in the Contract documents complete with all mounting accessories including boxes, connectors and terminations.
A18: Smoke detector - photoelectric, addressable, self diagnostic, self address | B18: 747 | C18: Ea | D18: 339.5 | E18: 672.3 | F18: =B18-E18 -> 74.7 | G18: =E18+F18 -> 747 | H18: =E18*D18 -> 228245.85 | I18: =F18*D18 -> 25360.65 | J18: =H18+I18 -> 253606.5 | K18: =G18/B18 -> 1 | L18: 120 | M18: 80 | N18: =B18*(L18+M18) -> 149400 | O18: =J18-N18 -> 104206.5
A19: Heat detector - rate of rise type with fix temperature | B19: 36 | C19: Ea | D19: 339.5 | E19: 32.4 | F19: =B19-E19 -> 3.6 | G19: =E19+F19 -> 36 | H19: =E19*D19 -> 10999.8 | I19: =F19*D19 -> 1222.2 | J19: =H19+I19 -> 12222 | K19: =G19/B19 -> 1 | L19: 110 | M19: 80 | N19: =B19*(L19+M19) -> 6840 | O19: =J19-N19 -> 5382
A20: Addressable manual fire alarm pull station | B20: 72 | C20: Ea | D20: 291 | E20: 64.8 | F20: =B20-E20 -> 7.2 | G20: =E20+F20 -> 72 | H20: =E20*D20 -> 18856.8 | I20: =F20*D20 -> 2095.2 | J20: =H20+I20 -> 20952 | K20: =G20/B20 -> 1 | L20: 160 | M20: 80 | N20: =B20*(L20+M20) -> 17280 | O20: =J20-N20 -> 3672
A21: Addressable manual fire alarm pull station, weather proof | B21: 27 | C21: Ea | D21: 368.6 | E21: 24.21 | F21: =B21-E21 -> 2.79 | G21: =E21+F21 -> 27 | H21: =E21*D21 -> 8923.806 | I21: =F21*D21 -> 1028.394 | J21: =H21+I21 -> 9952.2 | K21: =G21/B21 -> 1 | L21: 180 | M21: 80 | N21: =B21*(L21+M21) -> 7020 | O21: =J21-N21 -> 2932.2
A22: Other initiating devices and control devices
A23: Supply, Installation, testing and commissioning of all conventional I/O interfaces devices for interface and Integration with firefighting systems, gas alarm and control systems, lift safety devices, fire water pumps, HVAC systems. elevators and all other specified equipment as per contract drawings and specifications, complete with all mounting accessories including boxes and terminations.
A24: Fire alarm monitoring module (MM) | B24: 24 | C24: Ea | D24: 436.5 | E24: 21.52 | F24: =B24-E24 -> 2.48 | G24: =E24+F24 -> 24 | H24: =E24*D24 -> 9393.48 | I24: =F24*D24 -> 1082.52 | J24: =H24+I24 -> 10476 | K24: =G24/B24 -> 1 | L24: 140 | M24: 80 | N24: =B24*(L24+M24) -> 5280 | O24: =J24-N24 -> 5196
A25: Notification appliances
A26: Supply, installation, testing and commissioning of visual and sound alarm devices as shown on the Contract drawings and specified in the Contract documents complete with all mounting accessories including boxes and terminations.
A27: Bells, indoor with strobe lights / beacons - red body, red lens for fire alarm | B27: 84 | C27: Ea | D27: 388 | E27: 75.6 | F27: =B27-E27 -> 8.4 | G27: =E27+F27 -> 84 | H27: =E27*D27 -> 29332.8 | I27: =F27*D27 -> 3259.2 | J27: =H27+I27 -> 32592 | K27: =G27/B27 -> 1 | L27: 212 | M27: 80 | N27: =B27*(L27+M27) -> 24528 | O27: =J27-N27 -> 8064
A28: Bells, indoor with strobe lights / beacons - red body, red lens for fire alarm, weather proof | B28: 39 | C28: Ea | D28: 436.5 | E28: 34.97 | F28: =B28-E28 -> 4.03 | G28: =E28+F28 -> 39 | H28: =E28*D28 -> 15264.405 | I28: =F28*D28 -> 1759.095 | J28: =H28+I28 -> 17023.5 | K28: =G28/B28 -> 1 | L28: 250 | M28: 80 | N28: =B28*(L28+M28) -> 12870 | O28: =J28-N28 -> 4153.5
A29: Fire alarm cables - fire resistant cable, 300V/500V, red sheath with low emission of smoke, halogen free, thermoplastic material
A30: To include for the procurement, supply, factory testing, delivery to Site, installation, testing and commissioning of the cables, termination materials and all cable support and wiring, identification accessories.
A31: 2C x 2.5 mm², Stranded plain copper wire or solid conductor, overall shield with drain wire for SLC loop | B31: 3915 | C31: m | D31: 24.25 | E31: 3706.2 | F31: =B31-E31 -> 208.8 | G31: =E31+F31 -> 3915 | H31: =E31*D31 -> 89875.35 | I31: =F31*D31 -> 5063.4 | J31: =H31+I31 -> 94938.75 | K31: =G31/B31 -> 1 | L31: 8 | M31: 0 | N31: =B31*(L31+M31) -> 31320 | O31: =J31-N31 -> 63618.75
A32: 2C x 2.5 mm², Stranded plain copper wire or solid conductor, overall shield with drain wire for NAC Loop | B32: 1845 | C32: m | D32: 24.25 | E32: 1757 | F32: =B32-E32 -> 88 | G32: =E32+F32 -> 1845 | H32: =E32*D32 -> 42607.25 | I32: =F32*D32 -> 2134 | J32: =H32+I32 -> 44741.25 | K32: =G32/B32 -> 1 | L32: 8 | M32: 0 | N32: =B32*(L32+M32) -> 14760 | O32: =J32-N32 -> 29981.25
A33: Fire alarm cable conduit, all JB boxes, fittings and accessories for cable installations
A34: To include for the procurement, supply, installation of PVC conduits and flexible metallic conduits for fire cables, junction boxes, fittings, accessories and all other relevant items or Works to complete fully Fire alarm detection system installations.
A35: 20 mm diameter, PVC conduits | B35: 0 | C35: m | D35: 24.25 | E35: 0 | F35: =(B35*(0.4+0.125)) -> 0 | G35: =E35+F35 -> 0 | H35: =E35*D35 -> 0 | I35: =F35*D35 -> 0 | J35: =H35+I35 -> 0 | N35: =B35*(L35+M35) -> 0 | O35: =J35-N35 -> 0
A36: SUB-TOTAL ITEM NO. B1-28 00 00 | B36: xxx | C36: xxx | H36: =SUM(H13:H35) -> 699685.54 | I36: =SUM(I13:I35) -> 122738.66 | J36: =SUM(J12:J35) -> 822424.2 | N36: =SUM(N12:N35) -> 473058 | O36: =SUM(O12:O35) -> 349366.2
A37: (TO BE CARRIED TO COMPOSITE SUMMARY)
A39: OWNER | B39: CONSULTANT | H39: CONTRACTOR

Sheet JUN-T1-EXT
C5: JUN-T1
A6: SECTION 2- SCHEDULE OF QUANTITIES AND PRICES | C6: B O Q | F6: THE ACTUAL QTY | I6: AMOUNT (SR) | L6: Percentage
A7: PAY ITEM NO. | B7: DESCRIPTION OF ITEM | C7: ESTIMATED QUANTITY | D7: UNIT | E7: UNIT PRICE(SR) EXCL. VAT | F7: Previous QTY | G7: Current QTY | H7: Cumulative QTY | I7: Previous | J7: Current | K7: Cumulative | M7: Actual price | N7: Actual Labour charge | O7: Total AP+LC | P7: Profit
B8: DIVISION 10 - SPECIALTIES
A9: 1.0 | B9: Fire Extinguishers
B10: Includes mounting brackets, fasteners, service tags, fully charged and ready to use extinguishers.
A11: a. | B11: Multipurpose dry chemical type, UL rated ABC
A12: a.1 | B12: FE-1, 6 kg, multi purpose fire extinguisher | C12: 96 | D12: Ea | E12: 242.5 | F12: 96 | G12: 0 | H12: =F12+G12 -> 96 | I12: =E12*F12 -> 23280 | J12: =G12*E12 -> 0 | K12: =I12+J12 -> 23280 | L12: =H12/C12 -> 1 | M12: 240 | N12: 10 | O12: =C12*(M12+N12) -> 24000 | P12: =K12-O12 -> -720
A13: b. | B13: Wet chemical type, UL rated class K
A14: b.1 | B14: FE-3, kitchen type-K fire extinguisher 2 gallon | C14: 36 | D14: Ea | E14: 533.5 | F14: 36 | G14: 0 | H14: =F14+G14 -> 36 | I14: =E14*F14 -> 19206 | J14: =G14*E14 -> 0 | K14: =I14+J14 -> 19206 | L14: =H14/C14 -> 1 | M14: 320 | N14: 10 | O14: =C14*(M14+N14) -> 11880 | P14: =K14-O14 -> 7326
A15: c. | B15: Automatic fire extinguisher
A16: c.1 | B16: FE-2, 12 kg, multi purpose fire extinguisher, ceiling mounted | C16: 48 | D16: Ea | E16: 485 | F16: 48 | G16: 0 | H16: =F16+G16 -> 48 | I16: =E16*F16 -> 23280 | J16: =G16*E16 -> 0 | K16: =I16+J16 -> 23280 | L16: =H16/C16 -> 1 | M16: 304 | N16: 10 | O16: =C16*(M16+N16) -> 15072 | P16: =K16-O16 -> 8208
A17: d. | B17: Fire blanket
B18: Supply and installation of fire blanket of specified type to be located in kitchen with all fittings and supports required to provide satisfactory operation.
A19: d.1 | B19: Fire blanket, standard size (1.2 meter x 1.2 meter), NFPA approved | C19: 36 | D19: Ea | E19: 291 | F19: 36 | G19: 0 | H19: =F19+G19 -> 36 | I19: =E19*F19 -> 10476 | J19: =G19*E19 -> 0 | K19: =I19+J19 -> 10476 | L19: =H19/C19 -> 1 | M19: 16 | N19: 10 | O19: =C19*(M19+N19) -> 936 | P19: =K19-O19 -> 9540
B20: SUB-TOTAL ITEM NO. B1-10 00 00 | C20: xxx | D20: xxx | I20: =SUM(I9:I19) -> 76242 | J20: =SUM(J9:J19) -> 0 | K20: =SUM(K9:K19) -> 76242 | O20: =SUM(O9:O19) -> 51888 | P20: =SUM(P9:P19) -> 24354

Sheet JUN-T1
C3: JUN T1
A4: SECTION 2- SCHEDULE OF QUANTITIES AND PRICES | C4: B O Q | F4: THE ACTUAL QTY | I4: AMOUNT (SR) | L4: Percentage
A5: PAY ITEM NO. | B5: DESCRIPTION OF ITEM | C5: ESTIMATED QUANTITY | D5: UNIT | E5: UNIT PRICE(SR) EXCL. VAT | F5: Previous QTY | G5: Current QTY | H5: Cumulative QTY | I5: Previous | J5: Current | K5: Cumulative | M5: Actual price | N5: accessories | O5: Actual Labour charge | P5: Total AP+LC | Q5: Profit
B6: DIVISION 21 - FIRE SUPPRESSION
A7: 1.0 | B7: General-Duty Valves for Water-Based Fire-Suppression Piping
B8: Supply and installation of valves including all fixings, supports, all other accessories and associated Works.
A9: a. | B9: Gate valve, UL and FM global approved
A10: a.1 | B10: 150 mm diameter | C10: 6 | D10: Ea | E10: 3686 | F10: 5.2 | G10: =C10-F10 -> 0.8 | H10: =F10+G10 -> 6 | I10: =E10*F10 -> 19167.2 | J10: =G10*E10 -> 2948.8 | K10: =I10+J10 -> 22116 | L10: =H10/C10 -> 1 | M10: 1250 | N10: 100 | O10: 300 | P10: =C10*(M10+N10+O10) -> 9900 | Q10: =K10-P10 -> 12216
A11: b. | B11: Alarm check valve, UL and FM global approved
A12: b.1 | B12: 150 mm diameter | C12: 3 | D12: Ea | E12: 5577.5 | F12: 2.3 | G12: =C12-F12 -> 0.7 | H12: =F12+G12 -> 3 | I12: =E12*F12 -> 12828.25 | J12: =G12*E12 -> 3904.25 | K12: =I12+J12 -> 16732.5 | L12: =H12/C12 -> 1 | M12: 3830 | N12: 200 | O12: 100 | P12: =C12*(M12+N12+O12) -> 12390 | Q12: =K12-P12 -> 4342.5
A13: c. | B13: Zone control valve assembly
A14: c.1 | B14: 100 mm diameter | C14: 9 | D14: Ea | E14: 5626 | F14: 7.8 | G14: =C14-F14 -> 1.2 | H14: =F14+G14 -> 9 | I14: =E14*F14 -> 43882.8 | J14: =G14*E14 -> 6751.2 | K14: =I14+J14 -> 50634 | L14: =H14/C14 -> 1 | M14: 3000 | N14: 150 | O14: 100 | P14: =C14*(M14+N14+O14) -> 29250 | Q14: =K14-P14 -> 21384
A15: 2.0 | B15: Fire-Department Connections
B16: Two way, swivel fittings, Dust caps and chains of same material as body, chrome plated finish and threads to match local fire department hardware
A17: a. | B17: Flush wall mounted fire department connection with check valve
A18: a.1 | B18: Two-way swivel fittings, 65 x 65 x 100 mm single clapper Siamese-type connections | C18: 3 | D18: Ea | E18: 4462 | F18: 1.95 | G18: =C18-F18 -> 1.05 | H18: =F18+G18 -> 3 | I18: =E18*F18 -> 8700.9 | J18: =G18*E18 -> 4685.1 | K18: =I18+J18 -> 13386 | L18: =H18/C18 -> 1 | M18: 450 | N18: 150 | O18: 100 | P18: =C18*(M18+N18+O18) -> 2100 | Q18: =K18-P18 -> 11286
A19: 3.0 | B19: Wet-Pipe Sprinkler Systems
A20: a. | B20: Black steel fire water pipes
B21: Supply and installation of black steel pipe seamless type as per ASTM A53 including supports, hangers, fixing, fitting, all other accessories and associated Works as per Contract drawings and specifications.
A22: a.1 | B22: 25 mm diameter | C22: 2550 | D22: m | E22: 53.35 | F22: 2550 | G22: =C22-F22 -> 0 | H22: =F22+G22 -> 2550 | I22: =E22*F22 -> 136042.5 | J22: =G22*E22 -> 0 | K22: =I22+J22 -> 136042.5 | L22: =(H22/C22) -> 1 | M22: 15 | N22: 7.5 | O22: 0 | P22: =C22*(M22+N22+O22) -> 57375 | Q22: =K22-P22 -> 78667.5
A23: a.2 | B23: 32 mm diameter | C23: 375 | D23: m | E23: 63.05 | F23: 375 | G23: =C23-F23 -> 0 | H23: =F23+G23 -> 375 | I23: =E23*F23 -> 23643.75 | J23: =G23*E23 -> 0 | K23: =I23+J23 -> 23643.75 | L23: =(H23/C23) -> 1 | M23: 20 | N23: 10 | O23: 0 | P23: =C23*(M23+N23+O23) -> 11250 | Q23: =K23-P23 -> 12393.75
A24: a.3 | B24: 40 mm diameter | C24: 276 | D24: m | E24: 77.6 | F24: 276 | G24: =C24-F24 -> 0 | H24: =F24+G24 -> 276 | I24: =E24*F24 -> 21417.6 | J24: =G24*E24 -> 0 | K24: =I24+J24 -> 21417.6 | L24: =(H24/C24) -> 1 | M24: 24 | N24: 12 | O24: 0 | P24: =C24*(M24+N24+O24) -> 9936 | Q24: =K24-P24 -> 11481.6
A25: a.4 | B25: 50 mm diameter | C25: 90 | D25: m | E25: 95.06 | F25: 90 | G25: =C25-F25 -> 0 | H25: =F25+G25 -> 90 | I25: =E25*F25 -> 8555.4 | J25: =G25*E25 -> 0 | K25: =I25+J25 -> 8555.4 | L25: =(H25/C25) -> 1 | M25: 28 | N25: 14 | O25: 0 | P25: =C25*(M25+N25+O25) -> 3780 | Q25: =K25-P25 -> 4775.4
A26: a.5 | B26: 65 mm diameter | C26: 30 | D26: m | E26: 169.75 | F26: 30 | G26: =C26-F26 -> 0 | H26: =F26+G26 -> 30 | I26: =E26*F26 -> 5092.5 | J26: =G26*E26 -> 0 | K26: =I26+J26 -> 5092.5 | L26: =(H26/C26) -> 1 | M26: 30 | N26: 15 | O26: 0 | P26: =C26*(M26+N26+O26) -> 1350 | Q26: =K26-P26 -> 3742.5
A27: a.6 | B27: 80 mm diameter | C27: 30 | D27: m | E27: 190.12 | F27: 30 | G27: =C27-F27 -> 0 | H27: =F27+G27 -> 30 | I27: =E27*F27 -> 5703.6 | J27: =G27*E27 -> 0 | K27: =I27+J27 -> 5703.6 | L27: =(H27/C27) -> 1 | M27: 35 | N27: 25 | O27: 0 | P27: =C27*(M27+N27+O27) -> 1800 | Q27: =K27-P27 -> 3903.6
A28: a.7 | B28: 100 mm diameter | C28: 450 | D28: m | E28: 237.65 | F28: 450 | G28: =C28-F28 -> 0 | H28: =F28+G28 -> 450 | I28: =E28*F28 -> 106942.5 | J28: =G28*E28 -> 0 | K28: =I28+J28 -> 106942.5 | L28: =(H28/C28) -> 1 | M28: 90 | N28: 60 | O28: 0 | P28: =C28*(M28+N28+O28) -> 67500 | Q28: =K28-P28 -> 39442.5
A29: a.8 | B29: 150 mm diameter | C29: 120 | D29: m | E29: 344.35 | F29: 120 | G29: =C29-F29 -> 0 | H29: =F29+G29 -> 120 | I29: =E29*F29 -> 41322 | J29: =G29*E29 -> 0 | K29: =I29+J29 -> 41322 | L29: =(H29/C29) -> 1 | M29: 170 | N29: 90 | O29: 0 | P29: =C29*(M29+N29+O29) -> 31200 | Q29: =K29-P29 -> 10122
A30: b. | B30: Fire water sprinkler head
B31: Sprinkler Head, UL listed FM approved, chrome-plated, bronze and factory painted; Shall be of one manufacturer. (No mixing of sprinkler brands shall be permitted).
A32: b.1 | B32: Pendent type | C32: 750 | D32: Ea | E32: 63.05 | F32: 651.95 | G32: =C32-F32 -> 98.05 | H32: =F32+G32 -> 750 | I32: =E32*F32 -> 41105.448 | J32: =G32*E32 -> 6182.0525 | K32: =I32+J32 -> 47287.5 | L32: =H32/C32 -> 1 | M32: 25 | N32: 5 | O32: 100 | P32: =C32*(M32+N32+O32) -> 97500 | Q32: =K32-P32 -> -50212.5
A33: b.2 | B33: Upright type | C33: 48 | D33: Ea | E33: 33.95 | F33: 41.6 | G33: =C33-F33 -> 6.4 | H33: =F33+G33 -> 48 | I33: =E33*F33 -> 1412.32 | J33: =G33*E33 -> 217.28 | K33: =I33+J33 -> 1629.6 | L33: =H33/C33 -> 1 | M33: 19 | N33: 5 | O33: 100 | P33: =C33*(M33+N33+O33) -> 5952 | Q33: =K33-P33 -> -4322.4
A34: b.3 | B34: Wall side type | C34: 456 | D34: Ea | E34: 72.75 | F34: 395.2 | G34: =C34-F34 -> 60.8 | H34: =F34+G34 -> 456 | I34: =E34*F34 -> 28750.8 | J34: =G34*E34 -> 4423.2 | K34: =I34+J34 -> 33174 | L34: =H34/C34 -> 1 | M34: 59 | N34: 5 | O34: 100 | P34: =C34*(M34+N34+O34) -> 74784 | Q34: =K34-P34 -> -41610
A35: 4.0 | B35: Fire-Suppression Standpipes
A36: a. | B36: Fire Hose Cabinet
B37: Supply and installation of Surface mounted fire hose Cabinets Made of Stainless Steel, dimension (W 750 x H 850 x D 180). with Synthetic Single Jacket Hose 1.5” x 30 meter long and (1) multipurpose dry powder Extinguisher include fittings, joints, unions, dielectric fittings, flanges, gaskets, grooved mechanical couplings, nuts and bolts, hangers and supports and labelling.
A38: a.1 | B38: FHC-II | C38: 48 | D38: Ea | E38: 4704.5 | F38: 48 | G38: 0 | H38: =F38+G38 -> 48 | I38: =E38*F38 -> 225816 | J38: =G38*E38 -> 0 | K38: =I38+J38 -> 225816 | L38: =H38/C38 -> 1 | M38: 4200 | N38: 250 | O38: 400 | P38: =C38*(M38+N38+O38) -> 232800 | Q38: =K38-P38 -> -6984
B39: SUB-TOTAL ITEM NO. B1-21 00 00 | C39: xxx | D39: xxx | I39: =SUM(I9:I38) -> 730383.57 | J39: =SUM(J9:J38) -> 29111.882 | K39: =SUM(K9:K38) -> 759495.45 | P39: =SUM(P9:P38) -> 648867 | Q39: =SUM(Q9:Q38) -> 110628.45
B40: (TO BE CARRIED TO COMPOSITE SUMMARY)
B42: OWNER | C42: CONSULTANT | I42: CONTRACTOR

Sheet JUN-T2 E
B3: JUN T2 - E
B4: B O Q | E4: THE ACTUAL QTY | H4: AMOUNT (SR)
A5: DESCRIPTION OF ITEM | B5: ESTIMATED QUANTITY | C5: UNIT | D5: UNIT PRICE(SR) EXCL. VAT | E5: Previous QTY | F5: Current QTY | G5: Cumulative QTY | H5: Previous | I5: Current | J5: Cumulative | K5: Percentage | L5: Actual price | M5: Actual Labour charge | N5: Total AP+LC | O5: Profit
A7: DIVISION 28-ELECTRONIC SAFETY AND SECURITY
A8: Supply and installation of IP Fixed cameras, POE+ TCP/IP and IP Indoor fixed mini dome camera-ceiling mounted, including all accessories, testing, commissioning and configuration of the network and other Works as shown on the Contract drawings and specified in the Contract documents.
A9: Fire Detection and Alarm
A10: Fire alarm control panel (FACP)
A11: Supply, installation, testing and commissioning of a microprocessor based, addressable fire alarm control panel, complete with Chassis, 640-Character backlit LCD display, QWERTY programming and control keypad, loop cards, zone and input/output modules, supervisory devices, auxiliary relays, network capability modules, battery, battery charger, printer, internal alarm, interface contacts and all accessories and hardware as shown on the Contract drawings and specified in the Contract documents and to complete the fully functional, operable, reliable and maintainable fire alarm system.
A12: Microprocessor based, addressable FACP,5 loop type | B12: 2 | C12: Ea | D12: 22795 | E12: 1.8 | F12: =B12-E12 -> 0.2 | G12: =E12+F12 -> 2 | H12: =D12*E12 -> 41031 | I12: =D12*F12 -> 4559 | J12: =H12+I12 -> 45590 | K12: =G12/B12 -> 1 | L12: 16900 | M12: 80 | N12: =B12*(L12+M12) -> 33960 | O12: =J12-N12 -> 11630
A13: Power supply unit, batteries and battery chargers | B13: 2 | C13: Ea | D13: 4365 | E13: 0 | F13: =B13-E13 -> 2 | G13: =E13+F13 -> 2 | H13: =D13*E13 -> 0 | I13: =D13*F13 -> 8730 | J13: =H13+I13 -> 8730 | K13: =G13/B13 -> 1 | L13: 0 | M13: 0 | N13: =B13*(L13+M13) -> 0 | O13: =J13-N13 -> 8730
A14: Supply, selection and calculation, installation, testing and commissioning of FACP power supply unit, batteries for at least 24 hours during the normal operations and 15 mins under emergency full loaded condition. Provide separate combination of power Supply and battery enclosure when large batteries are required and not be able embedded inside FACP panel.
A15: Detection and initiation devices
A16: Supply, installation, testing and commissioning of intelligent, addressable type fire alarm detectors and initiating devices as shown on the Contract drawings and specified in the Contract documents complete with all mounting accessories including boxes, connectors and terminations.
A17: Smoke detector - photoelectric, addressable, self diagnostic, self address | B17: 244 | C17: Ea | D17: 339.5 | E17: 219.6 | F17: =B17-E17 -> 24.4 | G17: =E17+F17 -> 244 | H17: =D17*E17 -> 74554.2 | I17: =D17*F17 -> 8283.8 | J17: =H17+I17 -> 82838 | K17: =G17/B17 -> 1 | L17: 120 | M17: 80 | N17: =B17*(L17+M17) -> 48800 | O17: =J17-N17 -> 34038
A18: Heat detector - rate of rise type with fix temperature | B18: 6 | C18: Ea | D18: 339.5 | E18: 5.4 | F18: =B18-E18 -> 0.6 | G18: =E18+F18 -> 6 | H18: =D18*E18 -> 1833.3 | I18: =D18*F18 -> 203.7 | J18: =H18+I18 -> 2037 | K18: =G18/B18 -> 1 | L18: 110 | M18: 80 | N18: =B18*(L18+M18) -> 1140 | O18: =J18-N18 -> 897
A19: Addressable manual fire alarm pull station | B19: 12 | C19: Ea | D19: 291 | E19: 10.8 | F19: =B19-E19 -> 1.2 | G19: =E19+F19 -> 12 | H19: =D19*E19 -> 3142.8 | I19: =D19*F19 -> 349.2 | J19: =H19+I19 -> 3492 | K19: =G19/B19 -> 1 | L19: 160 | M19: 80 | N19: =B19*(L19+M19) -> 2880 | O19: =J19-N19 -> 612
A20: Addressable manual fire alarm pull station, weather proof | B20: 4 | C20: Ea | D20: 368.6 | E20: 3.6 | F20: =B20-E20 -> 0.4 | G20: =E20+F20 -> 4 | H20: =D20*E20 -> 1326.96 | I20: =D20*F20 -> 147.44 | J20: =H20+I20 -> 1474.4 | K20: =G20/B20 -> 1 | L20: 180 | M20: 80 | N20: =B20*(L20+M20) -> 1040 | O20: =J20-N20 -> 434.4
A21: Other initiating devices and control devices | F21: =B21-E21 -> 0
A22: Supply, Installation, testing and commissioning of all conventional I/O interfaces devices for interface and Integration with firefighting systems, gas alarm and control systems, lift safety devices, fire water pumps, HVAC systems. elevators and all other specified equipment as per contract drawings and specifications, complete with all mounting accessories including boxes and terminations. | F22: =B22-E22 -> 0
A23: Fire alarm monitoring module (MM) | B23: 16 | C23: Ea | D23: 436.5 | E23: 14.4 | F23: =B23-E23 -> 1.6 | G23: =E23+F23 -> 16 | H23: =D23*E23 -> 6285.6 | I23: =D23*F23 -> 698.4 | J23: =H23+I23 -> 6984 | K23: =G23/B23 -> 1 | L23: 140 | M23: 80 | N23: =B23*(L23+M23) -> 3520 | O23: =J23-N23 -> 3464
A24: Notification appliances | F24: =B24-E24 -> 0
A25: Supply, installation, testing and commissioning of visual and sound alarm devices as shown on the Contract drawings and specified in the Contract documents complete with all mounting accessories including boxes and terminations. | F25: =B25-E25 -> 0
A26: Bells, indoor with strobe lights / beacons - red body, red lens for fire alarm | B26: 14 | C26: Ea | D26: 388 | E26: 12.6 | F26: =B26-E26 -> 1.4 | G26: =E26+F26 -> 14 | H26: =D26*E26 -> 4888.8 | I26: =D26*F26 -> 543.2 | J26: =H26+I26 -> 5432 | K26: =G26/B26 -> 1 | L26: 212 | M26: 80 | N26: =B26*(L26+M26) -> 4088 | O26: =J26-N26 -> 1344
A27: Bells, indoor with strobe lights / beacons - red body, red lens for fire alarm, weather proof | B27: 8 | C27: Ea | D27: 436.5 | E27: 7.2 | F27: =B27-E27 -> 0.8 | G27: =E27+F27 -> 8 | H27: =D27*E27 -> 3142.8 | I27: =D27*F27 -> 349.2 | J27: =H27+I27 -> 3492 | K27: =G27/B27 -> 1 | L27: 250 | M27: 80 | N27: =B27*(L27+M27) -> 2640 | O27: =J27-N27 -> 852
A28: Fire alarm cables - fire resistant cable, 300V/500V, red sheath with low emission of smoke, halogen free, thermoplastic material | F28: =B28-E28 -> 0
A29: To include for the procurement, supply, factory testing, delivery to Site, installation, testing and commissioning of the cables, termination materials and all cable support and wiring, identification accessories. | F29: =B29-E29 -> 0
A30: 2C x 2.5 mm², Stranded plain copper wire or solid conductor, overall shield with drain wire for SLC loop | B30: 1600 | C30: m | D30: 24.25 | E30: 1514.6667 | F30: =B30-E30 -> 85.333333 | G30: =E30+F30 -> 1600 | H30: =D30*E30 -> 36730.667 | I30: =D30*F30 -> 2069.3333 | J30: =H30+I30 -> 38800 | K30: =G30/B30 -> 1 | L30: 8 | M30: 0 | N30: =B30*(L30+M30) -> 12800 | O30: =J30-N30 -> 26000
A31: 2C x 2.5 mm², Stranded plain copper wire or solid conductor, overall shield with drain wire for NAC Loop | B31: 800 | C31: m | D31: 24.25 | E31: 757.33333 | F31: =B31-E31 -> 42.666667 | G31: =E31+F31 -> 800 | H31: =D31*E31 -> 18365.333 | I31: =D31*F31 -> 1034.6667 | J31: =H31+I31 -> 19400 | K31: =G31/B31 -> 1 | L31: 8 | M31: 0 | N31: =B31*(L31+M31) -> 6400 | O31: =J31-N31 -> 13000
A32: Fire alarm cable conduit, all JB boxes, fittings and accessories for cable installations
A33: To include for the procurement, supply, installation of PVC conduits and flexible metallic conduits for fire cables, junction boxes, fittings, accessories and all other relevant items or Works to complete fully Fire alarm detection system installations.
A34: 20 mm diameter, PVC conduits | B34: 0 | C34: m | D34: 24.25 | E34: 0 | F34: 0 | G34: =E34+F34 -> 0 | H34: =D34*E34 -> 0 | I34: =D34*F34 -> 0 | N34: =B34*(L34+M34) -> 0 | O34: =J34-N34 -> 0
A35: SUB-TOTAL ITEM NO. B1-28 00 00 | B35: xxx | C35: xxx | H35: =SUM(H12:H34) -> 191301.46 | I35: =SUM(I12:I34) -> 26967.94 | J35: =SUM(J12:J34) -> 218269.4 | N35: =SUM(N11:N34) -> 117268 | O35: =SUM(O11:O34) -> 101001.4
A36: (TO BE CARRIED TO COMPOSITE SUMMARY)
A38: OWNER | B38: CONSULTANT | H38: CONTRACTOR

Sheet JUN-T2-EXT
C5: JUN-T2
A6: SECTION 2- SCHEDULE OF QUANTITIES AND PRICES | C6: B O Q | F6: THE ACTUAL QTY | I6: AMOUNT (SR) | L6: Percentage
A7: PAY ITEM NO. | B7: DESCRIPTION OF ITEM | C7: ESTIMATED QUANTITY | D7: UNIT | E7: UNIT PRICE(SR) EXCL. VAT | F7: Previous QTY | G7: Current QTY | H7: Cumulative QTY | I7: Previous | J7: Current | K7: Cumulative | M7: Actual price | N7: Actual Labour charge | O7: Total AP+LC | P7: Profit
B8: DIVISION 10 - SPECIALTIES
A9: 1.0 | B9: Fire Extinguishers
B10: Includes mounting brackets, fasteners, service tags, fully charged and ready to use extinguishers.
A11: a. | B11: Multipurpose dry chemical type, UL rated ABC
A12: a.1 | B12: FE-1, 6 kg, multi purpose fire extinguisher | C12: 28 | D12: Ea | E12: 242.5 | F12: 21 | G12: =C12-F12 -> 7 | H12: =F12+G12 -> 28 | I12: =E12*F12 -> 5092.5 | J12: =G12*E12 -> 1697.5 | K12: =I12+J12 -> 6790 | L12: =H12/C12 -> 1 | M12: 240 | N12: 10 | O12: =C12*(M12+N12) -> 7000 | P12: =K12-O12 -> -210
A13: b. | B13: Wet chemical type, UL rated class K
A14: b.1 | B14: FE-3, kitchen type-K fire extinguisher 2 gallon | C14: 6 | D14: Ea | E14: 533.5 | F14: 3.9 | G14: =C14-F14 -> 2.1 | H14: =F14+G14 -> 6 | I14: =E14*F14 -> 2080.65 | J14: =G14*E14 -> 1120.35 | K14: =I14+J14 -> 3201 | L14: =H14/C14 -> 1 | M14: 320 | N14: 10 | O14: =C14*(M14+N14) -> 1980 | P14: =K14-O14 -> 1221
A15: c. | B15: Automatic fire extinguisher
A16: c.1 | B16: FE-2, 12 kg, multi purpose fire extinguisher, ceiling mounted | C16: 8 | D16: Ea | E16: 485 | F16: 5.2 | G16: =C16-F16 -> 2.8 | H16: =F16+G16 -> 8 | I16: =E16*F16 -> 2522 | J16: =G16*E16 -> 1358 | K16: =I16+J16 -> 3880 | L16: =H16/C16 -> 1 | M16: 304 | N16: 10 | O16: =C16*(M16+N16) -> 2512 | P16: =K16-O16 -> 1368
A17: d. | B17: Fire blanket
B18: Supply and installation of fire blanket of specified type to be located in kitchen with all fittings and supports required to provide satisfactory operation.
A19: d.1 | B19: Fire blanket, standard size (1.2 meter x 1.2 meter), NFPA approved | C19: 6 | D19: Ea | E19: 291 | F19: 6 | G19: =C19-F19 -> 0 | H19: =F19+G19 -> 6 | I19: =E19*F19 -> 1746 | J19: =G19*E19 -> 0 | K19: =I19+J19 -> 1746 | L19: =H19/C19 -> 1 | M19: 16 | N19: 10 | O19: =C19*(M19+N19) -> 156 | P19: =K19-O19 -> 1590
B20: SUB-TOTAL ITEM NO. B2-10 00 00 | C20: xxx | D20: xxx | I20: =SUM(I9:I19) -> 11441.15 | J20: =SUM(J9:J19) -> 4175.85 | K20: =SUM(K9:K19) -> 15617 | O20: =SUM(O9:O19) -> 11648 | P20: =SUM(P9:P19) -> 3969

Sheet JUN-T2
C3: JUN-T2
A4: SECTION 2- SCHEDULE OF QUANTITIES AND PRICES | C4: B O Q | F4: THE ACTUAL QTY | I4: AMOUNT (SR)
A5: PAY ITEM NO. | B5: DESCRIPTION OF ITEM | C5: ESTIMATED QUANTITY | D5: UNIT | E5: UNIT PRICE(SR) EXCL. VAT | F5: Previous QTY | G5: Current QTY | H5: Cumulative QTY | I5: Previous | J5: Current | K5: Cumulative | L5: Percentage | M5: Actual price | N5: accessories | O5: Actual Labour charge | P5: Total AP+LC | Q5: Profit
B6: DIVISION 21 - FIRE SUPPRESSION
A7: 1.0 | B7: General-Duty Valves for Water-Based Fire-Suppression Piping
B8: Supply and installation of valves including all fixings, supports, all other accessories and associated Works.
A9: a. | B9: Gate valve, UL and FM global approved
A10: a.1 | B10: 150 mm diameter | C10: 4 | D10: Ea | E10: 3686 | F10: 3.6 | G10: =C10-F10 -> 0.4 | H10: =F10+G10 -> 4 | I10: =E10*F10 -> 13269.6 | J10: =G10*E10 -> 1474.4 | K10: =I10+J10 -> 14744 | L10: =H10/C10 -> 1 | M10: 1250 | N10: 100 | O10: 300 | P10: =C10*(M10+N10+O10) -> 6600 | Q10: =K10-P10 -> 8144
A11: b. | B11: Alarm check valve, UL and FM global approved
A12: b.1 | B12: 150 mm diameter | C12: 2 | D12: Ea | E12: 5577.5 | F12: 1.8 | G12: =C12-F12 -> 0.2 | H12: =F12+G12 -> 2 | I12: =E12*F12 -> 10039.5 | J12: =G12*E12 -> 1115.5 | K12: =I12+J12 -> 11155 | L12: =H12/C12 -> 1 | M12: 3830 | N12: 200 | O12: 100 | P12: =C12*(M12+N12+O12) -> 8260 | Q12: =K12-P12 -> 2895
A13: c. | B13: Zone control valve assembly | G13: =C13-F13 -> 0
A14: c.1 | B14: 100 mm diameter | C14: 12 | D14: Ea | E14: 5626 | F14: 11.97 | G14: =C14-F14 -> 0.03 | H14: =F14+G14 -> 12 | I14: =E14*F14 -> 67343.22 | J14: =G14*E14 -> 168.78 | K14: =I14+J14 -> 67512 | L14: =H14/C14 -> 1 | M14: 3000 | N14: 150 | O14: 100 | P14: =C14*(M14+N14+O14) -> 39000 | Q14: =K14-P14 -> 28512
A15: 2.0 | B15: Fire-Department Connections | G15: =C15-F15 -> 0
B16: Two way, swivel fittings, Dust caps and chains of same material as body, chrome plated finish and threads to match local fire department hardware | G16: =C16-F16 -> 0
A17: a. | B17: Flush wall mounted fire department connection with check valve | G17: =C17-F17 -> 0
A18: a.1 | B18: Two-way swivel fittings, 65 x 65 x 100 mm single clapper Siamese-type connections | C18: 2 | D18: Ea | E18: 4462 | F18: 1.8 | G18: =C18-F18 -> 0.2 | H18: =F18+G18 -> 2 | I18: =E18*F18 -> 8031.6 | J18: =G18*E18 -> 892.4 | K18: =I18+J18 -> 8924 | L18: =H18/C18 -> 1 | M18: 450 | N18: 150 | O18: 100 | P18: =C18*(M18+N18+O18) -> 1400 | Q18: =K18-P18 -> 7524
A19: 3.0 | B19: Wet-Pipe Sprinkler Systems | G19: =C19-F19 -> 0
A20: a. | B20: Black steel fire water pipes | G20: =C20-F20 -> 0
B21: Supply and installation of black steel pipe seamless type as per ASTM A53 including supports, hangers, fixing, fitting, all other accessories and associated Works as per Contract drawings and specifications. | G21: =C21-F21 -> 0
A22: a.1 | B22: 25 mm diameter | C22: 520 | D22: m | E22: 53.35 | F22: 520 | G22: =C22-F22 -> 0 | H22: =F22+G22 -> 520 | I22: =E22*F22 -> 27742 | J22: =G22*E22 -> 0 | K22: =I22+J22 -> 27742 | L22: =(H22/C22) -> 1 | M22: 15 | N22: 7.5 | O22: 0 | P22: =C22*(M22+N22+O22) -> 11700 | Q22: =K22-P22 -> 16042
A23: a.2 | B23: 32 mm diameter | C23: 120 | D23: m | E23: 63.05 | F23: 120 | G23: =C23-F23 -> 0 | H23: =F23+G23 -> 120 | I23: =E23*F23 -> 7566 | J23: =G23*E23 -> 0 | K23: =I23+J23 -> 7566 | L23: =(H23/C23) -> 1 | M23: 20 | N23: 10 | O23: 0 | P23: =C23*(M23+N23+O23) -> 3600 | Q23: =K23-P23 -> 3966
A24: a.3 | B24: 40 mm diameter | C24: 20 | D24: m | E24: 77.6 | F24: 20 | G24: =C24-F24 -> 0 | H24: =F24+G24 -> 20 | I24: =E24*F24 -> 1552 | J24: =G24*E24 -> 0 | K24: =I24+J24 -> 1552 | L24: =(H24/C24) -> 1 | M24: 24 | N24: 12 | O24: 0 | P24: =C24*(M24+N24+O24) -> 720 | Q24: =K24-P24 -> 832
A25: a.4 | B25: 50 mm diameter | C25: 130 | D25: m | E25: 95.06 | F25: 130 | G25: =C25-F25 -> 0 | H25: =F25+G25 -> 130 | I25: =E25*F25 -> 12357.8 | J25: =G25*E25 -> 0 | K25: =I25+J25 -> 12357.8 | L25: =(H25/C25) -> 1 | M25: 28 | N25: 14 | O25: 0 | P25: =C25*(M25+N25+O25) -> 5460 | Q25: =K25-P25 -> 6897.8
A26: a.5 | B26: 63 mm diameter | C26: 190 | D26: m | E26: 169.75 | F26: 190 | G26: =C26-F26 -> 0 | H26: =F26+G26 -> 190 | I26: =E26*F26 -> 32252.5 | J26: =G26*E26 -> 0 | K26: =I26+J26 -> 32252.5 | L26: =(H26/C26) -> 1 | M26: 30 | N26: 15 | O26: 0 | P26: =C26*(M26+N26+O26) -> 8550 | Q26: =K26-P26 -> 23702.5
A27: a.6 | B27: 80 mm diameter | C27: 50 | D27: m | E27: 190.12 | F27: 50 | G27: =C27-F27 -> 0 | H27: =F27+G27 -> 50 | I27: =E27*F27 -> 9506 | J27: =G27*E27 -> 0 | K27: =I27+J27 -> 9506 | L27: =(H27/C27) -> 1 | M27: 35 | N27: 25 | O27: 0 | P27: =C27*(M27+N27+O27) -> 3000 | Q27: =K27-P27 -> 6506
A28: a.7 | B28: 100 mm diameter | C28: 30 | D28: m | E28: 237.65 | F28: 30 | G28: =C28-F28 -> 0 | H28: =F28+G28 -> 30 | I28: =E28*F28 -> 7129.5 | J28: =G28*E28 -> 0 | K28: =I28+J28 -> 7129.5 | L28: =(H28/C28) -> 1 | M28: 90 | N28: 60 | O28: 0 | P28: =C28*(M28+N28+O28) -> 4500 | Q28: =K28-P28 -> 2629.5
A29: a.8 | B29: 150 mm diameter | C29: 40 | D29: m | E29: 344.35 | F29: 40 | G29: =C29-F29 -> 0 | H29: =F29+G29 -> 40 | I29: =E29*F29 -> 13774 | J29: =G29*E29 -> 0 | K29: =I29+J29 -> 13774 | L29: =(H29/C29) -> 1 | M29: 170 | N29: 90 | O29: 0 | P29: =C29*(M29+N29+O29) -> 10400 | Q29: =K29-P29 -> 3374
A30: b. | B30: Fire water sprinkler head | G30: =C30-F30 -> 0
B31: Sprinkler Head, UL listed FM approved, chrome-plated, bronze and factory painted; Shall be of one manufacturer. (No mixing of sprinkler brands shall be permitted). | G31: =C31-F31 -> 0
A32: b.1 | B32: Pendent type | C32: 218 | D32: Ea | E32: 63.05 | F32: 196.2 | G32: =C32-F32 -> 21.8 | H32: =F32+G32 -> 218 | I32: =E32*F32 -> 12370.41 | J32: =G32*E32 -> 1374.49 | K32: =I32+J32 -> 13744.9 | L32: =H32/C32 -> 1 | M32: 25 | N32: 5 | O32: 100 | P32: =C32*(M32+N32+O32) -> 28340 | Q32: =K32-P32 -> -14595.1
A33: b.2 | B33: Upright type | C33: 8 | D33: Ea | E33: 33.95 | F33: 7.2 | G33: =C33-F33 -> 0.8 | H33: =F33+G33 -> 8 | I33: =E33*F33 -> 244.44 | J33: =G33*E33 -> 27.16 | K33: =I33+J33 -> 271.6 | L33: =H33/C33 -> 1 | M33: 19 | N33: 5 | O33: 100 | P33: =C33*(M33+N33+O33) -> 992 | Q33: =K33-P33 -> -720.4
A34: b.3 | B34: Wall side type | C34: 184 | D34: Ea | E34: 72.75 | F34: 165.6 | G34: =C34-F34 -> 18.4 | H34: =F34+G34 -> 184 | I34: =E34*F34 -> 12047.4 | J34: =G34*E34 -> 1338.6 | K34: =I34+J34 -> 13386 | L34: =H34/C34 -> 1 | M34: 59 | N34: 5 | O34: 100 | P34: =C34*(M34+N34+O34) -> 30176 | Q34: =K34-P34 -> -16790
A35: 4.0 | B35: Fire-Suppression Standpipes | G35: =C35-F35 -> 0
A36: a. | B36: Fire Hose Cabinet | G36: =C36-F36 -> 0
B37: Supply and installation of Surface mounted fire hose Cabinets Made of Stainless Steel, dimension (W 750 x H 850 x D 180). with Synthetic Single Jacket Hose 1.5” x 30 meter long and (1) multipurpose dry powder Extinguisher include fittings, joints, unions, dielectric fittings, flanges, gaskets, grooved mechanical couplings, nuts and bolts, hangers and supports and labelling. | G37: =C37-F37 -> 0
A38: a.1 | B38: FHC-II | C38: 12 | D38: Ea | E38: 4704.5 | F38: 12 | G38: =C38-F38 -> 0 | H38: =F38+G38 -> 12 | I38: =E38*F38 -> 56454 | J38: =G38*E38 -> 0 | K38: =I38+J38 -> 56454 | L38: =H38/C38 -> 1 | M38: 4200 | N38: 250 | O38: 400 | P38: =C38*(M38+N38+O38) -> 58200 | Q38: =K38-P38 -> -1746
B39: SUB-TOTAL ITEM NO. B2-21 00 00 | C39: xxx | D39: xxx | I39: =SUM(I9:I38) -> 291679.97 | J39: =SUM(J9:J38) -> 6391.33 | K39: =SUM(K9:K38) -> 298071.3 | P39: =SUM(P9:P38) -> 220898 | Q39: =SUM(Q9:Q38) -> 77173.3
B40: (TO BE CARRIED TO COMPOSITE SUMMARY)
B42: OWNER | C42: CONSULTANT | K42: CONTRACTOR

Sheet SUPERVISOR -E
B3: SUPERVISOR - E
B4: B O Q | E4: THE ACTUAL QTY | H4: AMOUNT (SR)
A5: DESCRIPTION OF ITEM | B5: ESTIMATED QUANTITY | C5: UNIT | D5: UNIT PRICE(SR) EXCL. VAT | E5: Previous QTY | F5: Current QTY | G5: Cumulative QTY | H5: Previous | I5: Current | J5: Cumulative | K5: Percentage | L5: Actual price | M5: Actual Labour charge | N5: Total AP+LC | O5: Profit
A6: DIVISION 28-ELECTRONIC SAFETY AND SECURITY
A7: Fire Detection and Alarm
A8: Fire alarm control panel (FACP)
A9: Supply, installation, testing and commissioning of a microprocessor based, addressable fire alarm control panel, complete with Chassis, 640-Character backlit LCD display, QWERTY programming and control keypad, loop cards, zone and input/output modules, supervisory devices, auxiliary relays, network capability modules, battery, battery charger, printer, internal alarm, interface contacts and all accessories and hardware as shown on the Contract drawings and specified in the Contract documents and to complete the fully functional, operable, reliable and maintainable fire alarm system.
A10: Microprocessor based, addressable FACP, 5 loop type | B10: 3 | C10: Ea | D10: 22795 | E10: 2.45 | F10: =B10-E10 -> 0.55 | G10: =E10+F10 -> 3 | H10: =E10*D10 -> 55847.75 | I10: =F10*D10 -> 12537.25 | J10: =H10+I10 -> 68385 | K10: =G10/B10 -> 1 | L10: 16900 | M10: 80 | N10: =B10*(L10+M10) -> 50940 | O10: =J10-N10 -> 17445
A11: Power supply unit, batteries and battery chargers | B11: 3 | C11: Ea | D11: 4365 | E11: 0 | F11: =B11-E11 -> 3 | G11: =E11+F11 -> 3 | H11: =E11*D11 -> 0 | I11: =F11*D11 -> 13095 | J11: =H11+I11 -> 13095 | K11: =G11/B11 -> 1 | L11: 0 | M11: 0 | N11: =B11*(L11+M11) -> 0 | O11: =J11-N11 -> 13095
A12: Supply, selection and calculation, installation, testing and commissioning of FACP power supply unit, batteries for at least 24 hours during the normal operations and 15 mins under emergency full loaded condition. Provide separate combination of power Supply and battery enclosure when large batteries are required and not be able embedded inside FACP panel. | N12: =B12*(L12+M12) -> 0 | O12: =J12-N12 -> 0
A13: Detection and initiation devices | N13: =B13*(L13+M13) -> 0 | O13: =J13-N13 -> 0
A14: Supply, installation, testing and commissioning of intelligent, addressable type fire alarm detectors and initiating devices as shown on the Contract drawings and specified in the Contract documents complete with all mounting accessories including boxes, connectors and terminations. | F14: =B14-E14 -> 0 | N14: =B14*(L14+M14) -> 0 | O14: =J14-N14 -> 0
A15: Smoke detector - photoelectric, addressable, self diagnostic, self address | B15: 420 | C15: Ea | D15: 339.5 | E15: 343 | F15: =B15-E15 -> 77 | G15: =E15+F15 -> 420 | H15: =E15*D15 -> 116448.5 | I15: =F15*D15 -> 26141.5 | J15: =H15+I15 -> 142590 | K15: =G15/B15 -> 1 | L15: 120 | M15: 80 | N15: =B15*(L15+M15) -> 84000 | O15: =J15-N15 -> 58590
A16: Heat detector - rate of rise type with fix temperature | B16: 9 | C16: Ea | D16: 339.5 | E16: 6.26 | F16: =B16-E16 -> 2.74 | G16: =E16+F16 -> 9 | H16: =E16*D16 -> 2125.27 | I16: =F16*D16 -> 930.23 | J16: =H16+I16 -> 3055.5 | K16: =G16/B16 -> 1 | L16: 110 | M16: 80 | N16: =B16*(L16+M16) -> 1710 | O16: =J16-N16 -> 1345.5
A17: Addressable manual fire alarm pull station | B17: 18 | C17: Ea | D17: 291 | E17: 14.7 | F17: =B17-E17 -> 3.3 | G17: =E17+F17 -> 18 | H17: =E17*D17 -> 4277.7 | I17: =F17*D17 -> 960.3 | J17: =H17+I17 -> 5238 | K17: =G17/B17 -> 1 | L17: 160 | M17: 80 | N17: =B17*(L17+M17) -> 4320 | O17: =J17-N17 -> 918
A18: Addressable manual fire alarm pull station, weather proof | B18: 6 | C18: Ea | D18: 368.6 | E18: 4.9 | F18: =B18-E18 -> 1.1 | G18: =E18+F18 -> 6 | H18: =E18*D18 -> 1806.14 | I18: =F18*D18 -> 405.46 | J18: =H18+I18 -> 2211.6 | K18: =G18/B18 -> 1 | L18: 180 | M18: 80 | N18: =B18*(L18+M18) -> 1560 | O18: =J18-N18 -> 651.6
A19: Other initiating devices and control devices | F19: =B19-E19 -> 0 | N19: =B19*(L19+M19) -> 0 | O19: =J19-N19 -> 0
A20: Supply, Installation, testing and commissioning of all conventional I/O interfaces devices for interface and Integration with firefighting systems, gas alarm and control systems, lift safety devices, fire water pumps, HVAC systems. elevators and all other specified equipment as per contract drawings and specifications, complete with all mounting accessories including boxes and terminations. | F20: =B20-E20 -> 0 | N20: =B20*(L20+M20) -> 0 | O20: =J20-N20 -> 0
A21: Fire alarm monitoring module (MM) | B21: 24 | C21: Ea | D21: 436.5 | E21: 19.6 | F21: =B21-E21 -> 4.4 | G21: =E21+F21 -> 24 | H21: =E21*D21 -> 8555.4 | I21: =F21*D21 -> 1920.6 | J21: =H21+I21 -> 10476 | K21: =G21/B21 -> 1 | L21: 140 | M21: 80 | N21: =B21*(L21+M21) -> 5280 | O21: =J21-N21 -> 5196
A22: Notification appliances | N22: =B22*(L22+M22) -> 0 | O22: =J22-N22 -> 0
A23: Supply, installation, testing and commissioning of visual and sound alarm devices as shown on the Contract drawings and specified in the Contract documents complete with all mounting accessories including boxes and terminations. | N23: =B23*(L23+M23) -> 0 | O23: =J23-N23 -> 0
A24: Bells, indoor with strobe lights / beacons - red body, red lens for fire alarm | B24: 21 | C24: Ea | D24: 388 | E24: 17.15 | F24: =B24-E24 -> 3.85 | G24: =E24+F24 -> 21 | H24: =E24*D24 -> 6654.2 | I24: =F24*D24 -> 1493.8 | J24: =H24+I24 -> 8148 | K24: =G24/B24 -> 1 | L24: 212 | M24: 80 | N24: =B24*(L24+M24) -> 6132 | O24: =J24-N24 -> 2016
A25: Bells, indoor with strobe lights / beacons - red body, red lens for fire alarm, weather proof | B25: 12 | C25: Ea | D25: 436.5 | E25: 9.8 | F25: =B25-E25 -> 2.2 | G25: =E25+F25 -> 12 | H25: =E25*D25 -> 4277.7 | I25: =F25*D25 -> 960.3 | J25: =H25+I25 -> 5238 | K25: =G25/B25 -> 1 | L25: 250 | M25: 80 | N25: =B25*(L25+M25) -> 3960 | O25: =J25-N25 -> 1278
A26: Fire alarm cables - fire resistant cable, 300V/500V, red sheath with low emission of smoke, halogen free, thermoplastic material | F26: =B26-E26 -> 0 | N26: =B26*(L26+M26) -> 0 | O26: =J26-N26 -> 0
A27: To include for the procurement, supply, factory testing, delivery to Site, installation, testing and commissioning of the cables, termination materials and all cable support and wiring, identification accessories. | F27: =B27-E27 -> 0 | N27: =B27*(L27+M27) -> 0 | O27: =J27-N27 -> 0
A28: 2C x 2.5 mm², Stranded plain copper wire or solid conductor, overall shield with drain wire for SLC loop | B28: 2400 | C28: m | D28: 24.25 | E28: 2280 | F28: =B28-E28 -> 120 | G28: =E28+F28 -> 2400 | H28: =E28*D28 -> 55290 | I28: =F28*D28 -> 2910 | J28: =H28+I28 -> 58200 | K28: =G28/B28 -> 1 | L28: 8 | M28: 0 | N28: =B28*(L28+M28) -> 19200 | O28: =J28-N28 -> 39000
A29: 2C x 2.5 mm², Stranded plain copper wire or solid conductor, overall shield with drain wire for NAC Loop | B29: 1200 | C29: m | D29: 24.25 | E29: 1140 | F29: =B29-E29 -> 60 | G29: =E29+F29 -> 1200 | H29: =E29*D29 -> 27645 | I29: =F29*D29 -> 1455 | J29: =H29+I29 -> 29100 | K29: =G29/B29 -> 1 | L29: 8 | M29: 0 | N29: =B29*(L29+M29) -> 9600 | O29: =J29-N29 -> 19500
A30: Fire alarm cable conduit, all JB boxes, fittings and accessories for cable installations | F30: =B30-E30 -> 0 | N30: =B30*(L30+M30) -> 0 | O30: =J30-N30 -> 0
A31: To include for the procurement, supply, installation of PVC conduits and flexible metallic conduits for fire cables, junction boxes, fittings, accessories and all other relevant items or Works to complete fully Fire alarm detection system installations. | F31: =B31-E31 -> 0 | N31: =B31*(L31+M31) -> 0 | O31: =J31-N31 -> 0
A32: 20 mm diameter, PVC conduits | B32: 0 | C32: m | D32: 24.25 | E32: 0 | F32: =B32-E32 -> 0 | G32: =E32+F32 -> 0 | H32: =E32*D32 -> 0 | I32: =F32*D32 -> 0 | J32: 0 | N32: =B32*(L32+M32) -> 0 | O32: =J32-N32 -> 0
A33: SUB-TOTAL ITEM NO. B1-28 00 00 | B33: xxx | C33: xxx | E33: 0 | F33: =B33-E33 -> #VALUE! | G33: =E33+F33 -> #VALUE! | H33: =SUM(H10:H32) -> 282927.66 | I33: =SUM(I10:I32) -> 62809.44 | J33: =SUM(J10:J32) -> 345737.1 | N33: =SUM(N9:N32) -> 186702 | O33: =SUM(O9:O32) -> 159035.1
A34: (TO BE CARRIED TO COMPOSITE SUMMARY)
A36: OWNER | B36: CONSULTANT | H36: CONTRACTOR

Sheet SUPERVISOR-EXT 
C5: SUPERVISOR
A6: SECTION 2- SCHEDULE OF QUANTITIES AND PRICES | C6: B O Q | F6: THE ACTUAL QTY | I6: AMOUNT (SR) | L6: Percentage
A7: PAY ITEM NO. | B7: DESCRIPTION OF ITEM | C7: ESTIMATED QUANTITY | D7: UNIT | E7: UNIT PRICE(SR) EXCL. VAT | F7: Previous QTY | G7: Current QTY | H7: Cumulative QTY | I7: Previous | J7: Current | K7: Cumulative | M7: Actual price | N7: Actual Labour charge | O7: Total AP+LC | P7: Profit
B8: DIVISION 10 - SPECIALTIES
A9: 1.0 | B9: Fire Extinguishers
B10: Includes mounting brackets, fasteners, service tags, fully charged and ready to use extinguishers.
A11: a. | B11: Multipurpose dry chemical type, UL rated ABC
A12: a.1 | B12: FE-1, 6 kg, multi purpose fire extinguisher | C12: 42 | D12: Ea | E12: 242.5 | F12: 32 | G12: =C12-F12 -> 10 | H12: =F12+G12 -> 42 | I12: =E12*F12 -> 7760 | J12: =G12*E12 -> 2425 | K12: =I12+J12 -> 10185 | L12: =H12/C12 -> 1 | M12: 240 | N12: 10 | O12: =C12*(M12+N12) -> 10500 | P12: =K12-O12 -> -315
A13: b. | B13: Wet chemical type, UL rated class K
A14: b.1 | B14: FE-3, kitchen type-K fire extinguisher 2 gallon | C14: 9 | D14: Ea | E14: 533.5 | F14: 5.85 | G14: =C14-F14 -> 3.15 | H14: =F14+G14 -> 9 | I14: =E14*F14 -> 3120.975 | J14: =G14*E14 -> 1680.525 | K14: =I14+J14 -> 4801.5 | L14: =H14/C14 -> 1 | M14: 320 | N14: 10 | O14: =C14*(M14+N14) -> 2970 | P14: =K14-O14 -> 1831.5
A15: c. | B15: Automatic fire extinguisher
A16: c.1 | B16: FE-2, 15 kg, multi purpose fire extinguisher, ceiling mounted | C16: 21 | D16: Ea | E16: 485 | F16: 13.65 | G16: =C16-F16 -> 7.35 | H16: =F16+G16 -> 21 | I16: =E16*F16 -> 6620.25 | J16: =G16*E16 -> 3564.75 | K16: =I16+J16 -> 10185 | L16: =H16/C16 -> 1 | M16: 334 | N16: 10 | O16: =C16*(M16+N16) -> 7224 | P16: =K16-O16 -> 2961
A17: d. | B17: Fire blanket
B18: Supply and installation of fire blanket of specified type to be located in kitchen with all fittings and supports required to provide satisfactory operation.
A19: d.1 | B19: Fire blanket, standard size (1.2 meter x 1.2 meter), NFPA approved | C19: 9 | D19: Ea | E19: 291 | F19: 9 | G19: =C19-F19 -> 0 | H19: =F19+G19 -> 9 | I19: =E19*F19 -> 2619 | J19: =G19*E19 -> 0 | K19: =I19+J19 -> 2619 | L19: =H19/C19 -> 1 | M19: 16 | N19: 10 | O19: =C19*(M19+N19) -> 234 | P19: =K19-O19 -> 2385
B20: SUB-TOTAL ITEM NO. B3-10 00 00 | C20: xxx | D20: xxx | I20: =SUM(I9:I19) -> 20120.225 | J20: =SUM(J9:J19) -> 7670.275 | K20: =SUM(K9:K19) -> 27790.5 | O20: =SUM(O9:O19) -> 20928 | P20: =SUM(P9:P19) -> 6862.5

Sheet SUPERVISOR
C3: SUPERVISOR
A4: SECTION 2- SCHEDULE OF QUANTITIES AND PRICES | C4: B O Q | F4: THE ACTUAL QTY | I4: AMOUNT (SR)
A5: PAY ITEM NO. | B5: DESCRIPTION OF ITEM | C5: ESTIMATED QUANTITY | D5: UNIT | E5: UNIT PRICE(SR) EXCL. VAT | F5: Previous QTY | G5: Current QTY | H5: Cumulative QTY | I5: Previous | J5: Current | K5: Cumulative | L5: Percentage | M5: Actual price | N5: accessories | O5: Actual Labour charge | P5: Total AP+LC | Q5: Profit
B6: DIVISION 21 - FIRE SUPPRESSION
A7: 1.0 | B7: General-Duty Valves for Water-Based Fire-Suppression Piping
B8: Supply and installation of valves including all fixings, supports, all other accessories and associated Works.
A9: a. | B9: Gate valve, UL and FM global approved
A10: a.1 | B10: 150 mm diameter | C10: 6 | D10: Ea | E10: 3686 | F10: 5.4 | G10: =C10-F10 -> 0.6 | H10: =F10+G10 -> 6 | I10: =E10*F10 -> 19904.4 | J10: =G10*E10 -> 2211.6 | K10: =I10+J10 -> 22116 | L10: =H10/C10 -> 1 | M10: 1250 | N10: 100 | O10: 300 | P10: =C10*(M10+N10+O10) -> 9900 | Q10: =K10-P10 -> 12216
A11: b. | B11: Alarm check valve, UL and FM global approved
A12: b.1 | B12: 150 mm diameter | C12: 3 | D12: Ea | E12: 5577.5 | F12: 2.25 | G12: =C12-F12 -> 0.75 | H12: =F12+G12 -> 3 | I12: =E12*F12 -> 12549.375 | J12: =G12*E12 -> 4183.125 | K12: =I12+J12 -> 16732.5 | L12: =H12/C12 -> 1 | M12: 3830 | N12: 200 | O12: 100 | P12: =C12*(M12+N12+O12) -> 12390 | Q12: =K12-P12 -> 4342.5
A13: c. | B13: Zone control valve assembly
A14: c.1 | B14: 100 mm diameter | C14: 9 | D14: Ea | E14: 5626 | F14: 8.1 | G14: =C14-F14 -> 0.9 | H14: =F14+G14 -> 9 | I14: =E14*F14 -> 45570.6 | J14: =G14*E14 -> 5063.4 | K14: =I14+J14 -> 50634 | L14: =H14/C14 -> 1 | M14: 3000 | N14: 150 | O14: 100 | P14: =C14*(M14+N14+O14) -> 29250 | Q14: =K14-P14 -> 21384
A15: 2.0 | B15: Fire-Department Connections
B16: Two way, swivel fittings, Dust caps and chains of same material as body, chrome plated finish and threads to match local fire department hardware
A17: a. | B17: Flush wall mounted fire department connection with check valve
A18: a.1 | B18: Two-way swivel fittings, 65 x 65 x 100 mm single clapper Siamese-type connections | C18: 3 | D18: Ea | E18: 4462 | F18: 2.25 | G18: =C18-F18 -> 0.75 | H18: =F18+G18 -> 3 | I18: =E18*F18 -> 10039.5 | J18: =G18*E18 -> 3346.5 | K18: =I18+J18 -> 13386 | L18: =H18/C18 -> 1 | M18: 450 | N18: 150 | O18: 100 | P18: =C18*(M18+N18+O18) -> 2100 | Q18: =K18-P18 -> 11286
A19: 3.0 | B19: Wet-Pipe Sprinkler Systems
A20: a. | B20: Black steel fire water pipes
B21: Supply and installation of black steel pipe seamless type as per ASTM A53 including supports, hangers, fixing, fitting, all other accessories and associated Works as per Contract drawings and specifications.
A22: a.1 | B22: 25 mm diameter | C22: 1305 | D22: m | E22: 53.35 | F22: 1305 | G22: =C22-F22 -> 0 | H22: =F22+G22 -> 1305 | I22: =E22*F22 -> 69621.75 | J22: =G22*E22 -> 0 | K22: =I22+J22 -> 69621.75 | L22: =(H22/C22) -> 1 | M22: 15 | N22: 7.5 | O22: 0 | P22: =C22*(M22+N22+O22) -> 29362.5 | Q22: =K22-P22 -> 40259.25
A23: a.2 | B23: 32 mm diameter | C23: 90 | D23: m | E23: 63.05 | F23: 90 | G23: =C23-F23 -> 0 | H23: =F23+G23 -> 90 | I23: =E23*F23 -> 5674.5 | J23: =G23*E23 -> 0 | K23: =I23+J23 -> 5674.5 | L23: =(H23/C23) -> 1 | M23: 20 | N23: 10 | O23: 0 | P23: =C23*(M23+N23+O23) -> 2700 | Q23: =K23-P23 -> 2974.5
A24: a.3 | B24: 40 mm diameter | C24: 120 | D24: m | E24: 77.6 | F24: 120 | G24: =C24-F24 -> 0 | H24: =F24+G24 -> 120 | I24: =E24*F24 -> 9312 | J24: =G24*E24 -> 0 | K24: =I24+J24 -> 9312 | L24: =(H24/C24) -> 1 | M24: 24 | N24: 12 | O24: 0 | P24: =C24*(M24+N24+O24) -> 4320 | Q24: =K24-P24 -> 4992
A25: a.4 | B25: 50 mm diameter | C25: 60 | D25: m | E25: 95.06 | F25: 60 | G25: =C25-F25 -> 0 | H25: =F25+G25 -> 60 | I25: =E25*F25 -> 5703.6 | J25: =G25*E25 -> 0 | K25: =I25+J25 -> 5703.6 | L25: =(H25/C25) -> 1 | M25: 28 | N25: 14 | O25: 0 | P25: =C25*(M25+N25+O25) -> 2520 | Q25: =K25-P25 -> 3183.6
A26: a.5 | B26: 65 mm diameter | C26: 300 | D26: m | E26: 169.75 | F26: 298.75 | G26: =C26-F26 -> 1.25 | H26: =F26+G26 -> 300 | I26: =E26*F26 -> 50712.812 | J26: =G26*E26 -> 212.1875 | K26: =I26+J26 -> 50925 | L26: =(H26/C26) -> 1 | M26: 30 | N26: 15 | O26: 0 | P26: =C26*(M26+N26+O26) -> 13500 | Q26: =K26-P26 -> 37425
A27: a.6 | B27: 80 mm diameter | C27: 150 | D27: m | E27: 190.12 | F27: 150 | G27: =C27-F27 -> 0 | H27: =F27+G27 -> 150 | I27: =E27*F27 -> 28518 | J27: =G27*E27 -> 0 | K27: =I27+J27 -> 28518 | L27: =(H27/C27) -> 1 | M27: 35 | N27: 25 | O27: 0 | P27: =C27*(M27+N27+O27) -> 9000 | Q27: =K27-P27 -> 19518
A28: a.7 | B28: 100 mm diameter | C28: 30 | D28: m | E28: 237.65 | F28: 30 | G28: =C28-F28 -> 0 | H28: =F28+G28 -> 30 | I28: =E28*F28 -> 7129.5 | J28: =G28*E28 -> 0 | K28: =I28+J28 -> 7129.5 | L28: =(H28/C28) -> 1 | M28: 90 | N28: 60 | O28: 0 | P28: =C28*(M28+N28+O28) -> 4500 | Q28: =K28-P28 -> 2629.5
A29: a.8 | B29: 150 mm diameter | C29: =30*3 -> 90 | D29: m | E29: 344.35 | F29: 89.95 | G29: =C29-F29 -> 0.05 | H29: =F29+G29 -> 90 | I29: =E29*F29 -> 30974.283 | J29: =G29*E29 -> 17.2175 | K29: =I29+J29 -> 30991.5 | L29: =(H29/C29) -> 1 | M29: 170 | N29: 90 | O29: 0 | P29: =C29*(M29+N29+O29) -> 23400 | Q29: =K29-P29 -> 7591.5
A30: b. | B30: Fire water sprinkler head
B31: Sprinkler Head, UL listed FM approved, chrome-plated, bronze and factory painted; Shall be of one manufacturer. (No mixing of sprinkler brands shall be permitted).
A32: b.1 | B32: Pendent type | C32: 480 | D32: Ea | E32: 63.05 | F32: 479.99993 | G32: =C32-F32 -> 7e-05 | H32: =F32+G32 -> 480 | I32: =E32*F32 -> 30263.996 | J32: =G32*E32 -> 0.0044135 | K32: =I32+J32 -> 30264 | L32: =H32/C32 -> 1 | M32: 25 | N32: 5 | O32: 100 | P32: =C32*(M32+N32+O32) -> 62400 | Q32: =K32-P32 -> -32136
A33: b.2 | B33: Upright type | C33: 15 | D33: Ea | E33: 33.95 | F33: 14.9965 | G33: =C33-F33 -> 0.0035 | H33: =F33+G33 -> 15 | I33: =E33*F33 -> 509.13118 | J33: =G33*E33 -> 0.118825 | K33: =I33+J33 -> 509.25 | L33: =H33/C33 -> 1 | M33: 19 | N33: 5 | O33: 100 | P33: =C33*(M33+N33+O33) -> 1860 | Q33: =K33-P33 -> -1350.75
A34: b.3 | B34: Wall side type | C34: 282 | D34: Ea | E34: 72.75 | F34: 281.99662 | G34: =C34-F34 -> 0.00338 | H34: =F34+G34 -> 282 | I34: =E34*F34 -> 20515.254 | J34: =G34*E34 -> 0.245895 | K34: =I34+J34 -> 20515.5 | L34: =H34/C34 -> 1 | M34: 59 | N34: 5 | O34: 100 | P34: =C34*(M34+N34+O34) -> 46248 | Q34: =K34-P34 -> -25732.5
A35: 4.0 | B35: Fire-Suppression Standpipes
A36: a. | B36: Fire Hose Cabinet
B37: Supply and installation of Surface mounted fire hose Cabinets Made of Stainless Steel, dimension (W 750 x H 850 x D 180). with Synthetic Single Jacket Hose 1.5” x 30 meter long and (1) multipurpose dry powder Extinguisher include fittings, joints, unions, dielectric fittings, flanges, gaskets, grooved mechanical couplings, nuts and bolts, hangers and supports and labelling.
A38: a.1 | B38: FHC-II | C38: =6*3 -> 18 | D38: Ea | E38: 4704.5 | F38: 18 | G38: =C38-F38 -> 0 | H38: =F38+G38 -> 18 | I38: =E38*F38 -> 84681 | J38: =G38*E38 -> 0 | K38: =I38+J38 -> 84681 | L38: =H38/C38 -> 1 | M38: 4200 | N38: 250 | O38: 400 | P38: =C38*(M38+N38+O38) -> 87300 | Q38: =K38-P38 -> -2619
B39: SUB-TOTAL ITEM NO. B3-21 00 00 | C39: xxx | D39: xxx | I39: =SUM(I9:I38) -> 431679.7 | J39: =SUM(J9:J38) -> 15034.399 | K39: =SUM(K9:K38) -> 446714.1 | P39: =SUM(P9:P38) -> 340750.5 | Q39: =SUM(Q9:Q38) -> 105963.6
B40: (TO BE CARRIED TO COMPOSITE SUMMARY) | C40: 0
B42: OWNER | C42: CONSULTANT | I42: CONTRACTOR

Sheet ISOLATE - E
B3: ISOLATE - E
B4: B O Q | E4: THE ACTUAL QTY | H4: AMOUNT (SR)
A5: DESCRIPTION OF ITEM | B5: ESTIMATED QUANTITY | C5: UNIT | D5: UNIT PRICE(SR) EXCL. VAT | E5: Previous QTY | F5: Current QTY | G5: Cumulative QTY | H5: Previous | I5: Current | J5: Cumulative | K5: Percentage | L5: Actual price | M5: Actual Labour charge | N5: Total AP+LC | O5: Profit
A6: DIVISION 28-ELECTRONIC SAFETY AND SECURITY
A7: Fire Detection and Alarm
A8: Fire alarm control panel (FACP)
A9: Supply, installation, testing and commissioning of a microprocessor based, addressable fire alarm control panel, complete with Chassis, 640-Character backlit LCD display, QWERTY programming and control keypad, loop cards, zone and input/output modules, supervisory devices, auxiliary relays, network capability modules, battery, battery charger, printer, internal alarm, interface contacts and all accessories and hardware as shown on the Contract drawings and specified in the Contract documents and to complete the fully functional, operable, reliable and maintainable fire alarm system.
A10: Microprocessor based, addressable FACP, 5 loop type | B10: 1 | C10: Ea | D10: 22795 | E10: 0.9 | F10: =B10-E10 -> 0.1 | G10: =E10+F10 -> 1 | H10: =D10*E10 -> 20515.5 | I10: =F10*D10 -> 2279.5 | J10: =H10+I10 -> 22795 | K10: =G10/B10 -> 1 | L10: 16900 | M10: 80 | N10: =B10*(L10+M10) -> 16980 | O10: =J10-N10 -> 5815
A11: Power supply unit, batteries and battery chargers | B11: 1 | C11: Ea | D11: 4365 | E11: 0 | F11: =B11-E11 -> 1 | G11: =E11+F11 -> 1 | H11: =D11*E11 -> 0 | I11: =F11*D11 -> 4365 | J11: =H11+I11 -> 4365 | K11: =G11/B11 -> 1 | L11: 0 | M11: 0 | N11: =B11*(L11+M11) -> 0 | O11: =J11-N11 -> 4365
A12: Supply, selection and calculation, installation, testing and commissioning of FACP power supply unit, batteries for at least 24 hours during the normal operations and 15 mins under emergency full loaded condition. Provide separate combination of power Supply and battery enclosure when large batteries are required and not be able embedded inside FACP panel.
A13: Detection and initiation devices
A14: Supply, installation, testing and commissioning of intelligent, addressable type fire alarm detectors and initiating devices as shown on the Contract drawings and specified in the Contract documents complete with all mounting accessories including boxes, connectors and terminations.
A15: Smoke detector - photoelectric, addressable, self diagnostic, self address | B15: 87 | C15: Ea | D15: 339.5 | E15: 78.15 | F15: =B15-E15 -> 8.85 | G15: =E15+F15 -> 87 | H15: =D15*E15 -> 26531.925 | I15: =F15*D15 -> 3004.575 | J15: =H15+I15 -> 29536.5 | K15: =G15/B15 -> 1 | L15: 120 | M15: 80 | N15: =B15*(L15+M15) -> 17400 | O15: =J15-N15 -> 12136.5
A16: Heat detector - rate of rise type with fix temperature | B16: 3 | C16: Ea | D16: 339.5 | E16: 8.1 | F16: =B16-E16 -> -5.1 | G16: =E16+F16 -> 3 | H16: =D16*E16 -> 2749.95 | I16: =F16*D16 -> -1731.45 | J16: =H16+I16 -> 1018.5 | K16: =G16/B16 -> 1 | L16: 110 | M16: 80 | N16: =B16*(L16+M16) -> 570 | O16: =J16-N16 -> 448.5
A17: Addressable manual fire alarm pull station | B17: 4 | C17: Ea | D17: 291 | E17: 16.2 | F17: =B17-E17 -> -12.2 | G17: =E17+F17 -> 4 | H17: =D17*E17 -> 4714.2 | I17: =F17*D17 -> -3550.2 | J17: =H17+I17 -> 1164 | K17: =G17/B17 -> 1 | L17: 160 | M17: 80 | N17: =B17*(L17+M17) -> 960 | O17: =J17-N17 -> 204
A18: Addressable manual fire alarm pull station, weather proof | B18: 0 | C18: Ea | D18: 368.6 | E18: 5.37 | F18: =B18-E18 -> -5.37 | G18: =E18+F18 -> 0 | H18: =D18*E18 -> 1979.382 | I18: =F18*D18 -> -1979.382 | J18: =H18+I18 -> 0 | K18: =G18/B18 -> #DIV/0! | L18: 180 | M18: 80 | N18: =B18*(L18+M18) -> 0 | O18: =J18-N18 -> 0
A19: Other initiating devices and control devices
A20: Supply, Installation, testing and commissioning of all conventional I/O interfaces devices for interface and Integration with firefighting systems, gas alarm and control systems, lift safety devices, fire water pumps, HVAC systems. elevators and all other specified equipment as per contract drawings and specifications, complete with all mounting accessories including boxes and terminations.
A21: Fire alarm monitoring module (MM) | B21: 8 | C21: Ea | D21: 436.5 | E21: 21.6 | F21: =B21-E21 -> -13.6 | G21: =E21+F21 -> 8 | H21: =D21*E21 -> 9428.4 | I21: =F21*D21 -> -5936.4 | J21: =H21+I21 -> 3492 | K21: =G21/B21 -> 1 | L21: 140 | M21: 80 | N21: =B21*(L21+M21) -> 1760 | O21: =J21-N21 -> 1732
A22: Notification appliances
A23: Supply, installation, testing and commissioning of visual and sound alarm devices as shown on the Contract drawings and specified in the Contract documents complete with all mounting accessories including boxes and terminations.
A24: Bells, indoor with strobe lights / beacons - red body, red lens for fire alarm | B24: 5 | C24: Ea | D24: 388 | E24: 18.86 | F24: =B24-E24 -> -13.86 | G24: =E24+F24 -> 5 | H24: =D24*E24 -> 7317.68 | I24: =F24*D24 -> -5377.68 | J24: =H24+I24 -> 1940 | K24: =G24/B24 -> 1 | L24: 212 | M24: 80 | N24: =B24*(L24+M24) -> 1460 | O24: =J24-N24 -> 480
A25: Bells, indoor with strobe lights / beacons - red body, red lens for fire alarm, weather proof | B25: 2 | C25: Ea | D25: 436.5 | E25: 10.8 | F25: =B25-E25 -> -8.8 | G25: =E25+F25 -> 2 | H25: =D25*E25 -> 4714.2 | I25: =F25*D25 -> -3841.2 | J25: =H25+I25 -> 873 | K25: =G25/B25 -> 1 | L25: 250 | M25: 80 | N25: =B25*(L25+M25) -> 660 | O25: =J25-N25 -> 213
A26: Fire alarm cables - fire resistant cable, 300V/500V, red sheath with low emission of smoke, halogen free, thermoplastic material | D26: 0
A27: To include for the procurement, supply, factory testing, delivery to Site, installation, testing and commissioning of the cables, termination materials and all cable support and wiring, identification accessories.
A28: 2C x 2.5 mm², Stranded plain copper wire or solid conductor, overall shield with drain wire for SLC loop | B28: 800 | C28: m | D28: 24.25 | E28: 760 | F28: =B28-E28 -> 40 | G28: =E28+F28 -> 800 | H28: =D28*E28 -> 18430 | I28: =F28*D28 -> 970 | J28: =H28+I28 -> 19400 | K28: =G28/B28 -> 1 | L28: 8 | M28: 0 | N28: =B28*(L28+M28) -> 6400 | O28: =J28-N28 -> 13000
A29: 2C x 2.5 mm², Stranded plain copper wire or solid conductor, overall shield with drain wire for NAC Loop | B29: 400 | C29: m | D29: 24.25 | E29: 380 | F29: =B29-E29 -> 20 | G29: =E29+F29 -> 400 | H29: =D29*E29 -> 9215 | I29: =F29*D29 -> 485 | J29: =H29+I29 -> 9700 | K29: =G29/B29 -> 1 | L29: 8 | M29: 0 | N29: =B29*(L29+M29) -> 3200 | O29: =J29-N29 -> 6500
A30: Fire alarm cable conduit, all JB boxes, fittings and accessories for cable installations
A31: To include for the procurement, supply, installation of PVC conduits and flexible metallic conduits for fire cables, junction boxes, fittings, accessories and all other relevant items or Works to complete fully Fire alarm detection system installations.
A32: 20 mm diameter, PVC conduits | B32: 0 | C32: m | D32: 24.25 | E32: 0 | F32: 0 | G32: =E32+F32 -> 0 | H32: =D32*E32 -> 0 | I32: =F32*D32 -> 0 | J32: =H32+I32 -> 0 | N32: =B32*(L32+M32) -> 0 | O32: =J32-N32 -> 0
A33: SUB-TOTAL ITEM NO. B1-28 00 00 | B33: xxx | C33: xxx | E33: 0 | F33: 0 | G33: =E33+F33 -> 0 | H33: =D33*E33 -> 0 | I33: =F33*D33 -> 0 | J33: =H33+I33 -> 0 | N33: =SUM(N9:N32) -> 49390 | O33: =SUM(O9:O32) -> 44894
A34: (TO BE CARRIED TO COMPOSITE SUMMARY) | H34: =SUM(H10:H33) -> 105596.24 | I34: =SUM(I10:I33) -> -11312.237 | J34: =SUM(J10:J33) -> 94284
A36: OWNER | B36: CONSULTANT | H36: CONTRACTOR

Sheet ISOLATED-EXT 
C5: ISOLATED
A6: SECTION 2- SCHEDULE OF QUANTITIES AND PRICES | C6: B O Q | F6: THE ACTUAL QTY | I6: AMOUNT (SR) | L6: Percentage
A7: PAY ITEM NO. | B7: DESCRIPTION OF ITEM | C7: ESTIMATED QUANTITY | D7: UNIT | E7: UNIT PRICE(SR) EXCL. VAT | F7: Previous QTY | G7: Current QTY | H7: Cumulative QTY | I7: Previous | J7: Current | K7: Cumulative | M7: Actual price | N7: Actual Labour charge | O7: Total AP+LC | P7: Profit
B8: DIVISION 10 - SPECIALTIES
A9: 1.0 | B9: Fire Extinguishers
B10: Includes mounting brackets, fasteners, service tags, fully charged and ready to use extinguishers.
A11: a. | B11: Multipurpose dry chemical type, UL rated ABC
A12: a.1 | B12: FE-1, 6 kg, multi purpose fire extinguisher | C12: 9 | D12: Ea | E12: 243 | F12: 7 | G12: =C12-F12 -> 2 | H12: =F12+G12 -> 9 | I12: =E12*F12 -> 1701 | J12: =G12*E12 -> 486 | K12: =I12+J12 -> 2187 | L12: =H12/C12 -> 1 | M12: 240 | N12: 10 | O12: =C12*(M12+N12) -> 2250 | P12: =K12-O12 -> -63
A13: b. | B13: Wet chemical type, UL rated class K
A14: b.1 | B14: FE-3, kitchen type-K fire extinguisher 2 gallon | C14: 2 | D14: Ea | E14: 534 | F14: 1.3 | G14: =C14-F14 -> 0.7 | H14: =F14+G14 -> 2 | I14: =E14*F14 -> 694.2 | J14: =G14*E14 -> 373.8 | K14: =I14+J14 -> 1068 | L14: =H14/C14 -> 1 | M14: 320 | N14: 10 | O14: =C14*(M14+N14) -> 660 | P14: =K14-O14 -> 408
A15: c. | B15: Automatic fire extinguisher
A16: c.1 | B16: FE-2, 15 kg, multi purpose fire extinguisher, ceiling mounted | C16: 7 | D16: Ea | E16: 485 | F16: 4.55 | G16: =C16-F16 -> 2.45 | H16: =F16+G16 -> 7 | I16: =E16*F16 -> 2206.75 | J16: =G16*E16 -> 1188.25 | K16: =I16+J16 -> 3395 | L16: =H16/C16 -> 1 | M16: 334 | N16: 10 | O16: =C16*(M16+N16) -> 2408 | P16: =K16-O16 -> 987
A17: d. | B17: Fire blanket
B18: Supply and installation of fire blanket of specified type to be located in kitchen with all fittings and supports required to provide satisfactory operation.
A19: d.1 | B19: Fire blanket, standard size (1.2 meter x 1.2 meter), NFPA approved | C19: 2 | D19: Ea | E19: 391 | F19: 2 | G19: =C19-F19 -> 0 | H19: =F19+G19 -> 2 | I19: =E19*F19 -> 782 | J19: =E19*G19 -> 0 | K19: =I19+J19 -> 782 | L19: =H19/C19 -> 1 | M19: 16 | N19: 10 | O19: =C19*(M19+N19) -> 52 | P19: =K19-O19 -> 730
B20: SUB-TOTAL ITEM NO. B6-10 00 00 | C20: xxx | D20: xxx | I20: =SUM(I9:I19) -> 5383.95 | J20: =SUM(J9:J19) -> 2048.05 | K20: =SUM(K9:K19) -> 7432 | O20: =SUM(O9:O19) -> 5370 | P20: =SUM(P9:P19) -> 2062

Sheet ISOLATED
C3: ISOLATED
A4: SECTION 2- SCHEDULE OF QUANTITIES AND PRICES | C4: B O Q | F4: THE ACTUAL QTY | I4: AMOUNT (SR)
A5: PAY ITEM NO. | B5: DESCRIPTION OF ITEM | C5: ESTIMATED QUANTITY | D5: UNIT | E5: UNIT PRICE(SR) EXCL. VAT | F5: Previous QTY | G5: Current QTY | H5: Cumulative QTY | I5: Previous | J5: Current | K5: Cumulative | L5: Percentage | M5: Actual price | N5: accessories | O5: Actual Labour charge | P5: Total AP+LC | Q5: Profit
B6: DIVISION 21 - FIRE SUPPRESSION
A7: 1.0 | B7: General-Duty Valves for Water-Based Fire-Suppression Piping
B8: Supply and installation of valves including all fixings, supports, all other accessories and associated Works.
A9: a. | B9: Gate valve, UL and FM global approved
A10: a.1 | B10: 150 mm diameter | C10: 2 | D10: Ea | E10: 3686 | F10: 1.49 | G10: =C10-F10 -> 0.51 | H10: =F10+G10 -> 2 | I10: =E10*F10 -> 5492.14 | J10: =G10*E10 -> 1879.86 | K10: =I10+J10 -> 7372 | L10: =H10/C10 -> 1 | M10: 1250 | N10: 100 | O10: 300 | P10: =C10*(M10+N10+O10) -> 3300 | Q10: =K10-P10 -> 4072
A11: b. | B11: Alarm check valve, UL and FM global approved
A12: b.1 | B12: 150 mm diameter | C12: 1 | D12: Ea | E12: 5577.5 | F12: 0.75 | G12: =C12-F12 -> 0.25 | H12: =F12+G12 -> 1 | I12: =E12*F12 -> 4183.125 | J12: =G12*E12 -> 1394.375 | K12: =I12+J12 -> 5577.5 | L12: =H12/C12 -> 1 | M12: 3830 | N12: 200 | O12: 100 | P12: =C12*(M12+N12+O12) -> 4130 | Q12: =K12-P12 -> 1447.5
A13: c. | B13: Zone control valve assembly
A14: c.1 | B14: 100 mm diameter | C14: 2 | D14: Ea | E14: 5626 | F14: 1.5 | G14: =C14-F14 -> 0.5 | H14: =F14+G14 -> 2 | I14: =E14*F14 -> 8439 | J14: =G14*E14 -> 2813 | K14: =I14+J14 -> 11252 | L14: =H14/C14 -> 1 | M14: 3000 | N14: 150 | O14: 100 | P14: =C14*(M14+N14+O14) -> 6500 | Q14: =K14-P14 -> 4752
A15: 2.0 | B15: Fire-Department Connections
B16: Two way, swivel fittings, Dust caps and chains of same material as body, chrome plated finish and threads to match local fire department hardware
A17: a. | B17: Flush wall mounted fire department connection with check valve
A18: a.1 | B18: Two-way swivel fittings, 65 x 65 x 100 mm single clapper Siamese-type connections | C18: 1 | D18: Ea | E18: 4462 | F18: 0.65 | G18: =C18-F18 -> 0.35 | H18: =F18+G18 -> 1 | I18: =E18*F18 -> 2900.3 | J18: =G18*E18 -> 1561.7 | K18: =I18+J18 -> 4462 | L18: =H18/C18 -> 1 | M18: 450 | N18: 150 | O18: 100 | P18: =C18*(M18+N18+O18) -> 700 | Q18: =K18-P18 -> 3762
A19: 3.0 | B19: Wet-Pipe Sprinkler Systems
A20: a. | B20: Black steel fire water pipes
B21: Supply and installation of black steel pipe seamless type as per ASTM A53 including supports, hangers, fixing, fitting, all other accessories and associated Works as per Contract drawings and specifications.
A22: a.1 | B22: 25 mm diameter | C22: 250 | D22: m | E22: 53.35 | F22: 250 | G22: =C22-F22 -> 0 | H22: =F22+G22 -> 250 | I22: =E22*F22 -> 13337.5 | J22: =G22*E22 -> 0 | K22: =I22+J22 -> 13337.5 | L22: =(H22/C22) -> 1 | M22: 15 | N22: 7.5 | O22: 0 | P22: =C22*(M22+N22+O22) -> 5625 | Q22: =K22-P22 -> 7712.5
A23: a.2 | B23: 32 mm diameter | C23: 10 | D23: m | E23: 63.05 | F23: 10 | G23: =C23-F23 -> 0 | H23: =F23+G23 -> 10 | I23: =E23*F23 -> 630.5 | J23: =G23*E23 -> 0 | K23: =I23+J23 -> 630.5 | L23: =(H23/C23) -> 1 | M23: 20 | N23: 10 | O23: 0 | P23: =C23*(M23+N23+O23) -> 300 | Q23: =K23-P23 -> 330.5
A24: a.3 | B24: 40 mm diameter | C24: 40 | D24: m | E24: 77.6 | F24: 40 | G24: =C24-F24 -> 0 | H24: =F24+G24 -> 40 | I24: =E24*F24 -> 3104 | J24: =G24*E24 -> 0 | K24: =I24+J24 -> 3104 | L24: =(H24/C24) -> 1 | M24: 24 | N24: 12 | O24: 0 | P24: =C24*(M24+N24+O24) -> 1440 | Q24: =K24-P24 -> 1664
A25: a.4 | B25: 50 mm diameter | C25: 30 | D25: m | E25: 95.06 | F25: 30 | G25: =C25-F25 -> 0 | H25: =F25+G25 -> 30 | I25: =E25*F25 -> 2851.8 | J25: =G25*E25 -> 0 | K25: =I25+J25 -> 2851.8 | L25: =(H25/C25) -> 1 | M25: 28 | N25: 14 | O25: 0 | P25: =C25*(M25+N25+O25) -> 1260 | Q25: =K25-P25 -> 1591.8
A26: a.5 | B26: 63 mm diameter | C26: 70 | D26: m | E26: 169.75 | F26: 69.925 | G26: =C26-F26 -> 0.075 | H26: =F26+G26 -> 70 | I26: =E26*F26 -> 11869.769 | J26: =G26*E26 -> 12.73125 | K26: =I26+J26 -> 11882.5 | L26: =(H26/C26) -> 1 | M26: 30 | N26: 15 | O26: 0 | P26: =C26*(M26+N26+O26) -> 3150 | Q26: =K26-P26 -> 8732.5
A27: a.6 | B27: 80 mm diameter | C27: 40 | D27: m | E27: 190.12 | F27: 40 | G27: =C27-F27 -> 0 | H27: =F27+G27 -> 40 | I27: =E27*F27 -> 7604.8 | J27: =G27*E27 -> 0 | K27: =I27+J27 -> 7604.8 | L27: =(H27/C27) -> 1 | M27: 35 | N27: 25 | O27: 0 | P27: =C27*(M27+N27+O27) -> 2400 | Q27: =K27-P27 -> 5204.8
A28: a.7 | B28: 100 mm diameter | C28: 10 | D28: m | E28: 237.65 | F28: 10 | G28: =C28-F28 -> 0 | H28: =F28+G28 -> 10 | I28: =E28*F28 -> 2376.5 | J28: =G28*E28 -> 0 | K28: =I28+J28 -> 2376.5 | L28: =(H28/C28) -> 1 | M28: 90 | N28: 60 | O28: 0 | P28: =C28*(M28+N28+O28) -> 1500 | Q28: =K28-P28 -> 876.5
A29: a.8 | B29: 150 mm diameter | C29: 40 | D29: m | E29: 344.35 | F29: 40.05 | G29: =C29-F29 -> -0.05 | H29: =F29+G29 -> 40 | I29: =E29*F29 -> 13791.218 | J29: =G29*E29 -> -17.2175 | K29: =I29+J29 -> 13774 | L29: =(H29/C29) -> 1 | M29: 170 | N29: 90 | O29: 0 | P29: =C29*(M29+N29+O29) -> 10400 | Q29: =K29-P29 -> 3374
A30: b. | B30: Fire water sprinkler head | C30: 0
B31: Sprinkler Head, UL listed FM approved, chrome-plated, bronze and factory painted; Shall be of one manufacturer. (No mixing of sprinkler brands shall be permitted).
A32: b.1 | B32: Pendent type | C32: 122 | D32: Ea | E32: 63.05 | F32: 122 | G32: =C32-F32 -> 0 | H32: =F32+G32 -> 122 | I32: =E32*F32 -> 7692.1 | J32: =G32*E32 -> 0 | K32: =I32+J32 -> 7692.1 | L32: =H32/C32 -> 1 | M32: 25 | N32: 5 | O32: 100 | P32: =C32*(M32+N32+O32) -> 15860 | Q32: =K32-P32 -> -8167.9
A33: b.2 | B33: Upright type | C33: 6 | D33: Ea | E33: 33.95 | F33: 6 | G33: =C33-F33 -> 0 | H33: =F33+G33 -> 6 | I33: =E33*F33 -> 203.7 | J33: =G33*E33 -> 0 | K33: =I33+J33 -> 203.7 | L33: =H33/C33 -> 1 | M33: 19 | N33: 5 | O33: 100 | P33: =C33*(M33+N33+O33) -> 744 | Q33: =K33-P33 -> -540.3
A34: b.3 | B34: Wall side type | C34: 47 | D34: Ea | E34: 72.75 | F34: 47 | G34: =C34-F34 -> 0 | H34: =F34+G34 -> 47 | I34: =E34*F34 -> 3419.25 | J34: =G34*E34 -> 0 | K34: =I34+J34 -> 3419.25 | L34: =H34/C34 -> 1 | M34: 59 | N34: 5 | O34: 100 | P34: =C34*(M34+N34+O34) -> 7708 | Q34: =K34-P34 -> -4288.75
A35: 4.0 | B35: Fire-Suppression Standpipes
A36: a. | B36: Fire Hose Cabinet
B37: Supply and installation of Surface mounted fire hose Cabinets Made of Stainless Steel, dimension (W 750 x H 850 x D 180). with Synthetic Single Jacket Hose 1.5” x 30 meter long and (1) multipurpose dry powder Extinguisher include fittings, joints, unions, dielectric fittings, flanges, gaskets, grooved mechanical couplings, nuts and bolts, hangers and supports and labelling.
A38: a.1 | B38: FHC-II | C38: 4 | D38: Ea | E38: 4704.5 | F38: 4 | G38: =C38-F38 -> 0 | H38: =F38+G38 -> 4 | I38: =E38*F38 -> 18818 | J38: =G38*E38 -> 0 | K38: =I38+J38 -> 18818 | L38: =H38/C38 -> 1 | M38: 4200 | N38: 250 | O38: 400 | P38: =C38*(M38+N38+O38) -> 19400 | Q38: =K38-P38 -> -582
B39: SUB-TOTAL ITEM NO. B6-21 00 00 | C39: xxx | D39: xxx | I39: =SUM(I9:I38) -> 106713.7 | J39: =SUM(J9:J38) -> 7644.4488 | K39: =SUM(K9:K38) -> 114358.15 | P39: =SUM(P9:P38) -> 84417 | Q39: =SUM(Q9:Q38) -> 29941.15
B40: (TO BE CARRIED TO COMPOSITE SUMMARY)
B42: OWNER | C42: CONSULTANT | I42: CONTRACTOR

Sheet SENIOR - E
C3: SENIOR - E
C4: B O Q | F4: THE ACTUAL QTY | I4: AMOUNT (SR)
A5: SECTION 2- SCHEDULE OF QUANTITIES AND PRICES | B5: DESCRIPTION OF ITEM | C5: ESTIMATED QUANTITY | D5: UNIT | E5: UNIT PRICE(SR) EXCL. VAT | F5: Previous QTY | G5: Current QTY | H5: Cumulative QTY | I5: Previous | J5: Current | K5: Cumulative | L5: Percentage | M5: Actual price | N5: Actual Labour charge | O5: Total AP+LC | P5: Profit
A6: PAY ITEM NO.
B7: DIVISION 28-ELECTRONIC SAFETY AND SECURITY
B8: Supply and installation of IP Fixed cameras, POE+ TCP/IP and IP Indoor fixed mini dome camera-ceiling mounted, including all accessories, testing, commissioning and configuration of the network and other Works as shown on the Contract drawings and specified in the Contract documents.
A9: 2.0 | B9: Fire Detection and Alarm
A10: a. | B10: Fire alarm control panel (FACP)
B11: Supply, installation, testing and commissioning of a microprocessor based, addressable fire alarm control panel, complete with Chassis, 640-Character backlit LCD display, QWERTY programming and control keypad, loop cards, zone and input/output modules, supervisory devices, auxiliary relays, network capability modules, battery, battery charger, printer, internal alarm, interface contacts and all accessories and hardware as shown on the Contract drawings and specified in the Contract documents and to complete the fully functional, operable, reliable and maintainable fire alarm system.
A12: a.1 | B12: Microprocessor based, addressable FACP,5 loop type | C12: 3 | D12: Ea | E12: 22795 | F12: 2.7 | G12: =C12-F12 -> 0.3 | H12: =F12+G12 -> 3 | I12: =E12*F12 -> 61546.5 | J12: =G12*E12 -> 6838.5 | K12: =I12+J12 -> 68385 | L12: =H12/C12 -> 1 | M12: 16900 | N12: 80 | O12: =C12*(M12+N12) -> 50940 | P12: =K12-O12 -> 17445
A13: b. | B13: Power supply unit, batteries and battery chargers | C13: 3 | D13: Ea | E13: 4365 | F13: 0 | G13: =C13-F13 -> 3 | H13: =F13+G13 -> 3 | I13: 0 | J13: =G13*E13 -> 13095 | K13: =I13+J13 -> 13095 | L13: =H13/C13 -> 1 | M13: 0 | N13: 0 | O13: =C13*(M13+N13) -> 0 | P13: =K13-O13 -> 13095
B14: Supply, selection and calculation, installation, testing and commissioning of FACP power supply unit, batteries for at least 24 hours during the normal operations and 15 mins under emergency full loaded condition. Provide separate combination of power Supply and battery enclosure when large batteries are required and not be able embedded inside FACP panel.
A15: c. | B15: Detection and initiation devices
B16: Supply, installation, testing and commissioning of intelligent, addressable type fire alarm detectors and initiating devices as shown on the Contract drawings and specified in the Contract documents complete with all mounting accessories including boxes, connectors and terminations.
A17: c.1 | B17: Smoke detector - photoelectric, addressable, self diagnostic, self address | C17: 474 | D17: Ea | E17: 339.5 | F17: 426.33 | G17: =C17-F17 -> 47.67 | H17: =F17+G17 -> 474 | I17: =E17*F17 -> 144739.04 | J17: =G17*E17 -> 16183.965 | K17: =I17+J17 -> 160923 | L17: =H17/C17 -> 1 | M17: 120 | N17: 80 | O17: =C17*(M17+N17) -> 94800 | P17: =K17-O17 -> 66123
A18: c.2 | B18: Heat detector - rate of rise type with fix temperature | C18: 18 | D18: Ea | E18: 291 | F18: 16.25 | G18: =C18-F18 -> 1.75 | H18: =F18+G18 -> 18 | I18: =E18*F18 -> 4728.75 | J18: =G18*E18 -> 509.25 | K18: =I18+J18 -> 5238 | L18: =H18/C18 -> 1 | M18: 110 | N18: 80 | O18: =C18*(M18+N18) -> 3420 | P18: =K18-O18 -> 1818
A19: c.3 | B19: Addressable manual fire alarm pull station | C19: 6 | D19: Ea | E19: 368.6 | F19: 5.4 | G19: =C19-F19 -> 0.6 | H19: =F19+G19 -> 6 | I19: =E19*F19 -> 1990.44 | J19: =G19*E19 -> 221.16 | K19: =I19+J19 -> 2211.6 | L19: =H19/C19 -> 1 | M19: 160 | N19: 80 | O19: =C19*(M19+N19) -> 1440 | P19: =K19-O19 -> 771.6
A20: c.4 | B20: Addressable manual fire alarm pull station, weather proof
A21: d. | B21: Other initiating devices and control devices
B22: Supply, Installation, testing and commissioning of all conventional I/O interfaces devices for interface and Integration with firefighting systems, gas alarm and control systems, lift safety devices, fire water pumps, HVAC systems. elevators and all other specified equipment as per contract drawings and specifications, complete with all mounting accessories including boxes and terminations.
A23: d.1 | B23: Fire alarm monitoring module (MM) | C23: 24 | D23: Ea | E23: 436.5 | F23: 21.6 | G23: =C23-F23 -> 2.4 | H23: =F23+G23 -> 24 | I23: =E23*F23 -> 9428.4 | J23: =G23*E23 -> 1047.6 | K23: =I23+J23 -> 10476 | L23: =H23/C23 -> 1 | M23: 140 | N23: 80 | O23: =C23*(M23+N23) -> 5280 | P23: =K23-O23 -> 5196
A24: e. | B24: Notification appliances
B25: Supply, installation, testing and commissioning of visual and sound alarm devices as shown on the Contract drawings and specified in the Contract documents complete with all mounting accessories including boxes and terminations.
A26: e.1 | B26: Bells, indoor with strobe lights / beacons - red body, red lens for fire alarm | C26: 27 | D26: Ea | E26: 388 | F26: 24.3 | G26: =C26-F26 -> 2.7 | H26: =F26+G26 -> 27 | I26: =E26*F26 -> 9428.4 | J26: =G26*E26 -> 1047.6 | K26: =I26+J26 -> 10476 | L26: =H26/C26 -> 1 | M26: 212 | N26: 80 | O26: =C26*(M26+N26) -> 7884 | P26: =K26-O26 -> 2592
A27: e.2 | B27: Bells, indoor with strobe lights / beacons - red body, red lens for fire alarm, weather proof | C27: 12 | D27: Ea | E27: 436.5 | F27: 10.82 | G27: =C27-F27 -> 1.18 | H27: =F27+G27 -> 12 | I27: =E27*F27 -> 4722.93 | J27: =G27*E27 -> 515.07 | K27: =I27+J27 -> 5238 | L27: =H27/C27 -> 1 | M27: 250 | N27: 80 | O27: =C27*(M27+N27) -> 3960 | P27: =K27-O27 -> 1278
A28: f. | B28: Fire alarm cables - fire resistant cable, 300V/500V, red sheath with low emission of smoke, halogen free, thermoplastic material
B29: To include for the procurement, supply, factory testing, delivery to Site, installation, testing and commissioning of the cables, termination materials and all cable support and wiring, identification accessories.
A30: f.1 | B30: 2C x 2.5 mm², Stranded plain copper wire or solid conductor, overall shield with drain wire for SLC loop | C30: 3600 | D30: m | E30: 24.25 | F30: 3434 | G30: =C30-F30 -> 166 | H30: =F30+G30 -> 3600 | I30: =E30*F30 -> 83274.5 | J30: =G30*E30 -> 4025.5 | K30: =I30+J30 -> 87300 | L30: =H30/C30 -> 1 | M30: 8 | N30: 0 | O30: =C30*(M30+N30) -> 28800 | P30: =K30-O30 -> 58500
A31: f.2 | B31: 2C x 2.5 mm², Stranded plain copper wire or solid conductor, overall shield with drain wire for NAC Loop | C31: 1800 | D31: m | E31: 24.25 | F31: 1717 | G31: =C31-F31 -> 83 | H31: =F31+G31 -> 1800 | I31: =E31*F31 -> 41637.25 | J31: =G31*E31 -> 2012.75 | K31: =I31+J31 -> 43650 | L31: =H31/C31 -> 1 | M31: 8 | N31: 0 | O31: =C31*(M31+N31) -> 14400 | P31: =K31-O31 -> 29250
A32: g. | B32: Fire alarm cable conduit, all JB boxes, fittings and accessories for cable installations
B33: To include for the procurement, supply, installation of PVC conduits and flexible metallic conduits for fire cables, junction boxes, fittings, accessories and all other relevant items or Works to complete fully Fire alarm detection system installations.
A34: g.1 | B34: 20 mm diameter, PVC conduits | C34: 0 | D34: m | E34: 24.25 | F34: 0 | G34: 0 | H34: =F34+G34 -> 0 | I34: =E34*F34 -> 0 | J34: =G34*E34 -> 0 | K34: =I34+J34 -> 0
B35: SUB-TOTAL ITEM NO. B1-28 00 00 | C35: xxx | D35: xxx | I35: =SUM(I12:I34) -> 361496.2 | J35: =SUM(J12:J34) -> 45496.395 | K35: =SUM(K12:K34) -> 406992.6 | O35: =SUM(O11:O34) -> 210924 | P35: =SUM(P11:P34) -> 196068.6
A36: 4.0 | B36: (TO BE CARRIED TO COMPOSITE SUMMARY)
A37: a.
B38: OWNER | C38: CONSULTANT | I38: CONTRACTOR

Sheet SENIOR-EXT
C5: SENIOR
A6: SECTION 2- SCHEDULE OF QUANTITIES AND PRICES | C6: B O Q | F6: THE ACTUAL QTY | I6: AMOUNT (SR) | L6: Percentage
A7: PAY ITEM NO. | B7: DESCRIPTION OF ITEM | C7: ESTIMATED QUANTITY | D7: UNIT | E7: UNIT PRICE(SR) EXCL. VAT | F7: Previous QTY | G7: Current QTY | H7: Cumulative QTY | I7: Previous | J7: Current | K7: Cumulative | M7: Actual price | N7: Actual Labour charge | O7: Total AP+LC | P7: Profit
B8: DIVISION 10 - SPECIALTIES
A9: 2.0 | B9: Fire Extinguishers
B10: Includes mounting brackets, fasteners, service tags, fully charged and ready to use extinguishers.
A11: a. | B11: Multipurpose dry chemical type, UL rated ABC
A12: a.1 | B12: FE-1, 6 kg, multi purpose fire extinguisher | C12: =14*3 -> 42 | D12: Ea | E12: 250 | F12: 32 | G12: =C12-F12 -> 10 | H12: =F12+G12 -> 42 | I12: =E12*F12 -> 8000 | J12: =G12*E12 -> 2500 | K12: =I12+J12 -> 10500 | L12: =H12/C12 -> 1 | M12: 240 | N12: 10 | O12: =C12*(M12+N12) -> 10500 | P12: =K12-O12 -> 0
A13: b. | B13: Automatic fire extinguisher
A14: b.1 | B14: FE-3, 15 kg, multi purpose fire extinguisher, ceiling mounted | C14: 12 | D14: Ea | E14: 631 | F14: 12 | G14: =C14-F14 -> 0 | H14: =F14+G14 -> 12 | I14: =E14*F14 -> 7572 | J14: =E14*G14 -> 0 | K14: =I14+J14 -> 7572 | L14: =H14/C14 -> 1 | M14: 334 | N14: 10 | O14: =C14*(M14+N14) -> 4128 | P14: =K14-O14 -> 3444
B15: SUB-TOTAL ITEM NO. B4-10 00 00 | C15: xxx | D15: xxx | I15: =SUM(I9:I14) -> 15572 | J15: =SUM(J9:J14) -> 2500 | K15: =SUM(K9:K14) -> 18072 | O15: =SUM(O9:O14) -> 14628 | P15: =SUM(P9:P14) -> 3444

Sheet SENIOR
C3: SENIOR
A4: SECTION 2- SCHEDULE OF QUANTITIES AND PRICES | C4: B O Q | F4: THE ACTUAL QTY | I4: AMOUNT (SR)
A5: PAY ITEM NO. | B5: DESCRIPTION OF ITEM | C5: ESTIMATED QUANTITY | D5: UNIT | E5: UNIT PRICE(SR) EXCL. VAT | F5: Previous QTY | G5: Current QTY | H5: Cumulative QTY | I5: Previous | J5: Current | K5: Cumulative | L5: Percentage | M5: Actual price | N5: accessories | O5: Actual Labour charge | P5: Total AP+LC | Q5: Profit
B6: DIVISION 21 - FIRE SUPPRESSION
A7: 1.0 | B7: General-Duty Valves for Water-Based Fire-Suppression Piping
B8: Supply and installation of valves including all fixings, supports, all other accessories and associated Works.
A9: a. | B9: Gate valve, UL and FM global approved
A10: a.1 | B10: 150 mm diameter | C10: 6 | D10: Ea | E10: 3686 | F10: 5.4 | G10: =C10-F10 -> 0.6 | H10: =F10+G10 -> 6 | I10: =E10*F10 -> 19904.4 | J10: =G10*E10 -> 2211.6 | K10: =I10+J10 -> 22116 | L10: =H10/C10 -> 1 | M10: 1250 | N10: 100 | O10: 300 | P10: =C10*(M10+N10+O10) -> 9900 | Q10: =K10-P10 -> 12216
A11: b. | B11: Alarm check valve, UL and FM global approved
A12: b.1 | B12: 150 mm diameter | C12: 3 | D12: Ea | E12: 5577.5 | F12: 2.7 | G12: =C12-F12 -> 0.3 | H12: =F12+G12 -> 3 | I12: =E12*F12 -> 15059.25 | J12: =G12*E12 -> 1673.25 | K12: =I12+J12 -> 16732.5 | L12: =H12/C12 -> 1 | M12: 3830 | N12: 200 | O12: 100 | P12: =C12*(M12+N12+O12) -> 12390 | Q12: =K12-P12 -> 4342.5
A13: c. | B13: Zone control valve assembly
A14: c.1 | B14: 150 mm diameter | C14: 9 | D14: Ea | E14: 5626 | F14: 8.1 | G14: =C14-F14 -> 0.9 | H14: =F14+G14 -> 9 | I14: =E14*F14 -> 45570.6 | J14: =G14*E14 -> 5063.4 | K14: =I14+J14 -> 50634 | L14: =H14/C14 -> 1 | M14: 3000 | N14: 150 | O14: 100 | P14: =C14*(M14+N14+O14) -> 29250 | Q14: =K14-P14 -> 21384
A15: 2.0 | B15: Fire-Department Connections
B16: Two way, swivel fittings, Dust caps and chains of same material as body, chrome plated finish and threads to match local fire department hardware
A17: a. | B17: Flush wall mounted fire department connection with check valve
A18: a.1 | B18: Two-way swivel fittings, 65 x 65 x 100 mm single clapper Siamese-type connections | C18: 3 | D18: Ea | E18: 4462 | F18: 2.7 | G18: =C18-F18 -> 0.3 | H18: =F18+G18 -> 3 | I18: =E18*F18 -> 12047.4 | J18: =G18*E18 -> 1338.6 | K18: =I18+J18 -> 13386 | L18: =H18/C18 -> 1 | M18: 450 | N18: 150 | O18: 100 | P18: =C18*(M18+N18+O18) -> 2100 | Q18: =K18-P18 -> 11286
A19: 3.0 | B19: Wet-Pipe Sprinkler Systems
A20: a. | B20: Black steel fire water pipes
B21: Supply and installation of black steel pipe seamless type as per ASTM A53 including supports, hangers, fixing, fitting, all other accessories and associated Works as per Contract drawings and specifications.
A22: a.1 | B22: 25 mm diameter | C22: 1485 | D22: m | E22: 53.35 | F22: 1491.4417 | G22: =C22-F22 -> -6.4416667 | H22: =F22+G22 -> 1485 | I22: =E22*F22 -> 79568.413 | J22: =G22*E22 -> -343.66292 | K22: =I22+J22 -> 79224.75 | L22: =(H22/C22) -> 1 | M22: 15 | N22: 7.5 | O22: 0 | P22: =C22*(M22+N22+O22) -> 33412.5 | Q22: =K22-P22 -> 45812.25
A23: a.2 | B23: 32 mm diameter | C23: 90 | D23: m | E23: 63.05 | F23: 89.95 | G23: =C23-F23 -> 0.05 | H23: =F23+G23 -> 90 | I23: =E23*F23 -> 5671.3475 | J23: =G23*E23 -> 3.1525 | K23: =I23+J23 -> 5674.5 | L23: =(H23/C23) -> 1 | M23: 20 | N23: 10 | O23: 0 | P23: =C23*(M23+N23+O23) -> 2700 | Q23: =K23-P23 -> 2974.5
A24: a.3 | B24: 40 mm diameter | C24: 135 | D24: m | E24: 77.6 | F24: 134.38333 | G24: =C24-F24 -> 0.61666667 | H24: =F24+G24 -> 135 | I24: =E24*F24 -> 10428.147 | J24: =G24*E24 -> 47.853333 | K24: =I24+J24 -> 10476 | L24: =(H24/C24) -> 1 | M24: 24 | N24: 12 | O24: 0 | P24: =C24*(M24+N24+O24) -> 4860 | Q24: =K24-P24 -> 5616
A25: a.4 | B25: 50 mm diameter | C25: 90 | D25: m | E25: 95.06 | F25: 89.625 | G25: =C25-F25 -> 0.375 | H25: =F25+G25 -> 90 | I25: =E25*F25 -> 8519.7525 | J25: =G25*E25 -> 35.6475 | K25: =I25+J25 -> 8555.4 | L25: =(H25/C25) -> 1 | M25: 28 | N25: 14 | O25: 0 | P25: =C25*(M25+N25+O25) -> 3780 | Q25: =K25-P25 -> 4775.4
A26: a.5 | B26: 65 mm diameter | C26: 345 | D26: m | E26: 169.75 | F26: 343.61667 | G26: =C26-F26 -> 1.3833333 | H26: =F26+G26 -> 345 | I26: =E26*F26 -> 58328.929 | J26: =G26*E26 -> 234.82083 | K26: =I26+J26 -> 58563.75 | L26: =(H26/C26) -> 1 | M26: 30 | N26: 15 | O26: 0 | P26: =C26*(M26+N26+O26) -> 15525 | Q26: =K26-P26 -> 43038.75
A27: a.6 | B27: 80 mm diameter | C27: 180 | D27: m | E27: 190.12 | F27: 179.86667 | G27: =C27-F27 -> 0.13333333 | H27: =F27+G27 -> 180 | I27: =E27*F27 -> 34196.251 | J27: =G27*E27 -> 25.349333 | K27: =I27+J27 -> 34221.6 | L27: =(H27/C27) -> 1 | M27: 35 | N27: 25 | O27: 0 | P27: =C27*(M27+N27+O27) -> 10800 | Q27: =K27-P27 -> 23421.6
A28: a.7 | B28: 100 mm diameter | C28: 30 | D28: m | E28: 237.65 | F28: 30 | G28: =C28-F28 -> 0 | H28: =F28+G28 -> 30 | I28: =E28*F28 -> 7129.5 | J28: =G28*E28 -> 0 | K28: =I28+J28 -> 7129.5 | L28: =(H28/C28) -> 1 | M28: 90 | N28: 60 | O28: 0 | P28: =C28*(M28+N28+O28) -> 4500 | Q28: =K28-P28 -> 2629.5
A29: a.8 | B29: 150 mm diameter | C29: =40*3 -> 120 | D29: m | E29: 344.35 | F29: 119.5 | G29: =C29-F29 -> 0.5 | H29: =F29+G29 -> 120 | I29: =E29*F29 -> 41149.825 | J29: =G29*E29 -> 172.175 | K29: =I29+J29 -> 41322 | L29: =(H29/C29) -> 1 | M29: 170 | N29: 90 | O29: 0 | P29: =C29*(M29+N29+O29) -> 31200 | Q29: =K29-P29 -> 10122
A30: b. | B30: Fire water sprinkler head
B31: Sprinkler Head, UL listed FM approved, chrome-plated, bronze and factory painted; Shall be of one manufacturer. (No mixing of sprinkler brands shall be permitted).
A32: b.1 | B32: Pendent type | C32: 546 | D32: Ea | E32: 63.05 | F32: 491.4 | G32: =C32-F32 -> 54.6 | H32: =F32+G32 -> 546 | I32: =E32*F32 -> 30982.77 | J32: =G32*E32 -> 3442.53 | K32: =I32+J32 -> 34425.3 | L32: =H32/C32 -> 1 | M32: 25 | N32: 5 | O32: 100 | P32: =C32*(M32+N32+O32) -> 70980 | Q32: =K32-P32 -> -36554.7
A33: b.2 | B33: Upright type | C33: =6*3 -> 18 | D33: Ea | E33: 33.95 | F33: 16.2 | G33: =C33-F33 -> 1.8 | H33: =F33+G33 -> 18 | I33: =E33*F33 -> 549.99 | J33: =G33*E33 -> 61.11 | K33: =I33+J33 -> 611.1 | L33: =H33/C33 -> 1 | M33: 19 | N33: 5 | O33: 100 | P33: =C33*(M33+N33+O33) -> 2232 | Q33: =K33-P33 -> -1620.9
A34: b.3 | B34: Wall side type | C34: 336 | D34: Ea | E34: 72.75 | F34: 301.3 | G34: =C34-F34 -> 34.7 | H34: =F34+G34 -> 336 | I34: =E34*F34 -> 21919.575 | J34: =G34*E34 -> 2524.425 | K34: =I34+J34 -> 24444 | L34: =H34/C34 -> 1 | M34: 59 | N34: 5 | O34: 100 | P34: =C34*(M34+N34+O34) -> 55104 | Q34: =K34-P34 -> -30660
A35: 4.0 | B35: Fire-Suppression Standpipes
A36: a. | B36: Fire Hose Cabinet
B37: Supply and installation of Surface mounted fire hose Cabinets Made of Stainless Steel, dimension (W 750 x H 850 x D 180). with Synthetic Single Jacket Hose 1.5” x 30 meter long and (1) multipurpose dry powder Extinguisher include fittings, joints, unions, dielectric fittings, flanges, gaskets, grooved mechanical couplings, nuts and bolts, hangers and supports and labelling.
A38: a.1 | B38: FHC-II | C38: =6*3 -> 18 | D38: Ea | E38: 4704.5 | F38: 18 | G38: =C38-F38 -> 0 | H38: =F38+G38 -> 18 | I38: =E38*F38 -> 84681 | J38: =G38*E38 -> 0 | K38: =I38+J38 -> 84681 | L38: =H38/C38 -> 1 | M38: 4200 | N38: 250 | O38: 400 | P38: =C38*(M38+N38+O38) -> 87300 | Q38: =K38-P38 -> -2619
B39: SUB-TOTAL ITEM NO. B4-21 00 00 | C39: xxx | D39: xxx | I39: =SUM(I9:I38) -> 475707.15 | J39: =SUM(J9:J38) -> 16490.251 | K39: =SUM(K9:K38) -> 492197.4 | P39: =SUM(P9:P38) -> 376033.5 | Q39: =SUM(Q9:Q38) -> 116163.9
B40: (TO BE CARRIED TO COMPOSITE SUMMARY) | C40: 0
B42: OWNER | C42: CONSULTANT | I42: CONTRACTOR

Sheet ADMIN -E
C4: ADMIN - E
A5: SECTION 2- SCHEDULE OF QUANTITIES AND PRICES | C5: B O Q | F5: THE ACTUAL QTY | I5: AMOUNT (SR)
A6: PAY ITEM NO. | B6: DESCRIPTION OF ITEM | C6: ESTIMATED QUANTITY | D6: UNIT | E6: UNIT PRICE(SR) EXCL. VAT | F6: Previous QTY | G6: Current QTY | H6: Cumulative QTY | I6: Previous | J6: Current | K6: Cumulative | L6: Percentage | M6: Actual price | N6: Actual Labour charge | O6: Total AP+LC | P6: Profit
B7: DIVISION 28-ELECTRONIC SAFETY AND SECURITY
A8: 2.0 | B8: Fire Detection and Alarm
A9: a. | B9: Fire alarm control panel (FACP)
B10: Supply, installation, testing and commissioning of a microprocessor based, addressable fire alarm control panel, complete with Chassis, 640-Character backlit LCD display, QWERTY programming and control keypad, loop cards, zone and input/output modules, supervisory devices, auxiliary relays, network capability modules, battery, battery charger, printer, internal alarm, interface contacts and all accessories and hardware as shown on the Contract drawings and specified in the Contract documents and to complete the fully functional, operable, reliable and maintainable fire alarm system.
A11: a.1 | B11: Microprocessor based, addressable FACP,5 loop type | C11: 1 | D11: Ea | E11: 22795 | F11: 0.9 | G11: =C11-F11 -> 0.1 | H11: =F11+G11 -> 1 | I11: =E11*F11 -> 20515.5 | J11: =G11*E11 -> 2279.5 | K11: =I11+J11 -> 22795 | L11: =H11/C11 -> 1 | M11: 16900 | N11: 80 | O11: =C11*(M11+N11) -> 16980 | P11: =K11-O11 -> 5815
A12: b. | B12: Power supply unit, batteries and battery chargers | C12: 1 | D12: Ea | E12: 4365 | F12: 0 | G12: =C12-F12 -> 1 | H12: =F12+G12 -> 1 | I12: =E12*F12 -> 0 | J12: =G12*E12 -> 4365 | K12: =I12+J12 -> 4365 | L12: =H12/C12 -> 1 | M12: 0 | N12: 0 | O12: =C12*(M12+N12) -> 0 | P12: =K12-O12 -> 4365
B13: Supply, selection and calculation, installation, testing and commissioning of FACP power supply unit, batteries for at least 24 hours during the normal operations and 15 mins under emergency full loaded condition. Provide separate combination of power Supply and battery enclosure when large batteries are required and not be able embedded inside FACP panel.
A14: c. | B14: Detection and initiation devices
B15: Supply, installation, testing and commissioning of intelligent, addressable type fire alarm detectors and initiating devices as shown on the Contract drawings and specified in the Contract documents complete with all mounting accessories including boxes, connectors and terminations.
A16: c.1 | B16: Smoke detector - photoelectric, addressable, self diagnostic, self address | C16: 52 | D16: Ea | E16: 339.5 | F16: 46.8 | G16: =C16-F16 -> 5.2 | H16: =F16+G16 -> 52 | I16: =E16*F16 -> 15888.6 | J16: =G16*E16 -> 1765.4 | K16: =I16+J16 -> 17654 | L16: =H16/C16 -> 1 | M16: 120 | N16: 80 | O16: =C16*(M16+N16) -> 10400 | P16: =K16-O16 -> 7254
A17: c.2 | B17: Heat detector - rate of rise type with fix temperature | C17: 2 | D17: Ea | E17: 291 | F17: 1.8 | G17: =C17-F17 -> 0.2 | H17: =F17+G17 -> 2 | I17: =E17*F17 -> 523.8 | J17: =G17*E17 -> 58.2 | K17: =I17+J17 -> 582 | L17: =H17/C17 -> 1 | M17: 110 | N17: 80 | O17: =C17*(M17+N17) -> 380 | P17: =K17-O17 -> 202
A18: c.3 | B18: Addressable manual fire alarm pull station | C18: 4 | D18: Ea | E18: 368.6 | F18: 3.6 | G18: =C18-F18 -> 0.4 | H18: =F18+G18 -> 4 | I18: =E18*F18 -> 1326.96 | J18: =G18*E18 -> 147.44 | K18: =I18+J18 -> 1474.4 | L18: =H18/C18 -> 1 | M18: 160 | N18: 80 | O18: =C18*(M18+N18) -> 960 | P18: =K18-O18 -> 514.4
A19: d. | B19: Other initiating devices and control devices
B20: Supply, Installation, testing and commissioning of all conventional I/O interfaces devices for interface and Integration with firefighting systems, gas alarm and control systems, lift safety devices, fire water pumps, HVAC systems. elevators and all other specified equipment as per contract drawings and specifications, complete with all mounting accessories including boxes and terminations.
A21: d.1 | B21: Fire alarm monitoring module (MM) | C21: 3 | D21: Ea | E21: 436.5 | F21: 2.7 | G21: =C21-F21 -> 0.3 | H21: =F21+G21 -> 3 | I21: =E21*F21 -> 1178.55 | J21: =G21*E21 -> 130.95 | K21: =I21+J21 -> 1309.5 | L21: =H21/C21 -> 1 | M21: 140 | N21: 80 | O21: =C21*(M21+N21) -> 660 | P21: =K21-O21 -> 649.5
A22: e. | B22: Notification appliances
B23: Supply, installation, testing and commissioning of visual and sound alarm devices as shown on the Contract drawings and specified in the Contract documents complete with all mounting accessories including boxes and terminations.
A24: e.1 | B24: Bells, indoor with strobe lights / beacons - red body, red lens for fire alarm | C24: 4 | D24: Ea | E24: 388 | F24: 0 | G24: =C24-F24 -> 4 | H24: =F24+G24 -> 4 | I24: =E24*F24 -> 0 | J24: =G24*E24 -> 1552 | K24: =I24+J24 -> 1552 | L24: =H24/C24 -> 1 | M24: 212 | N24: 80 | O24: =C24*(M24+N24) -> 1168 | P24: =K24-O24 -> 384
A25: e.2 | B25: Bells, indoor with strobe lights / beacons - red body, red lens for fire alarm, weather proof | C25: 2 | D25: Ea | E25: 436.5 | F25: 0 | G25: =C25-F25 -> 2 | H25: =F25+G25 -> 2 | I25: =E25*F25 -> 0 | J25: =G25*E25 -> 873 | K25: =I25+J25 -> 873 | L25: =H25/C25 -> 1 | M25: 250 | N25: 80 | O25: =C25*(M25+N25) -> 660 | P25: =K25-O25 -> 213
A26: f. | B26: Fire alarm cables - fire resistant cable, 300V/500V, red sheath with low emission of smoke, halogen free, thermoplastic material
B27: To include for the procurement, supply, factory testing, delivery to Site, installation, testing and commissioning of the cables, termination materials and all cable support and wiring, identification accessories.
A28: f.1 | B28: 2C x 2.5 mm², Stranded plain copper wire or solid conductor, overall shield with drain wire for SLC loop | C28: 800 | D28: m | E28: 24.25 | F28: 760 | G28: =C28-F28 -> 40 | H28: =F28+G28 -> 800 | I28: =E28*F28 -> 18430 | J28: =G28*E28 -> 970 | K28: =I28+J28 -> 19400 | L28: =H28/C28 -> 1 | M28: 8 | N28: 0 | O28: =C28*(M28+N28) -> 6400 | P28: =K28-O28 -> 13000
A29: f.2 | B29: 2C x 2.5 mm², Stranded plain copper wire or solid conductor, overall shield with drain wire for NAC Loop | C29: 400 | D29: m | E29: 24.25 | F29: 380 | G29: =C29-F29 -> 20 | H29: =F29+G29 -> 400 | I29: =E29*F29 -> 9215 | J29: =G29*E29 -> 485 | K29: =I29+J29 -> 9700 | L29: =H29/C29 -> 1 | M29: 8 | N29: 0 | O29: =C29*(M29+N29) -> 3200 | P29: =K29-O29 -> 6500
A30: g. | B30: Fire alarm cable conduit, all JB boxes, fittings and accessories for cable installations
B31: To include for the procurement, supply, installation of PVC conduits and flexible metallic conduits for fire cables, junction boxes, fittings, accessories and all other relevant items or Works to complete fully Fire alarm detection system installations.
A32: g.1 | B32: 20 mm diameter, PVC conduits
A33: h. | B33: Fire Alarm Workstations (WS) | C33: 1 | D33: Ea | E33: 63632 | F33: 0 | G33: =C33-F33 -> 1 | H33: =F33+G33 -> 1 | I33: =E33*F33 -> 0 | J33: =G33*E33 -> 63632 | K33: =I33+J33 -> 63632 | L33: =H33/C33 -> 1 | M33: 25800 | N33: 0 | O33: =C33*(M33+N33) -> 25800 | P33: =K33-O33 -> 37832
A34: i. | B34: Fire Alarm Fault/Short circuit isolator | C34: 2 | D34: Ea | E34: 1455 | F34: 0 | G34: =C34-F34 -> 2 | H34: =F34+G34 -> 2 | I34: =E34*F34 -> 0 | J34: =G34*E34 -> 2910 | K34: =I34+J34 -> 2910 | L34: =H34/C34 -> 1 | M34: 250 | N34: 0 | O34: =C34*(M34+N34) -> 500 | P34: =K34-O34 -> 2410
B35: SUB-TOTAL ITEM NO. B7-28 00 00 | C35: xxx | D35: xxx | I35: =SUM(I11:I34) -> 67078.41 | J35: =SUM(J11:J34) -> 79168.49 | K35: =SUM(K11:K34) -> 146246.9 | O35: =SUM(O11:O34) -> 67108 | P35: =SUM(P11:P34) -> 79138.9
B36: (TO BE CARRIED TO COMPOSITE SUMMARY)
B38: OWNER | C38: CONSULTANT | I38: CONTRACTOR

Sheet ADMIN-EXT
C5: ADMIN
A6: SECTION 2- SCHEDULE OF QUANTITIES AND PRICES | C6: B O Q | F6: THE ACTUAL QTY | I6: AMOUNT (SR) | L6: Percentage
A7: PAY ITEM NO. | B7: DESCRIPTION OF ITEM | C7: ESTIMATED QUANTITY | D7: UNIT | E7: UNIT PRICE(SR) EXCL. VAT | F7: Previous QTY | G7: Current QTY | H7: Cumulative QTY | I7: Previous | J7: Current | K7: Cumulative | M7: Actual price | N7: Actual Labour charge | O7: Total AP+LC | P7: Profit
B8: DIVISION 10 - SPECIALTIES
A9: 1.0 | B9: Fire Extinguishers
B10: Includes mounting brackets, fasteners, service tags, fully charged and ready to use extinguishers.
A11: a. | B11: Multipurpose dry chemical type, UL rated ABC
A12: a.1 | B12: FE-1, 6 kg, multi purpose fire extinguisher | C12: 7 | D12: Ea | E12: 242.5 | F12: 5 | G12: =C12-F12 -> 2 | H12: =F12+G12 -> 7 | I12: =E12*F12 -> 1212.5 | J12: =G12*E12 -> 485 | K12: =I12+J12 -> 1697.5 | L12: =H12/C12 -> 1 | M12: 240 | N12: 10 | O12: =C12*(M12+N12) -> 1750 | P12: =K12-O12 -> -52.5
A13: b. | B13: Wet chemical type, UL rated class K | E13: 0
A14: b.1 | B14: FE-3, kitchen type-K fire extinguisher 2 gallon | C14: 2 | D14: Ea | E14: 533.5 | F14: 1.3 | G14: =C14-F14 -> 0.7 | H14: =F14+G14 -> 2 | I14: =E14*F14 -> 693.55 | J14: =G14*E14 -> 373.45 | K14: =I14+J14 -> 1067 | L14: =H14/C14 -> 1 | M14: 320 | N14: 10 | O14: =C14*(M14+N14) -> 660 | P14: =K14-O14 -> 407
A15: c. | B15: Automatic fire extinguisher
A16: c.1 | B16: AFE-3, 15 kg, multi purpose fire extinguisher, ceiling mounted | C16: 1 | D16: Ea | E16: 485 | F16: 0.65 | G16: =C16-F16 -> 0.35 | H16: =F16+G16 -> 1 | I16: =E16*F16 -> 315.25 | J16: =G16*E16 -> 169.75 | K16: =I16+J16 -> 485 | L16: =H16/C16 -> 1 | M16: 334 | N16: 10 | O16: =C16*(M16+N16) -> 344 | P16: =K16-O16 -> 141
A17: c.2 | B17: AFE-4, 20 kg, multi purpose fire extinguisher, ceiling mounted | C17: 2 | D17: Ea | E17: 582 | F17: 0 | G17: =C17-F17 -> 2 | H17: =F17+G17 -> 2 | I17: =E17*F17 -> 0 | J17: =G17*E17 -> 1164 | K17: =I17+J17 -> 1164 | L17: =H17/C17 -> 1 | M17: 424 | N17: 10 | O17: =C17*(M17+N17) -> 868 | P17: =K17-O17 -> 296
A18: d. | B18: Fire blanket
B19: Supply and installation of fire blanket of specified type to be located in kitchen with all fittings and supports required to provide satisfactory operation.
A20: d.1 | B20: Fire blanket, standard size (1.2 meter x 1.2 meter), NFPA approved | C20: 2 | D20: Ea | E20: 291 | F20: 2 | G20: =C20-F20 -> 0 | H20: =F20+G20 -> 2 | I20: =E20*F20 -> 582 | J20: =G20*E20 -> 0 | K20: =I20+J20 -> 582 | L20: =H20/C20 -> 1 | M20: 16 | N20: 10 | O20: =C20*(M20+N20) -> 52 | P20: =K20-O20 -> 530
B21: SUB-TOTAL ITEM NO. B7-10 00 00 | C21: xxx | D21: xxx | I21: =SUM(I9:I20) -> 2803.3 | J21: =SUM(J9:J20) -> 2192.2 | K21: =SUM(K9:K20) -> 4995.5 | O21: =SUM(O10:O20) -> 3674 | P21: =SUM(P10:P20) -> 1321.5

Sheet ADMIN
C3: ADMIN
A4: SECTION 2- SCHEDULE OF QUANTITIES AND PRICES | C4: B O Q | F4: THE ACTUAL QTY | I4: AMOUNT (SR)
A5: PAY ITEM NO. | B5: DESCRIPTION OF ITEM | C5: ESTIMATED QUANTITY | D5: UNIT | E5: UNIT PRICE(SR) EXCL. VAT | F5: Previous QTY | G5: Current QTY | H5: Cumulative QTY | I5: Previous | J5: Current | K5: Cumulative | L5: Percentage | M5: Actual price | N5: accessories | O5: Actual Labour charge | P5: Total AP+LC | Q5: Profit
B6: DIVISION 21 - FIRE SUPPRESSION
A7: 1.0 | B7: Fire-Department Connections
A8: a. | B8: Flush wall mounted fire department connection with check valve
B9: Two way, swivel fittings, Dust caps and chains of same material as body, chrome plated finish and threads to match local fire department hardware
A10: a.1 | B10: Two-way swivel fittings, 65 x 65 x 100 mm single clapper Siamese-type connections | C10: 1 | D10: Ea | E10: 4462 | F10: 0.65 | G10: =C10-F10 -> 0.35 | H10: =F10+G10 -> 1 | I10: =E10*F10 -> 2900.3 | J10: =G10*E10 -> 1561.7 | K10: =I10+J10 -> 4462 | L10: =H10/C10 -> 1 | M10: 450 | N10: 150 | O10: 100 | P10: =C10*(M10+N10+O10) -> 700 | Q10: =K10-P10 -> 3762
A11: 2.0 | B11: Fire-Suppression Standpipes
A12: a. | B12: Fire Hose Cabinet
B13: Supply and installation of Surface mounted fire hose Cabinets Made of Stainless Steel, dimension (W 750 x H 850 x D 180). with Synthetic Single Jacket Hose 1.5” x 30 meter long and (1) multipurpose dry powder Extinguisher include fittings, joints, unions, dielectric fittings, flanges, gaskets, grooved mechanical couplings, nuts and bolts, hangers and supports and labelling.
A14: a.1 | B14: FHC-II | C14: 4 | D14: Ea | E14: 4462 | F14: 4 | G14: =C14-F14 -> 0 | H14: =F14+G14 -> 4 | I14: =E14*F14 -> 17848 | J14: =G14*E14 -> 0 | K14: =I14+J14 -> 17848 | L14: =H14/C14 -> 1 | M14: 4200 | N14: 250 | O14: 400 | P14: =C14*(M14+N14+O14) -> 19400 | Q14: =K14-P14 -> -1552
A15: 3.0 | B15: Wet-Pipe Sprinkler Systems
A16: a. | B16: Black steel fire water pipes
B17: Supply and installation of black steel pipe seamless type as per ASTM A53 including supports, hangers, fixing, fitting, all other accessories and associated Works as per Contract drawings and specifications.
A18: a.1 | B18: 40 mm diameter | C18: 40 | D18: m | E18: 77.6 | F18: 40 | G18: =C18-F18 -> 0 | H18: =F18+G18 -> 40 | I18: =E18*F18 -> 3104 | J18: =G18*E18 -> 0 | K18: =I18+J18 -> 3104 | L18: =(H18/C18) -> 1 | M18: 24 | N18: 12 | O18: 0 | P18: =C18*(M18+N18+O18) -> 1440 | Q18: =K18-P18 -> 1664
A19: a.2 | B19: 50 mm diameter | C19: 30 | D19: m | E19: 95.06 | F19: 30 | G19: =C19-F19 -> 0 | H19: =F19+G19 -> 30 | I19: =E19*F19 -> 2851.8 | J19: =G19*E19 -> 0 | K19: =I19+J19 -> 2851.8 | L19: =(H19/C19) -> 1 | M19: 28 | N19: 14 | O19: 0 | P19: =C19*(M19+N19+O19) -> 1260 | Q19: =K19-P19 -> 1591.8
A20: a.3 | B20: 65 mm diameter | C20: 30 | D20: m | E20: 169.75 | F20: 30 | G20: =C20-F20 -> 0 | H20: =F20+G20 -> 30 | I20: =E20*F20 -> 5092.5 | J20: =G20*E20 -> 0 | K20: =I20+J20 -> 5092.5 | L20: =(H20/C20) -> 1 | M20: 30 | N20: 15 | O20: 0 | P20: =C20*(M20+N20+O20) -> 1350 | Q20: =K20-P20 -> 3742.5
A21: a.4 | B21: 100 mm diameter | C21: 10 | D21: m | E21: 237.65 | F21: 10 | G21: =C21-F21 -> 0 | H21: =F21+G21 -> 10 | I21: =E21*F21 -> 2376.5 | J21: =G21*E21 -> 0 | K21: =I21+J21 -> 2376.5 | L21: =(H21/C21) -> 1 | M21: 90 | N21: 60 | O21: 0 | P21: =C21*(M21+N21+O21) -> 1500 | Q21: =K21-P21 -> 876.5
A22: 4.0 | B22: Clean-Agent Fire-Extinguishing Systems
A23: a. | B23: Clean agent modular cylinder with piping, sprinkler heads, nozzles, electric actuator, Instruments Accessories
B24: Piping, fittings, joints, unions, dielectric fittings, flanges, gaskets, grooved mechanical couplings, nuts and bolts, hangers and supports, labeling, discharge manifold - including all piping, valves, controls and support, extinguishing agent containers - including extinguishing agent (less than 999 kg), safety devices and safety brackets, discharge nozzles, control panel (FM approved or UL Listed) - including cylinder cabinets mounting and all wiring, detection devices, graphic annunciator including mounting and all wiring. Testing and commissioning.
A25: a.1 | B25: 28 kg Set | C25: 2 | D25: Ea | E25: 34435 | F25: 1.6 | G25: =C25-F25 -> 0.4 | H25: =F25+G25 -> 2 | I25: =E25*F25 -> 55096 | J25: =G25*E25 -> 13774 | K25: =I25+J25 -> 68870 | L25: =H25/C25 -> 1 | M25: 19000 | N25: 500 | O25: 1500 | P25: =C25*(M25+N25+O25) -> 42000 | Q25: =K25-P25 -> 26870
A26: a.2 | B26: 56 kg Set | C26: 1 | D26: Ea | E26: 52186 | F26: 0.8 | G26: =C26-F26 -> 0.2 | H26: =F26+G26 -> 1 | I26: =E26*F26 -> 41748.8 | J26: =G26*E26 -> 10437.2 | K26: =I26+J26 -> 52186 | L26: =H26/C26 -> 1 | M26: 30000 | N26: 500 | O26: 1500 | P26: =C26*(M26+N26+O26) -> 32000 | Q26: =K26-P26 -> 20186
B27: SUB-TOTAL ITEM NO. B7-21 00 00 | C27: xxx | D27: xxx | I27: =SUM(I10:I26) -> 131017.9 | J27: =SUM(J10:J26) -> 25772.9 | K27: =SUM(K10:K26) -> 156790.8 | P27: =SUM(P10:P26) -> 99650 | Q27: =SUM(Q10:Q26) -> 57140.8
B28: (TO BE CARRIED TO COMPOSITE SUMMARY)
B30: OWNER | C30: CONSULTANT | J30: CONTRACTOR

Sheet RECREATION - E
C4: REC - E
A5: SECTION 2- SCHEDULE OF QUANTITIES AND PRICES | C5: B O Q | F5: THE ACTUAL QTY | I5: AMOUNT (SR) | L5: Percentage
A6: PAY ITEM NO. | B6: DESCRIPTION OF ITEM | C6: ESTIMATED QUANTITY | D6: UNIT | E6: UNIT PRICE(SR) EXCL. VAT | F6: Previous QTY | G6: Current QTY | H6: Cumulative QTY | I6: Previous | J6: Current | K6: Cumulative | L6: Cumulative | M6: Actual price | N6: Actual Labour charge | O6: Total AP+LC | P6: Profit
B7: DIVISION 28-ELECTRONIC SAFETY AND SECURITY
A8: 2.0 | B8: Fire Detection and Alarm
A9: a. | B9: Fire alarm control panel (FACP)
B10: Supply, installation, testing and commissioning of a microprocessor based, addressable fire alarm control panel, complete with Chassis, 640-Character backlit LCD display, QWERTY programming and control keypad, loop cards, zone and input/output modules, supervisory devices, auxiliary relays, network capability modules, battery, battery charger, printer, internal alarm, interface contacts and all accessories and hardware as shown on the Contract drawings and specified in the Contract documents and to complete the fully functional, operable, reliable and maintainable fire alarm system.
A11: a.1 | B11: Microprocessor based, addressable FACP, 5 loop type | C11: 1 | D11: Ea | E11: 22795 | F11: 0.9 | G11: =C11-F11 -> 0.1 | H11: =F11+G11 -> 1 | I11: =F11*E11 -> 20515.5 | J11: =G11*E11 -> 2279.5 | K11: =I11+J11 -> 22795 | L11: =H11/C11 -> 1 | M11: 16900 | N11: 80 | O11: =C11*(M11+N11) -> 16980 | P11: =K11-O11 -> 5815
A12: b. | B12: Power supply unit, batteries and battery chargers | C12: 1 | D12: Ea | E12: 4365 | F12: 0 | G12: =C12-F12 -> 1 | H12: =F12+G12 -> 1 | I12: =F12*E12 -> 0 | J12: =G12*E12 -> 4365 | K12: =I12+J12 -> 4365 | L12: =H12/C12 -> 1 | M12: 0 | N12: 0 | O12: =C12*(M12+N12) -> 0 | P12: =K12-O12 -> 4365
B13: Supply, selection and calculation, installation, testing and commissioning of FACP power supply unit, batteries for at least 24 hours during the normal operations and 15 mins under emergency full loaded condition. Provide separate combination of power Supply and battery enclosure when large batteries are required and not be able embedded inside FACP panel.
A14: c. | B14: Detection and initiation devices
B15: Supply, installation, testing and commissioning of intelligent, addressable type fire alarm detectors and initiating devices as shown on the Contract drawings and specified in the Contract documents complete with all mounting accessories including boxes, connectors and terminations.
A16: c.1 | B16: Smoke detector - photoelectric, addressable, self diagnostic, self address | C16: 99 | D16: Ea | E16: 339.5 | F16: 89.52 | G16: =C16-F16 -> 9.48 | H16: =F16+G16 -> 99 | I16: =F16*E16 -> 30392.04 | J16: =G16*E16 -> 3218.46 | K16: =I16+J16 -> 33610.5 | L16: =H16/C16 -> 1 | M16: 120 | N16: 80 | O16: =C16*(M16+N16) -> 19800 | P16: =K16-O16 -> 13810.5
A17: c.2 | B17: Air duct smoke detectors with remote LED indicator and test devices | C17: 14 | D17: Ea | E17: 1746 | F17: 12.6 | G17: =C17-F17 -> 1.4 | H17: =F17+G17 -> 14 | I17: =F17*E17 -> 21999.6 | J17: =G17*E17 -> 2444.4 | K17: =I17+J17 -> 24444 | L17: =H17/C17 -> 1 | M17: 250 | N17: 80 | O17: =C17*(M17+N17) -> 4620 | P17: =K17-O17 -> 19824
A18: c.3 | B18: Heat detector - rate of rise type with fix temperature | C18: 2 | D18: Ea | E18: 339.5 | F18: 1.8 | G18: =C18-F18 -> 0.2 | H18: =F18+G18 -> 2 | I18: =F18*E18 -> 611.1 | J18: =G18*E18 -> 67.9 | K18: =I18+J18 -> 679 | L18: =H18/C18 -> 1 | M18: 110 | N18: 80 | O18: =C18*(M18+N18) -> 380 | P18: =K18-O18 -> 299
A19: c.4 | B19: Beam detector transmitter, 50 meter range | C19: 2 | D19: Ea | E19: 2783.9 | F19: 1.3 | G19: =C19-F19 -> 0.7 | H19: =F19+G19 -> 2 | I19: =F19*E19 -> 3619.07 | J19: =G19*E19 -> 1948.73 | K19: =I19+J19 -> 5567.8 | L19: =H19/C19 -> 1 | M19: 180 | N19: 80 | O19: =C19*(M19+N19) -> 520 | P19: =K19-O19 -> 5047.8
A20: c.5 | B20: Beam detector receiver, 50 meter range | C20: 2 | D20: Ea | E20: 2783.9 | F20: 1.3 | G20: =C20-F20 -> 0.7 | H20: =F20+G20 -> 2 | I20: =F20*E20 -> 3619.07 | J20: =G20*E20 -> 1948.73 | K20: =I20+J20 -> 5567.8 | L20: =H20/C20 -> 1 | M20: 180 | N20: 80 | O20: =C20*(M20+N20) -> 520 | P20: =K20-O20 -> 5047.8
A21: c.6 | B21: Addressable manual fire alarm pull station | C21: 12 | D21: Ea | E21: 291 | F21: 10.82 | G21: =C21-F21 -> 1.18 | H21: =F21+G21 -> 12 | I21: =F21*E21 -> 3148.62 | J21: =G21*E21 -> 343.38 | K21: =I21+J21 -> 3492 | L21: =H21/C21 -> 1 | M21: 160 | N21: 80 | O21: =C21*(M21+N21) -> 2880 | P21: =K21-O21 -> 612
A22: d. | B22: Other initiating devices and control devices
B23: Supply, Installation, testing and commissioning of all conventional I/O interfaces devices for interface and Integration with firefighting systems, gas alarm and control systems, lift safety devices, fire water pumps, HVAC systems. elevators and all other specified equipment as per contract drawings and specifications, complete with all mounting accessories including boxes and terminations.
A24: d.1 | B24: Fire alarm monitoring module (MM) | C24: 6 | D24: Ea | E24: 436.5 | F24: 5.4 | G24: =C24-F24 -> 0.6 | H24: =F24+G24 -> 6 | I24: =F24*E24 -> 2357.1 | J24: =G24*E24 -> 261.9 | K24: =I24+J24 -> 2619 | L24: =H24/C24 -> 1 | M24: 140 | N24: 80 | O24: =C24*(M24+N24) -> 1320 | P24: =K24-O24 -> 1299
A25: e. | B25: Notification appliances
B26: Supply, installation, testing and commissioning of visual and sound alarm devices as shown on the Contract drawings and specified in the Contract documents complete with all mounting accessories including boxes and terminations.
A27: e.1 | B27: Bells, indoor with strobe lights / beacons - red body, red lens for fire alarm | C27: 12 | D27: Ea | E27: 388 | F27: 3.9 | G27: =C27-F27 -> 8.1 | H27: =F27+G27 -> 12 | I27: =F27*E27 -> 1513.2 | J27: =G27*E27 -> 3142.8 | K27: =I27+J27 -> 4656 | L27: =H27/C27 -> 1 | M27: 212 | N27: 80 | O27: =C27*(M27+N27) -> 3504 | P27: =K27-O27 -> 1152
A28: e.2 | B28: Bells, indoor with strobe lights / beacons - red body, red lens for fire alarm, weather proof | C28: 4 | D28: Ea | E28: 436.5 | F28: 0 | G28: =C28-F28 -> 4 | H28: =F28+G28 -> 4 | I28: =F28*E28 -> 0 | J28: =G28*E28 -> 1746 | K28: =I28+J28 -> 1746 | L28: =H28/C28 -> 1 | M28: 250 | N28: 80 | O28: =C28*(M28+N28) -> 1320 | P28: =K28-O28 -> 426
A29: f. | B29: Fire alarm cables - fire resistant cable, 300V/500V, red sheath with low emission of smoke, halogen free, thermoplastic material
B30: To include for the procurement, supply, factory testing, delivery to Site, installation, testing and commissioning of the cables, termination materials and all cable support and wiring, identification accessories.
A31: f.1 | B31: 2C x 2.5 mm², Stranded plain copper wire or solid conductor, overall shield with drain wire for SLC loop | C31: 2000 | D31: m | E31: 24.25 | F31: 1900 | G31: =C31-F31 -> 100 | H31: =F31+G31 -> 2000 | I31: =F31*E31 -> 46075 | J31: =G31*E31 -> 2425 | K31: =I31+J31 -> 48500 | L31: =H31/C31 -> 1 | M31: 8 | N31: 0 | O31: =C31*(M31+N31) -> 16000 | P31: =K31-O31 -> 32500
A32: f.2 | B32: 2C x 2.5 mm², Stranded plain copper wire or solid conductor, overall shield with drain wire for NAC Loop | C32: 800 | D32: m | E32: 24.25 | F32: 760 | G32: =C32-F32 -> 40 | H32: =F32+G32 -> 800 | I32: =F32*E32 -> 18430 | J32: =G32*E32 -> 970 | K32: =I32+J32 -> 19400 | L32: =H32/C32 -> 1 | M32: 8 | N32: 0 | O32: =C32*(M32+N32) -> 6400 | P32: =K32-O32 -> 13000
A33: g. | B33: Fire alarm cable conduit, all JB boxes, fittings and accessories for cable installations
B34: To include for the procurement, supply, installation of PVC conduits and flexible metallic conduits for fire cables, junction boxes, fittings, accessories and all other relevant items or Works to complete fully Fire alarm detection system installations.
A35: g.1 | B35: 20 mm diameter, PVC conduits | C35: 0 | D35: m | E35: 24.25 | F35: 0 | G35: 0 | H35: =F35+G35 -> 0 | I35: 0 | J35: =G35*E35 -> 0 | K35: =I35+J35 -> 0
B36: SUB-TOTAL ITEM NO. B8-28 00 00 | C36: xxx | D36: xxx | F36: 0 | G36: 0 | H36: =F36+G36 -> 0 | I36: =SUM(I13:I35) -> 131764.8 | J36: =SUM(J13:J35) -> 18517.3 | K36: =SUM(K13:K35) -> 150282.1 | O36: =SUM(O13:O35) -> 57264 | P36: =SUM(P13:P35) -> 93018.1
B37: (TO BE CARRIED TO COMPOSITE SUMMARY)
B39: OWNER | C39: CONSULTANT | I39: CONTRACTOR

Sheet RECREATION-EXT
C5: RECREATION
A6: SECTION 2- SCHEDULE OF QUANTITIES AND PRICES | C6: B O Q | F6: THE ACTUAL QTY | I6: AMOUNT (SR) | L6: Percentage
A7: PAY ITEM NO. | B7: DESCRIPTION OF ITEM | C7: ESTIMATED QUANTITY | D7: UNIT | E7: UNIT PRICE(SR) EXCL. VAT | F7: Previous QTY | G7: Current QTY | H7: Cumulative QTY | I7: Previous | J7: Current | K7: Cumulative | M7: Actual price | N7: Actual Labour charge | O7: Total AP+LC | P7: Profit
B8: DIVISION 10 - SPECIALTIES
A9: 3.0 | B9: Fire Extinguishers
B10: Includes mounting brackets, fasteners, service tags, fully charged and ready to use extinguishers.
A11: a. | B11: Multipurpose dry chemical type, UL rated ABC
A12: a.1 | B12: FE-1, 6 kg, multi purpose fire extinguisher | C12: 39 | D12: Ea | E12: 250 | F12: 29 | G12: =C12-F12 -> 10 | H12: =F12+G12 -> 39 | I12: =E12*F12 -> 7250 | J12: =G12*E12 -> 2500 | K12: =I12+J12 -> 9750 | L12: =H12/C12 -> 1 | M12: 240 | N12: 10 | O12: =C12*(M12+N12) -> 9750 | P12: =K12-O12 -> 0
A13: b. | B13: Carbon dioxide type, UL rated BC
A14: b.1 | B14: FE-2, 6kg, carbon dioxide portable fire extinguisher | C14: 2 | D14: Ea | E14: 550 | F14: 1.3 | G14: =C14-F14 -> 0.7 | H14: =F14+G14 -> 2 | I14: =E14*F14 -> 715 | J14: =G14*E14 -> 385 | K14: =I14+J14 -> 1100 | L14: =H14/C14 -> 1 | M14: 500 | N14: 10 | O14: =C14*(M14+N14) -> 1020 | P14: =K14-O14 -> 80
A15: c. | B15: Automatic fire extinguisher
A16: c.1 | B16: FE-3, 15 kg, multi purpose fire extinguisher, ceiling mounted | C16: 8 | D16: Ea | E16: 500 | F16: 5.2 | G16: =C16-F16 -> 2.8 | H16: =F16+G16 -> 8 | I16: =E16*F16 -> 2600 | J16: =G16*E16 -> 1400 | K16: =I16+J16 -> 4000 | L16: =H16/C16 -> 1 | M16: 334 | N16: 10 | O16: =C16*(M16+N16) -> 2752 | P16: =K16-O16 -> 1248
B17: SUB-TOTAL ITEM NO. B8-10 00 00 | C17: xxx | D17: xxx | I17: =SUM(I9:I16) -> 10565 | J17: =SUM(J9:J16) -> 4285 | K17: =SUM(K9:K16) -> 14850 | O17: =SUM(O10:O16) -> 13522 | P17: =SUM(P10:P16) -> 1328

Sheet RECREATION
C3: REC
A4: SECTION 2- SCHEDULE OF QUANTITIES AND PRICES | C4: B O Q | F4: THE ACTUAL QTY | I4: AMOUNT (SR)
A5: PAY ITEM NO. | B5: DESCRIPTION OF ITEM | C5: ESTIMATED QUANTITY | D5: UNIT | E5: UNIT PRICE(SR) EXCL. VAT | F5: Previous QTY | G5: Current QTY | H5: Cumulative QTY | I5: Previous | J5: Current | K5: Cumulative | L5: Percentage | M5: Actual price | N5: accessories | O5: Actual Labour charge | P5: Total AP+LC | Q5: Profit
B6: DIVISION 21 - FIRE SUPPRESSION
A7: 1.0 | B7: General-Duty Valves for Water-Based Fire-Suppression Piping
B8: Supply and installation of valves including all fixings, supports, all other accessories and associated Works.
A9: a. | B9: Gate valve, UL and FM global approved
A10: a.1 | B10: 150 mm diameter | C10: 2 | D10: Ea | E10: 3686 | F10: 1.8 | G10: =C10-F10 -> 0.2 | H10: =F10+G10 -> 2 | I10: =E10*F10 -> 6634.8 | J10: =G10*E10 -> 737.2 | K10: =I10+J10 -> 7372 | L10: =H10/C10 -> 1 | M10: 1250 | N10: 100 | O10: 300 | P10: =C10*(M10+N10+O10) -> 3300 | Q10: =K10-P10 -> 4072
A11: b. | B11: Alarm check valve, UL and FM global approved
A12: b.1 | B12: 150 mm diameter | C12: 1 | D12: Ea | E12: 5577.5 | F12: 0.9 | G12: =C12-F12 -> 0.1 | H12: =F12+G12 -> 1 | I12: =E12*F12 -> 5019.75 | J12: =G12*E12 -> 557.75 | K12: =I12+J12 -> 5577.5 | L12: =H12/C12 -> 1 | M12: 3830 | N12: 200 | O12: 100 | P12: =C12*(M12+N12+O12) -> 4130 | Q12: =K12-P12 -> 1447.5
A13: c. | B13: Zone control valve assembly
A14: c.1 | B14: 100 mm diameter | C14: 2 | D14: Ea | E14: 5626 | F14: 1.79 | G14: =C14-F14 -> 0.21 | H14: =F14+G14 -> 2 | I14: =E14*F14 -> 10070.54 | J14: =G14*E14 -> 1181.46 | K14: =I14+J14 -> 11252 | L14: =H14/C14 -> 1 | M14: 3000 | N14: 150 | O14: 100 | P14: =C14*(M14+N14+O14) -> 6500 | Q14: =K14-P14 -> 4752
A15: 2.0 | B15: Fire-Department Connections
B16: Two way, swivel fittings, Dust caps and chains of same material as body, chrome plated finish and threads to match local fire department hardware
A17: a. | B17: Flush wall mounted fire department connection with check valve
A18: a.1 | B18: Two-way swivel fittings, 65 x 65 x 100 mm single clapper Siamese-type connections | C18: 1 | D18: Ea | E18: 4462 | F18: 0.65 | G18: =C18-F18 -> 0.35 | H18: =F18+G18 -> 1 | I18: =E18*F18 -> 2900.3 | J18: =G18*E18 -> 1561.7 | K18: =I18+J18 -> 4462 | L18: =H18/C18 -> 1 | M18: 450 | N18: 150 | O18: 100 | P18: =C18*(M18+N18+O18) -> 700 | Q18: =K18-P18 -> 3762
A19: 3.0 | B19: Wet-Pipe Sprinkler Systems
A20: a. | B20: Black steel fire water pipes
B21: Supply and installation of black steel pipe seamless type as per ASTM A53 including supports, hangers, fixing, fitting, all other accessories and associated Works as per Contract drawings and specifications.
A22: a.1 | B22: 25 mm diameter | C22: 1080 | D22: m | E22: 53.35 | F22: 972 | G22: =C22-F22 -> 108 | H22: =F22+G22 -> 1080 | I22: =E22*F22 -> 51856.2 | J22: =G22*E22 -> 5761.8 | K22: =I22+J22 -> 57618 | L22: =(H22/C22) -> 1 | M22: 15 | N22: 7.5 | O22: 0 | P22: =C22*(M22+N22+O22) -> 24300 | Q22: =K22-P22 -> 33318
A23: a.2 | B23: 32 mm diameter | C23: 325 | D23: m | E23: 63.05 | F23: 292.5 | G23: =C23-F23 -> 32.5 | H23: =F23+G23 -> 325 | I23: =E23*F23 -> 18442.125 | J23: =G23*E23 -> 2049.125 | K23: =I23+J23 -> 20491.25 | L23: =(H23/C23) -> 1 | M23: 20 | N23: 10 | O23: 0 | P23: =C23*(M23+N23+O23) -> 9750 | Q23: =K23-P23 -> 10741.25
A24: a.3 | B24: 40 mm diameter | C24: 130 | D24: m | E24: 77.6 | F24: 117 | G24: =C24-F24 -> 13 | H24: =F24+G24 -> 130 | I24: =E24*F24 -> 9079.2 | J24: =G24*E24 -> 1008.8 | K24: =I24+J24 -> 10088 | L24: =(H24/C24) -> 1 | M24: 24 | N24: 12 | O24: 0 | P24: =C24*(M24+N24+O24) -> 4680 | Q24: =K24-P24 -> 5408
A25: a.4 | B25: 50 mm diameter | C25: 60 | D25: m | E25: 95.06 | F25: 54 | G25: =C25-F25 -> 6 | H25: =F25+G25 -> 60 | I25: =E25*F25 -> 5133.24 | J25: =G25*E25 -> 570.36 | K25: =I25+J25 -> 5703.6 | L25: =(H25/C25) -> 1 | M25: 28 | N25: 14 | O25: 0 | P25: =C25*(M25+N25+O25) -> 2520 | Q25: =K25-P25 -> 3183.6
A26: a.5 | B26: 65 mm diameter | C26: 130 | D26: m | E26: 169.75 | F26: 117 | G26: =C26-F26 -> 13 | H26: =F26+G26 -> 130 | I26: =E26*F26 -> 19860.75 | J26: =G26*E26 -> 2206.75 | K26: =I26+J26 -> 22067.5 | L26: =(H26/C26) -> 1 | M26: 30 | N26: 15 | O26: 0 | P26: =C26*(M26+N26+O26) -> 5850 | Q26: =K26-P26 -> 16217.5
A27: a.6 | B27: 80 mm diameter | C27: 40 | D27: m | E27: 190.12 | F27: 36 | G27: =C27-F27 -> 4 | H27: =F27+G27 -> 40 | I27: =E27*F27 -> 6844.32 | J27: =G27*E27 -> 760.48 | K27: =I27+J27 -> 7604.8 | L27: =(H27/C27) -> 1 | M27: 35 | N27: 25 | O27: 0 | P27: =C27*(M27+N27+O27) -> 2400 | Q27: =K27-P27 -> 5204.8
A28: a.7 | B28: 100 mm diameter | C28: 80 | D28: m | E28: 237.65 | F28: 72 | G28: =C28-F28 -> 8 | H28: =F28+G28 -> 80 | I28: =E28*F28 -> 17110.8 | J28: =G28*E28 -> 1901.2 | K28: =I28+J28 -> 19012 | L28: =(H28/C28) -> 1 | M28: 90 | N28: 60 | O28: 0 | P28: =C28*(M28+N28+O28) -> 12000 | Q28: =K28-P28 -> 7012
A29: a.8 | B29: 150 mm diameter | C29: 20 | D29: m | E29: 344.35 | F29: 18.025 | G29: =C29-F29 -> 1.975 | H29: =F29+G29 -> 20 | I29: =E29*F29 -> 6206.9087 | J29: =G29*E29 -> 680.09125 | K29: =I29+J29 -> 6887 | L29: =(H29/C29) -> 1 | M29: 170 | N29: 90 | O29: 0 | P29: =C29*(M29+N29+O29) -> 5200 | Q29: =K29-P29 -> 1687
A30: b. | B30: Fire water sprinkler head
B31: Sprinkler Head, UL listed FM approved, chrome-plated, bronze and factory painted; Shall be of one manufacturer. (No mixing of sprinkler brands shall be permitted).
A32: b.1 | B32: Pendent type (K=5.60) | C32: 212 | D32: Ea | E32: 63.05 | F32: 169.6 | G32: =C32-F32 -> 42.4 | H32: =F32+G32 -> 212 | I32: =E32*F32 -> 10693.28 | J32: =G32*E32 -> 2673.32 | K32: =I32+J32 -> 13366.6 | L32: =H32/C32 -> 1 | M32: 25 | N32: 5 | O32: 100 | P32: =C32*(M32+N32+O32) -> 27560 | Q32: =K32-P32 -> -14193.4
A33: b.2 | B33: Upright type (K=5.60) | C33: 70 | D33: Ea | E33: 33.95 | F33: 56 | G33: =C33-F33 -> 14 | H33: =F33+G33 -> 70 | I33: =E33*F33 -> 1901.2 | J33: =G33*E33 -> 475.3 | K33: =I33+J33 -> 2376.5 | L33: =H33/C33 -> 1 | M33: 19 | N33: 5 | O33: 100 | P33: =C33*(M33+N33+O33) -> 8680 | Q33: =K33-P33 -> -6303.5
A34: b.3 | B34: Upright type (K=8.0) | C34: 36 | D34: Ea | E34: 72.75 | F34: 23.4 | G34: =C34-F34 -> 12.6 | H34: =F34+G34 -> 36 | I34: =E34*F34 -> 1702.35 | J34: =G34*E34 -> 916.65 | K34: =I34+J34 -> 2619 | L34: =H34/C34 -> 1 | M34: 59 | N34: 5 | O34: 100 | P34: =C34*(M34+N34+O34) -> 5904 | Q34: =K34-P34 -> -3285
A35: b.4 | B35: Wall side type (K=5.6) | C35: 7 | D35: Ea | E35: 145.5 | F35: 5.6 | G35: =C35-F35 -> 1.4 | H35: =F35+G35 -> 7 | I35: =E35*F35 -> 814.8 | J35: =G35*E35 -> 203.7 | K35: =I35+J35 -> 1018.5 | L35: =H35/C35 -> 1
A36: 4.0 | B36: Fire-Suppression Standpipes
A37: a. | B37: Fire Hose Cabinet
B38: Supply and installation of Surface mounted fire hose Cabinets Made of Stainless Steel, dimension (W 750 x H 850 x D 180). with Synthetic Single Jacket Hose 1.5” x 30 meter long and (1) multipurpose dry powder Extinguisher include fittings, joints, unions, dielectric fittings, flanges, gaskets, grooved mechanical couplings, nuts and bolts, hangers and supports and labelling.
A40: a.1 | B40: FHC-II | C40: 8 | D40: Ea | E40: 4704.5 | F40: 5.2 | G40: =C40-F40 -> 2.8 | H40: =F40+G40 -> 8 | I40: =E40*F40 -> 24463.4 | J40: =G40*E40 -> 13172.6 | K40: =I40+J40 -> 37636 | L40: =H40/C40 -> 1 | M40: 4200 | N40: 250 | O40: 400 | P40: =C40*(M40+N40+O40) -> 38800 | Q40: =K40-P40 -> -1164
I41: =SUM(I10:I40) -> 198733.96 | J41: =SUM(J10:J40) -> 36418.286 | K41: =SUM(K10:K40) -> 235152.25 | P41: =SUM(P9:P40) -> 162274 | Q41: =SUM(Q9:Q40) -> 71859.75
B42: SUB-TOTAL ITEM NO. B8-21 00 00 | C42: xxx | D42: xxx
B43: (TO BE CARRIED TO COMPOSITE SUMMARY)
B45: OWNER | C45: CONSULTANT | I45: CONTRACTOR

Sheet SERVICE - E
C3: SERVICE - E
C4: B O Q | F4: THE ACTUAL QTY | I4: AMOUNT (SR)
A5: SECTION 2- SCHEDULE OF QUANTITIES AND PRICES | B5: DESCRIPTION OF ITEM | C5: ESTIMATED QUANTITY | D5: UNIT | E5: UNIT PRICE(SR) EXCL. VAT | F5: Previous QTY | G5: Current QTY | H5: Cumulative QTY | I5: Previous | J5: Current | K5: Cumulative | L5: Percentage | M5: Actual price | N5: Actual Labour charge | O5: Total AP+LC | P5: Profit
A6: PAY ITEM NO.
B7: DIVISION 28-ELECTRONIC SAFETY AND SECURITY
A8: 2.0 | B8: Fire Detection and Alarm
A9: a. | B9: Fire alarm control panel (FACP)
B10: Supply, installation, testing and commissioning of a microprocessor based, addressable fire alarm control panel, complete with Chassis, 640-Character backlit LCD display, QWERTY programming and control keypad, loop cards, zone and input/output modules, supervisory devices, auxiliary relays, network capability modules, battery, battery charger, printer, internal alarm, interface contacts and all accessories and hardware as shown on the Contract drawings and specified in the Contract documents and to complete the fully functional, operable, reliable and maintainable fire alarm system.
A11: a.1 | B11: Microprocessor based, addressable FACP, 5 loop type | C11: 2 | D11: Ea | E11: 22795 | F11: 1.3 | G11: =C11-F11 -> 0.7 | H11: =F11+G11 -> 2 | I11: =E11*F11 -> 29633.5 | J11: =E11*G11 -> 15956.5 | K11: =I11+J11 -> 45590 | L11: =H11/C11 -> 1 | M11: 16900 | N11: 80 | O11: =C11*(M11+N11) -> 33960 | P11: =K11-O11 -> 11630
A12: b. | B12: Power supply unit, batteries and battery chargers | C12: 2 | D12: Ea | E12: 4365 | F12: 0 | G12: =C12-F12 -> 2 | H12: =F12+G12 -> 2 | I12: =E12*F12 -> 0 | J12: =E12*G12 -> 8730 | K12: =I12+J12 -> 8730 | L12: =H12/C12 -> 1 | M12: 0 | N12: 0 | O12: =C12*(M12+N12) -> 0 | P12: =K12-O12 -> 8730
B13: Supply, selection and calculation, installation, testing and commissioning of FACP power supply unit, batteries for at least 24 hours during the normal operations and 15 mins under emergency full loaded condition. Provide separate combination of power Supply and battery enclosure when large batteries are required and not be able embedded inside FACP panel.
A14: c. | B14: Detection and initiation devices
B15: Supply, installation, testing and commissioning of intelligent, addressable type fire alarm detectors and initiating devices as shown on the Contract drawings and specified in the Contract documents complete with all mounting accessories including boxes, connectors and terminations.
A16: c.1 | B16: Smoke detector - photoelectric, addressable, self diagnostic, self address | C16: 229 | D16: Ea | E16: 339.5 | F16: 148.85 | G16: =C16-F16 -> 80.15 | H16: =F16+G16 -> 229 | I16: =E16*F16 -> 50534.575 | J16: =E16*G16 -> 27210.925 | K16: =I16+J16 -> 77745.5 | L16: =H16/C16 -> 1 | M16: 120 | N16: 80 | O16: =C16*(M16+N16) -> 45800 | P16: =K16-O16 -> 31945.5
A17: c.2 | B17: Air duct smoke detectors with remote LED indicator and test devices | C17: 28 | D17: Ea | E17: 1746 | F17: 10.4 | G17: =C17-F17 -> 17.6 | H17: =F17+G17 -> 28 | I17: =E17*F17 -> 18158.4 | J17: =E17*G17 -> 30729.6 | K17: =I17+J17 -> 48888 | L17: =H17/C17 -> 1 | M17: 250 | N17: 80 | O17: =C17*(M17+N17) -> 9240 | P17: =K17-O17 -> 39648
A18: c.3 | B18: Heat detector - rate of rise type with fix temperature | C18: 24 | D18: Ea | E18: 339.5 | F18: 8.45 | G18: =C18-F18 -> 15.55 | H18: =F18+G18 -> 24 | I18: =E18*F18 -> 2868.775 | J18: =E18*G18 -> 5279.225 | K18: =I18+J18 -> 8148 | L18: =H18/C18 -> 1 | M18: 110 | N18: 80 | O18: =C18*(M18+N18) -> 4560 | P18: =K18-O18 -> 3588
A19: c.4 | B19: Addressable manual fire alarm pull station | C19: 26 | D19: Ea | E19: 291 | F19: 16.9 | G19: =C19-F19 -> 9.1 | H19: =F19+G19 -> 26 | I19: =E19*F19 -> 4917.9 | J19: =E19*G19 -> 2648.1 | K19: =I19+J19 -> 7566 | L19: =H19/C19 -> 1 | M19: 180 | N19: 80 | O19: =C19*(M19+N19) -> 6760 | P19: =K19-O19 -> 806
A20: c.5 | B20: Addressable manual fire alarm pull station, weather proof | C20: 5 | D20: Ea | E20: 339.5 | F20: 3.25 | G20: =C20-F20 -> 1.75 | H20: =F20+G20 -> 5 | I20: =E20*F20 -> 1103.375 | J20: =E20*G20 -> 594.125 | K20: =I20+J20 -> 1697.5 | L20: =H20/C20 -> 1 | M20: 250 | N20: 80 | O20: =C20*(M20+N20) -> 1650 | P20: =K20-O20 -> 47.5
A21: d. | B21: Other initiating devices and control devices
B22: Supply, Installation, testing and commissioning of all conventional I/O interfaces devices for interface and Integration with firefighting systems, gas alarm and control systems, lift safety devices, fire water pumps, HVAC systems. elevators and all other specified equipment as per contract drawings and specifications, complete with all mounting accessories including boxes and terminations.
A23: d.1 | B23: Fire alarm monitoring module (MM) | C23: 24 | D23: Ea | E23: 436.5 | F23: 15.6 | G23: =C23-F23 -> 8.4 | H23: =F23+G23 -> 24 | I23: =E23*F23 -> 6809.4 | J23: =E23*G23 -> 3666.6 | K23: =I23+J23 -> 10476 | L23: =H23/C23 -> 1 | M23: 140 | N23: 80 | O23: =C23*(M23+N23) -> 5280 | P23: =K23-O23 -> 5196
A24: e. | B24: Notification appliances
B25: Supply, installation, testing and commissioning of visual and sound alarm devices as shown on the Contract drawings and specified in the Contract documents complete with all mounting accessories including boxes and terminations.
A26: e.1 | B26: Bells, indoor with strobe lights / beacons - red body, red lens for fire alarm | C26: 28 | D26: Ea | E26: 388 | F26: 18.2 | G26: =C26-F26 -> 9.8 | H26: =F26+G26 -> 28 | I26: =E26*F26 -> 7061.6 | J26: =E26*G26 -> 3802.4 | K26: =I26+J26 -> 10864 | L26: =H26/C26 -> 1 | M26: 212 | N26: 80 | O26: =C26*(M26+N26) -> 8176 | P26: =K26-O26 -> 2688
A27: e.2 | B27: Bells, indoor with strobe lights / beacons - red body, red lens for fire alarm, weather proof | C27: 23 | D27: Ea | E27: 436.5 | F27: 14.3 | G27: =C27-F27 -> 8.7 | H27: =F27+G27 -> 23 | I27: =E27*F27 -> 6241.95 | J27: =E27*G27 -> 3797.55 | K27: =I27+J27 -> 10039.5 | L27: =H27/C27 -> 1 | M27: 250 | N27: 80 | O27: =C27*(M27+N27) -> 7590 | P27: =K27-O27 -> 2449.5
A28: f. | B28: Fire alarm cables - fire resistant cable, 300V/500V, red sheath with low emission of smoke, halogen free, thermoplastic material
B29: To include for the procurement, supply, factory testing, delivery to Site, installation, testing and commissioning of the cables, termination materials and all cable support and wiring, identification accessories.
A30: f.1 | B30: 2C x 2.5 mm², Stranded plain copper wire or solid conductor, overall shield with drain wire for SLC loop | C30: 2000 | D30: m | E30: 24.25 | F30: 1788 | G30: =C30-F30 -> 212 | H30: =F30+G30 -> 2000 | I30: =E30*F30 -> 43359 | J30: =E30*G30 -> 5141 | K30: =I30+J30 -> 48500 | L30: =H30/C30 -> 1 | M30: 8 | N30: 0 | O30: =C30*(M30+N30) -> 16000 | P30: =K30-O30 -> 32500
A31: f.2 | B31: 2C x 2.5 mm², Stranded plain copper wire or solid conductor, overall shield with drain wire for NAC Loop | C31: 800 | D31: m | E31: 24.25 | F31: 712 | G31: =C31-F31 -> 88 | H31: =F31+G31 -> 800 | I31: =E31*F31 -> 17266 | J31: =E31*G31 -> 2134 | K31: =I31+J31 -> 19400 | L31: =H31/C31 -> 1 | M31: 8 | N31: 0 | O31: =C31*(M31+N31) -> 6400 | P31: =K31-O31 -> 13000
A33: g. | B33: Fire alarm cable conduit, all JB boxes, fittings and accessories for cable installations
B34: To include for the procurement, supply, installation of PVC conduits and flexible metallic conduits for fire cables, junction boxes, fittings, accessories and all other relevant items or Works to complete fully Fire alarm detection system installations. | O34: =SUM(O9:O33) -> 145416 | P34: =SUM(P9:P33) -> 152228.5
A35: g.1 | B35: 20 mm diameter, PVC conduits | C35: 0 | D35: m | E35: 24.25 | F35: 0 | G35: 0 | H35: 0 | I35: =E35*F35 -> 0 | J35: =E35*H35 -> 0 | K35: 0
B36: SUB-TOTAL ITEM NO. B9-28 00 00 | C36: xxx | D36: xxx | I36: =SUM(I10:I35) -> 187954.47 | J36: =SUM(J10:J35) -> 109690.03 | K36: =SUM(K11:K35) -> 297644.5
B37: (TO BE CARRIED TO COMPOSITE SUMMARY)
B39: OWNER | C39: CONSULTANT | I39: CONTRACTOR

Sheet SERVICE-EXT
C5: SERVICE
A6: SECTION 2- SCHEDULE OF QUANTITIES AND PRICES | C6: B O Q | F6: THE ACTUAL QTY | I6: AMOUNT (SR) | L6: Percentage
A7: PAY ITEM NO. | B7: DESCRIPTION OF ITEM | C7: ESTIMATED QUANTITY | D7: UNIT | E7: UNIT PRICE(SR) EXCL. VAT | F7: Previous QTY | G7: Current QTY | H7: Cumulative QTY | I7: Previous | J7: Current | K7: Cumulative | M7: Actual price | N7: Actual Labour charge | O7: Total AP+LC | P7: Profit
B8: DIVISION 10 - SPECIALTIES
A9: 3.0 | B9: Fire Extinguishers
B10: Includes mounting brackets, fasteners, service tags, fully charged and ready to use extinguishers.
A11: a. | B11: Multipurpose dry chemical type, UL rated ABC
A12: a.1 | B12: FE-1, 6 kg, multi purpose fire extinguisher | C12: 102 | D12: Ea | E12: 250 | F12: 77 | G12: =C12-F12 -> 25 | H12: =F12+G12 -> 102 | I12: =E12*F12 -> 19250 | J12: =G12*E12 -> 6250 | K12: =I12+J12 -> 25500 | L12: =H12/C12 -> 1 | M12: 240 | N12: 10 | O12: =C12*(M12+N12) -> 25500 | P12: =K12-O12 -> 0
A13: b. | B13: Carbon dioxide type, UL rated BC
A14: b.1 | B14: FE-2, 6kg, carbon dioxide portable fire extinguisher | C14: 7 | D14: Ea | E14: 350 | F14: 4.55 | G14: =C14-F14 -> 2.45 | H14: =F14+G14 -> 7 | I14: =E14*F14 -> 1592.5 | J14: =G14*E14 -> 857.5 | K14: =I14+J14 -> 2450 | L14: =H14/C14 -> 1 | M14: 500 | N14: 10 | O14: =C14*(M14+N14) -> 3570 | P14: =K14-O14 -> -1120
A15: c. | B15: Wet chemical type, UL rated class K
A16: c.1 | B16: FE-3, kitchen type-K fire extinguisher 2 gallon | C16: 2 | D16: Ea | E16: 500 | F16: 1.3 | G16: =C16-F16 -> 0.7 | H16: =F16+G16 -> 2 | I16: =E16*F16 -> 650 | J16: =G16*E16 -> 350 | K16: =I16+J16 -> 1000 | L16: =H16/C16 -> 1 | M16: 320 | N16: 10 | O16: =C16*(M16+N16) -> 660 | P16: =K16-O16 -> 340
A17: d. | B17: Automatic fire extinguisher
A18: d.1 | B18: AFE-3, 15 kg, multi purpose fire extinguisher, ceiling mounted | C18: 13 | D18: Ea | E18: 500 | F18: 0 | G18: =C18-F18 -> 13 | H18: =F18+G18 -> 13 | I18: 0 | J18: =G18*E18 -> 6500 | K18: =I18+J18 -> 6500 | L18: =H18/C18 -> 1 | M18: 334 | N18: 10 | O18: =C18*(M18+N18) -> 4472 | P18: =K18-O18 -> 2028
A19: e. | B19: Fire blanket
B20: Supply and installation of fire blanket of specified type to be located in kitchen with all fittings and supports required to provide satisfactory operation.
A21: e.1 | B21: Fire blanket, standard size (1.2 meter x 1.2 meter), NFPA approved | C21: 2 | D21: Ea | E21: 300 | F21: 0 | G21: =C21-F21 -> 2 | H21: =F21+G21 -> 2 | I21: 0 | J21: =G21*E21 -> 600 | K21: =I21+J21 -> 600 | L21: =H21/C21 -> 1 | M21: 16 | N21: 10 | O21: =C21*(M21+N21) -> 52 | P21: =K21-O21 -> 548
B22: SUB-TOTAL ITEM NO. B9-10 00 00 | C22: xxx | D22: xxx | I22: =SUM(I9:I21) -> 21492.5 | J22: =SUM(J9:J21) -> 14557.5 | K22: =SUM(K9:K21) -> 36050 | O22: =SUM(O10:O21) -> 34254 | P22: =SUM(P10:P21) -> 1796

Sheet SERVICE
C3: SERVICE
A4: SECTION 2- SCHEDULE OF QUANTITIES AND PRICES | C4: B O Q | F4: THE ACTUAL QTY | I4: AMOUNT (SR)
A5: PAY ITEM NO. | B5: DESCRIPTION OF ITEM | C5: ESTIMATED QUANTITY | D5: UNIT | E5: UNIT PRICE(SR) EXCL. VAT | F5: Previous QTY | G5: Current QTY | H5: Cumulative QTY | I5: Previous | J5: Current | K5: Cumulative | L5: Percentage | M5: Actual price | N5: accessories | O5: Actual Labour charge | P5: Total AP+LC | Q5: Profit
B6: DIVISION 21 - FIRE SUPPRESSION
A7: 1.0 | B7: General-Duty Valves for Water-Based Fire-Suppression Piping
B8: Supply and installation of valves including all fixings, supports, all other accessories and associated Works.
A9: a. | B9: Gate valve, UL and FM global approved
A10: a.1 | B10: 150 mm diameter | C10: 2 | D10: Ea | E10: 3800 | F10: 1.3 | G10: =C10-F10 -> 0.7 | H10: =F10+G10 -> 2 | I10: =E10*F10 -> 4940 | J10: =G10*E10 -> 2660 | K10: =I10+J10 -> 7600 | L10: =H10/C10 -> 1 | M10: 1250 | N10: 100 | O10: 300 | P10: =C10*(M10+N10+O10) -> 3300 | Q10: =K10-P10 -> 4300
A11: b. | B11: Alarm check valve, UL and FM global approved
A12: b.1 | B12: 150 mm diameter | C12: 4 | D12: Ea | E12: 5750 | F12: 2.6 | G12: =C12-F12 -> 1.4 | H12: =F12+G12 -> 4 | I12: =E12*F12 -> 14950 | J12: =G12*E12 -> 8050 | K12: =I12+J12 -> 23000 | L12: =H12/C12 -> 1 | M12: 3830 | N12: 200 | O12: 100 | P12: =C12*(M12+N12+O12) -> 16520 | Q12: =K12-P12 -> 6480
A13: c. | B13: Zone control valve assembly
A14: c.1 | B14: 100 mm diameter | C14: 8 | D14: Ea | E14: 5800 | F14: 5.16 | G14: =C14-F14 -> 2.84 | H14: =F14+G14 -> 8 | I14: =E14*F14 -> 29928 | J14: =G14*E14 -> 16472 | K14: =I14+J14 -> 46400 | L14: =H14/C14 -> 1 | M14: 3000 | N14: 150 | O14: 100 | P14: =C14*(M14+N14+O14) -> 26000 | Q14: =K14-P14 -> 20400
A15: 2.0 | B15: Fire-Department Connections
B16: Two way, swivel fittings, Dust caps and chains of same material as body, chrome plated finish and threads to match local fire department hardware
A17: a. | B17: Flush wall mounted fire department connection with check valve
A18: a.1 | B18: Two-way swivel fittings, 65 x 65 x 100 mm single clapper Siamese-type connections | C18: 4 | D18: Ea | E18: 4600 | F18: 2.6 | G18: =C18-F18 -> 1.4 | H18: =F18+G18 -> 4 | I18: =E18*F18 -> 11960 | J18: =G18*E18 -> 6440 | K18: =I18+J18 -> 18400 | L18: =H18/C18 -> 1 | M18: 450 | N18: 150 | O18: 100 | P18: =C18*(M18+N18+O18) -> 2800 | Q18: =K18-P18 -> 15600
A19: 3.0 | B19: Wet-Pipe Sprinkler Systems
A20: a. | B20: Black steel fire water pipes
B21: Supply and installation of black steel pipe seamless type as per ASTM A53 including supports, hangers, fixing, fitting, all other accessories and associated Works as per Contract drawings and specifications.
A22: a.1 | B22: 25 mm diameter | C22: 2100 | D22: m | E22: 53.35 | F22: 1779.75 | G22: =C22-F22 -> 320.25 | H22: =F22+G22 -> 2100 | I22: =E22*F22 -> 94949.663 | J22: =G22*E22 -> 17085.338 | K22: =I22+J22 -> 112035 | L22: =(H22/C22) -> 1 | M22: 15 | N22: 7.5 | O22: 0 | P22: =C22*(M22+N22+O22) -> 47250 | Q22: =K22-P22 -> 64785
A23: a.2 | B23: 32 mm diameter | C23: 535 | D23: m | E23: 63.05 | F23: 453.4125 | G23: =C23-F23 -> 81.5875 | H23: =F23+G23 -> 535 | I23: =E23*F23 -> 28587.658 | J23: =G23*E23 -> 5144.0919 | K23: =I23+J23 -> 33731.75 | L23: =(H23/C23) -> 1 | M23: 20 | N23: 10 | O23: 0 | P23: =C23*(M23+N23+O23) -> 16050 | Q23: =K23-P23 -> 17681.75
A24: a.3 | B24: 40 mm diameter | C24: 285 | D24: m | E24: 77.6 | F24: 241.5375 | G24: =C24-F24 -> 43.4625 | H24: =F24+G24 -> 285 | I24: =E24*F24 -> 18743.31 | J24: =G24*E24 -> 3372.69 | K24: =I24+J24 -> 22116 | L24: =(H24/C24) -> 1 | M24: 24 | N24: 12 | O24: 0 | P24: =C24*(M24+N24+O24) -> 10260 | Q24: =K24-P24 -> 11856
A25: a.4 | B25: 50 mm diameter | C25: 110 | D25: m | E25: 95.06 | F25: 93.225 | G25: =C25-F25 -> 16.775 | H25: =F25+G25 -> 110 | I25: =E25*F25 -> 8861.9685 | J25: =G25*E25 -> 1594.6315 | K25: =I25+J25 -> 10456.6 | L25: =(H25/C25) -> 1 | M25: 28 | N25: 14 | O25: 0 | P25: =C25*(M25+N25+O25) -> 4620 | Q25: =K25-P25 -> 5836.6
A26: a.5 | B26: 65 mm diameter | C26: 130 | D26: m | E26: 169.75 | F26: 110.175 | G26: =C26-F26 -> 19.825 | H26: =F26+G26 -> 130 | I26: =E26*F26 -> 18702.206 | J26: =G26*E26 -> 3365.2938 | K26: =I26+J26 -> 22067.5 | L26: =(H26/C26) -> 1 | M26: 30 | N26: 15 | O26: 0 | P26: =C26*(M26+N26+O26) -> 5850 | Q26: =K26-P26 -> 16217.5
A27: a.6 | B27: 80 mm diameter | C27: 200 | D27: m | E27: 190.12 | F27: 169.5 | G27: =C27-F27 -> 30.5 | H27: =F27+G27 -> 200 | I27: =E27*F27 -> 32225.34 | J27: =G27*E27 -> 5798.66 | K27: =I27+J27 -> 38024 | L27: =(H27/C27) -> 1 | M27: 35 | N27: 25 | O27: 0 | P27: =C27*(M27+N27+O27) -> 12000 | Q27: =K27-P27 -> 26024
A28: a.7 | B28: 100 mm diameter | C28: 180 | D28: m | E28: 237.65 | F28: 152.55 | G28: =C28-F28 -> 27.45 | H28: =F28+G28 -> 180 | I28: =E28*F28 -> 36253.508 | J28: =G28*E28 -> 6523.4925 | K28: =I28+J28 -> 42777 | L28: =(H28/C28) -> 1 | M28: 90 | N28: 60 | O28: 0 | P28: =C28*(M28+N28+O28) -> 27000 | Q28: =K28-P28 -> 15777
A29: a.8 | B29: 150 mm diameter | C29: 40 | D29: m | E29: 344.35 | F29: 33.95 | G29: =C29-F29 -> 6.05 | H29: =F29+G29 -> 40 | I29: =E29*F29 -> 11690.683 | J29: =G29*E29 -> 2083.3175 | K29: =I29+J29 -> 13774 | L29: =(H29/C29) -> 1 | M29: 170 | N29: 90 | O29: 0 | P29: =C29*(M29+N29+O29) -> 10400 | Q29: =K29-P29 -> 3374
A30: b. | B30: Fire water sprinkler head
B31: Sprinkler Head, UL listed FM approved, chrome-plated, bronze and factory painted; Shall be of one manufacturer. (No mixing of sprinkler brands shall be permitted).
A32: b.1 | B32: Pendent type | C32: 644 | D32: Ea | E32: 65 | F32: 396.78 | G32: =C32-F32 -> 247.22 | H32: =F32+G32 -> 644 | I32: =E32*F32 -> 25790.7 | J32: =G32*E32 -> 16069.3 | K32: =I32+J32 -> 41860 | L32: =H32/C32 -> 1 | M32: 25 | N32: 5 | O32: 100 | P32: =C32*(M32+N32+O32) -> 83720 | Q32: =K32-P32 -> -41860
A33: b.2 | B33: Upright type | C33: 209 | D33: Ea | E33: 35 | F33: 95.88 | G33: =C33-F33 -> 113.12 | H33: =F33+G33 -> 209 | I33: =E33*F33 -> 3355.8 | J33: =G33*E33 -> 3959.2 | K33: =I33+J33 -> 7315 | L33: =H33/C33 -> 1 | M33: 19 | N33: 5 | O33: 100 | P33: =C33*(M33+N33+O33) -> 25916 | Q33: =K33-P33 -> -18601
A34: b.3 | B34: Wall side type | C34: 26 | D34: Ea | E34: 75 | F34: 19.175 | G34: =C34-F34 -> 6.825 | H34: =F34+G34 -> 26 | I34: =E34*F34 -> 1438.125 | J34: =G34*E34 -> 511.875 | K34: =I34+J34 -> 1950 | L34: =H34/C34 -> 1 | M34: 59 | N34: 5 | O34: 100 | P34: =C34*(M34+N34+O34) -> 4264 | Q34: =K34-P34 -> -2314
A35: b.4 | B35: Pendent type for kitchen and laundry | C35: 35 | D35: Ea | E35: 80 | F35: 22.75 | G35: =C35-F35 -> 12.25 | H35: =F35+G35 -> 35 | I35: =E35*F35 -> 1820 | J35: =G35*E35 -> 980 | K35: =I35+J35 -> 2800 | L35: =H35/C35 -> 1
A36: 4.0 | B36: Wet-Chemical Fire-Extinguishing System
B37: Supply and installation Wet-chemical fire-extinguishing piping include Piping, fittings, joints, unions, dielectric fittings, flanges, gaskets, grooved mechanical couplings, nuts and bolts, hangers and supports, labelling; discharge manifold - including all piping, valves, controls and support; extinguishing agent containers - including extinguishing agent safety devices and safety brackets, discharge nozzles, control panel (FM approved or UL Listed) - including mounting and all wiring, detection devices.
A38: a.1 | B38: Wet-chemical fire-extinguishing system | C38: 7 | D38: Set | E38: 18500 | F38: 0 | G38: =C38-F38 -> 7 | H38: =F38+G38 -> 7 | I38: =E38*F38 -> 0 | J38: =G38*E38 -> 129500 | K38: =I38+J38 -> 129500 | L38: =H38/C38 -> 1 | M38: 0 | P38: =C38*(M38+N38+O38) -> 0 | Q38: =K38-P38 -> 129500
A39: a.2 | B39: Wet-chemical fire-extinguishing piping | C39: 7 | D39: Set | E39: 2500 | F39: 0 | G39: =C39-F39 -> 7 | H39: =F39+G39 -> 7 | I39: =E39*F39 -> 0 | J39: =G39*E39 -> 17500 | K39: =I39+J39 -> 17500 | L39: =H39/C39 -> 1 | M39: 0 | P39: =C39*(M39+N39+O39) -> 0 | Q39: =K39-P39 -> 17500
A40: a.3 | B40: Wet-chemical fire-extinguishing equipment | C40: 7 | D40: Set | E40: 4000 | F40: 0 | G40: =C40-F40 -> 7 | H40: =F40+G40 -> 7 | I40: =E40*F40 -> 0 | J40: =G40*E40 -> 28000 | K40: =I40+J40 -> 28000 | L40: =H40/C40 -> 1 | M40: 0 | P40: =C40*(M40+N40+O40) -> 0 | Q40: =K40-P40 -> 28000
A41: 4.0 | B41: Fire-Suppression Standpipes
A42: a. | B42: Fire Hose Cabinet
B43: Supply and installation of Surface mounted fire hose Cabinets Made of Stainless Steel, dimension (W 750 x H 850 x D 180). with Synthetic Single Jacket Hose 1.5” x 30 meter long and (1) multipurpose dry powder Extinguisher include fittings, joints, unions, dielectric fittings, flanges, gaskets, grooved mechanical couplings, nuts and bolts, hangers and supports and labelling.
A44: a.1 | B44: FHC-II | C44: 24 | D44: Ea | E44: 4850 | F44: 17.39 | G44: =C44-F44 -> 6.61 | H44: =F44+G44 -> 24 | I44: =E44*F44 -> 84341.5 | J44: =G44*E44 -> 32058.5 | K44: =I44+J44 -> 116400 | L44: =H44/C44 -> 1 | M44: 4200 | N44: 250 | O44: 400 | P44: =C44*(M44+N44+O44) -> 116400 | Q44: =K44-P44 -> 0
B45: SUB-TOTAL ITEM NO. B9-21 00 00 | C45: xxx | D45: xxx | I45: =SUM(I9:I44) -> 428538.46 | J45: =SUM(J9:J44) -> 307168.39 | K45: =SUM(K9:K44) -> 735706.85 | P45: =SUM(P9:P44) -> 412350 | Q45: =SUM(Q9:Q44) -> 320556.85
B46: (TO BE CARRIED TO COMPOSITE SUMMARY)
B48: OWNER | C48: CONSULTANT | I48: CONTRACTOR

Sheet PUMP RM-1
A5: SECTION 2- SCHEDULE OF QUANTITIES AND PRICES | C5: B O Q | G5: THE ACTUAL QTY | J5: AMOUNT (SR) | M5: Percentage
A6: PAY ITEM NO. | B6: DESCRIPTION OF ITEM | C6: ESTIMATED QUANTITY | D6: UNIT | E6: UNIT PRICE(SR) EXCL. VAT | F6: UNIT PRICE(SR) -10% ADVANCE PAYMENT | G6: Previous QTY | H6: Current QTY | I6: Cumulative QTY | J6: Previous | K6: Current | L6: Cumulative | N6: Actual price | O6: Actual Labour charge | P6: Total AP+LC | Q6: Profit
B7: DIVISION 28-ELECTRONIC SAFETY AND SECURITY
A8: 2.0 | B8: Fire Detection and Alarm
A9: a. | B9: Detection and initiation devices
B10: Supply, installation, testing and commissioning of intelligent, addressable type fire alarm detectors and initiating devices as shown on the Contract drawings and specified in the Contract documents complete with all mounting accessories including boxes, connectors and terminations.
A11: a.1 | B11: Smoke detector - photoelectric, addressable, self diagnostic, self address, weather proof | C11: 2 | D11: Ea | E11: 339.5 | F11: =E11*0.9 -> 305.55 | G11: 0 | H11: 2 | I11: =G11+H11 -> 2 | J11: 0 | K11: =H11*E11 -> 679 | L11: =J11+K11 -> 679 | M11: =I11/C11 -> 1 | N11: 120 | O11: 80 | P11: =C11*(N11+O11) -> 400 | Q11: =L11-P11 -> 279
A12: a.2 | B12: Addressable manual fire alarm pull station, weather proof | C12: 1 | D12: Ea | E12: 291 | F12: =E12*0.9 -> 261.9 | G12: 0 | H12: 1 | I12: =G12+H12 -> 1 | J12: 0 | K12: =H12*E12 -> 291 | L12: =J12+K12 -> 291 | M12: =I12/C12 -> 1 | N12: 160 | O12: 80 | P12: =C12*(N12+O12) -> 240 | Q12: =L12-P12 -> 51
A13: b. | B13: Fire alarm cables - fire resistant cable, 300V/500V, red sheath with low emission of smoke, halogen free, thermoplastic material | E13: 0
B14: To include for the procurement, supply, factory testing, delivery to Site, installation, testing and commissioning of the cables, termination materials and all cable support and wiring, identification accessories.
A15: b.1 | B15: 2C x 2.5 mm², Stranded plain copper wire or solid conductor, overall shield with drain wire for NAC Loop | C15: 80 | D15: m | E15: 24.25 | F15: =E15*0.9 -> 21.825 | G15: 0 | H15: 80 | I15: =G15+H15 -> 80 | J15: =G15*E15 -> 0 | K15: =H15*E15 -> 1940 | L15: =J15+K15 -> 1940 | M15: =I15/C15 -> 1 | N15: 8 | O15: 0 | P15: =C15*(N15+O15) -> 640 | Q15: =L15-P15 -> 1300
A16: c. | B16: Fire alarm cable conduit, all JB boxes, fittings and accessories for cable installations
B17: To include for the procurement, supply, installation of PVC conduits and flexible metallic conduits for fire cables, junction boxes, fittings, accessories and all other relevant items or Works to complete fully Fire alarm detection system installations.
A18: c.1 | B18: 20 mm diameter, PVC conduits | C18: 0 | D18: m | E18: 24.25 | F18: =E18*0.9 -> 21.825 | G18: 0 | H18: 0 | I18: 0 | J18: 0 | K18: 0 | L18: =J18+K18 -> 0
B19: SUB-TOTAL ITEM NO. B11-28 00 00 | C19: xxx | D19: xxx | J19: 0 | K19: =SUM(K11:K18) -> 2910 | L19: =SUM(L11:L18) -> 2910 | P19: =SUM(P11:P18) -> 1280 | Q19: =SUM(Q11:Q18) -> 1630
B20: (TO BE CARRIED TO COMPOSITE SUMMARY)
B21: OWNER | C21: CONSULTANT | J21: CONTRACTOR

Sheet PUMP-R1-EXT
C5: PUMP01
A6: SECTION 2- SCHEDULE OF QUANTITIES AND PRICES | C6: B O Q | F6: THE ACTUAL QTY | I6: AMOUNT (SR) | L6: Percentage
A7: PAY ITEM NO. | B7: DESCRIPTION OF ITEM | C7: ESTIMATED QUANTITY | D7: UNIT | E7: UNIT PRICE(SR) EXCL. VAT | F7: Previous QTY | G7: Current QTY | H7: Cumulative QTY | I7: Previous | J7: Current | K7: Cumulative | M7: Actual price | N7: Actual Labour charge | O7: Total AP+LC | P7: Profit
B8: DIVISION 10 - SPECIALTIES
A9: 1.0 | B9: Fire Extinguishers
A10: a. | B10: Multipurpose dry chemical type, UL rated ABC
B11: Includes mounting brackets, fasteners, service tags, fully charged and ready to use extinguishers.
A12: a.1 | B12: FE-1, 6 kg, Multi-purpose fire extinguisher | C12: 1 | D12: Ea | E12: 242.5 | F12: 0.75 | G12: =C12-F12 -> 0.25 | H12: =F12+G12 -> 1 | I12: =E12*F12 -> 181.875 | J12: =G12*E12 -> 60.625 | K12: =I12+J12 -> 242.5 | L12: =H12/C12 -> 1 | M12: 240 | N12: 10 | O12: =C12*(M12+N12) -> 250 | P12: =K12-O12 -> -7.5
A13: a.2 | B13: FE-2, 6 kg, carbon dioxide fire extinguisher | C13: 1 | D13: Ea | E13: 388 | F13: 0.65 | G13: =C13-F13 -> 0.35 | H13: =F13+G13 -> 1 | I13: =E13*F13 -> 252.2 | J13: =G13*E13 -> 135.8 | K13: =I13+J13 -> 388 | L13: =H13/C13 -> 1 | M13: 500 | N13: 10 | O13: =C13*(M13+N13) -> 510 | P13: =K13-O13 -> -122
A14: b. | B14: Automatic fire extinguisher
A15: b.1 | B15: AFE-5, 30 kg, multi purpose fire extinguisher, ceiling mounted | C15: 25 | D15: Ea | E15: 630.5 | F15: 8.45 | G15: =C15-F15 -> 16.55 | H15: =F15+G15 -> 25 | I15: =E15*F15 -> 5327.725 | J15: =G15*E15 -> 10434.775 | K15: =I15+J15 -> 15762.5 | L15: =H15/C15 -> 1 | M15: 435 | N15: 10 | O15: =C15*(M15+N15) -> 11125 | P15: =K15-O15 -> 4637.5
B16: SUB-TOTAL ITEM NO. B11-10 00 00 | C16: xxx | D16: xxx | I16: =SUM(I9:I15) -> 5761.8 | J16: =SUM(J9:J15) -> 10631.2 | K16: =SUM(K9:K15) -> 16393 | O16: =SUM(O10:O15) -> 11885 | P16: =SUM(P10:P15) -> 4508

Sheet PUMP RM-2
A5: SECTION 2- SCHEDULE OF QUANTITIES AND PRICES | C5: B O Q | G5: THE ACTUAL QTY | J5: AMOUNT (SR) | M5: Percentage
A6: PAY ITEM NO. | B6: DESCRIPTION OF ITEM | C6: ESTIMATED QUANTITY | D6: UNIT | E6: UNIT PRICE(SR) EXCL. VAT | F6: UNIT PRICE(SR) -10% ADVANCE PAYMENT | G6: Previous QTY | H6: Current QTY | I6: Cumulative QTY | J6: Previous | K6: Current | L6: Cumulative | N6: Actual price | O6: Actual Labour charge | P6: Total AP+LC | Q6: Profit
B7: DIVISION 28-ELECTRONIC SAFETY AND SECURITY
A8: 2.0 | B8: Fire Detection and Alarm
A9: a. | B9: Detection and initiation devices
B10: Supply, installation, testing and commissioning of intelligent, addressable type fire alarm detectors and initiating devices as shown on the Contract drawings and specified in the Contract documents complete with all mounting accessories including boxes, connectors and terminations.
A11: a.1 | B11: Smoke detector - photoelectric, addressable, self diagnostic, self address, weather proof | C11: 2 | D11: Ea | E11: 339.5 | F11: =E11*0.9 -> 305.55 | G11: 0 | H11: 2 | I11: =G11+H11 -> 2 | J11: 0 | K11: =H11*E11 -> 679 | L11: =J11+K11 -> 679 | M11: =I11/C11 -> 1 | N11: 120 | O11: 80 | P11: =C11*(N11+O11) -> 400 | Q11: =L11-P11 -> 279
A12: a.2 | B12: Addressable manual fire alarm pull station, weather proof | C12: 1 | D12: Ea | E12: 291 | F12: =E12*0.9 -> 261.9 | G12: 0 | H12: 1 | I12: =G12+H12 -> 1 | J12: 0 | K12: =H12*E12 -> 291 | L12: =J12+K12 -> 291 | M12: =I12/C12 -> 1 | N12: 160 | O12: 80 | P12: =C12*(N12+O12) -> 240 | Q12: =L12-P12 -> 51
A13: b. | B13: Other initiating devices and control devices
B14: Supply, Installation, testing and commissioning of all conventional I/O interfaces devices for interface and Integration with firefighting systems, gas alarm and control systems, lift safety devices, fire water pumps, HVAC systems. elevators and all other specified equipment as per contract drawings and specifications, complete with all mounting accessories including boxes and terminations.
A15: b.1 | B15: Fire alarm monitoring module (MM) | C15: 2 | D15: Ea | E15: 4365 | F15: =E15*0.9 -> 3928.5 | G15: 0 | H15: 2 | I15: =G15+H15 -> 2 | J15: 0 | K15: =H15*E15 -> 8730 | L15: =J15+K15 -> 8730 | M15: =I15/C15 -> 1 | N15: 140 | O15: 0 | P15: =C15*(N15+O15) -> 280 | Q15: =L15-P15 -> 8450
A16: c. | B16: Fire alarm cables - fire resistant cable, 300V/500V, red sheath with low emission of smoke, halogen free, thermoplastic material
B17: To include for the procurement, supply, factory testing, delivery to Site, installation, testing and commissioning of the cables, termination materials and all cable support and wiring, identification accessories.
A18: c.1 | B18: 2C x 2.5 mm², Stranded plain copper wire or solid conductor, overall shield with drain wire for NAC Loop | C18: 80 | D18: m | E18: 24.25 | F18: =E18*0.9 -> 21.825 | G18: 0 | H18: 80 | I18: =G18+H18 -> 80 | J18: =G18*E18 -> 0 | K18: =H18*E18 -> 1940 | L18: =J18+K18 -> 1940 | M18: =I18/C18 -> 1 | N18: 8 | O18: 0 | P18: =C18*(N18+O18) -> 640 | Q18: =L18-P18 -> 1300
A19: d. | B19: Fire alarm cable conduit, all JB boxes, fittings and accessories for cable installations
B20: To include for the procurement, supply, installation of PVC conduits and flexible metallic conduits for fire cables, junction boxes, fittings, accessories and all other relevant items or Works to complete fully Fire alarm detection system installations.
A21: d.1 | B21: 20 mm diameter, PVC conduits | C21: 0 | D21: m | E21: 24.25 | F21: =E21*0.9 -> 21.825 | G21: 0 | H21: 0 | I21: 0 | J21: 0 | K21: 0 | L21: =J21+K21 -> 0
B22: SUB-TOTAL ITEM NO. B12-28 00 00 | C22: xxx | D22: xxx | G22: 0 | J22: =SUM(J11:J21) -> 0 | K22: =SUM(K11:K21) -> 11640 | L22: =SUM(L11:L21) -> 11640 | P22: =SUM(P11:P18) -> 1560 | Q22: =SUM(Q11:Q18) -> 10080
B23: (TO BE CARRIED TO COMPOSITE SUMMARY)
B24: OWNER | C24: CONSULTANT | J24: CONTRACTOR

Sheet PUMP-R2-EXT
C5: PUMP02
A6: SECTION 2- SCHEDULE OF QUANTITIES AND PRICES | C6: B O Q | F6: THE ACTUAL QTY | I6: AMOUNT (SR) | L6: Percentage
A7: PAY ITEM NO. | B7: DESCRIPTION OF ITEM | C7: ESTIMATED QUANTITY | D7: UNIT | E7: UNIT PRICE(SR) EXCL. VAT | F7: Previous QTY | G7: Current QTY | H7: Cumulative QTY | I7: Previous | J7: Current | K7: Cumulative | M7: Actual price | N7: Actual Labour charge | O7: Total AP+LC | P7: Profit
B8: DIVISION 10 - SPECIALTIES
A9: 1.0 | B9: Fire Extinguishers
B10: Includes mounting brackets, fasteners, service tags, fully charged and ready to use extinguishers.
A11: a. | B11: Multipurpose dry chemical type, UL rated ABC
A12: a.1 | B12: FE-1, 6 kg, multi purpose fire extinguisher | C12: 1 | D12: Ea | E12: 242.5 | F12: 0.75 | G12: =C12-F12 -> 0.25 | H12: =F12+G12 -> 1 | I12: =E12*F12 -> 181.875 | J12: =G12*E12 -> 60.625 | K12: =I12+J12 -> 242.5 | L12: =H12/C12 -> 1 | M12: 240 | N12: 10 | O12: =C12*(M12+N12) -> 250 | P12: =K12-O12 -> -7.5
A13: b. | B13: Automatic fire extinguisher
A14: b.1 | B14: FE-2, 6 kg, carbon dioxide fire extinguisher | C14: 1 | D14: Ea | E14: 388 | F14: 0.65 | G14: =C14-F14 -> 0.35 | H14: =F14+G14 -> 1 | I14: =E14*F14 -> 252.2 | J14: =G14*E14 -> 135.8 | K14: =I14+J14 -> 388 | L14: =H14/C14 -> 1 | M14: 500 | N14: 10 | O14: =C14*(M14+N14) -> 510 | P14: =K14-O14 -> -122
B15: SUB-TOTAL ITEM NO. B12-10 00 00 | C15: xxx | D15: xxx | I15: =SUM(I9:I14) -> 434.075 | J15: =SUM(J9:J14) -> 196.425 | K15: =SUM(K9:K14) -> 630.5 | O15: =SUM(O9:O14) -> 760 | P15: =SUM(P9:P14) -> -129.5

Sheet PUMP RM-3
B4: PUMP RM3
B5: B O Q | F5: THE ACTUAL QTY | I5: AMOUNT (SR)
A6: DESCRIPTION OF ITEM | B6: ESTIMATED QUANTITY | C6: UNIT | D6: UNIT PRICE(SR) EXCL. VAT | E6: UNIT PRICE(SR) -10% ADVANCE PAYMENT | F6: Previous QTY | G6: Current QTY | H6: Cumulative QTY | I6: Previous | J6: Current | K6: Cumulative | L6: Percentage | M6: Actual price | N6: Actual Labour charge | O6: Total AP+LC | P6: Profit
A7: DIVISION 28-ELECTRONIC SAFETY AND SECURITY
A8: Fire Detection and Alarm
A9: Detection and initiation devices
A10: Supply, installation, testing and commissioning of intelligent, addressable type fire alarm detectors and initiating devices as shown on the Contract drawings and specified in the Contract documents complete with all mounting accessories including boxes, connectors and terminations.
A11: Smoke detector - photoelectric, addressable, self diagnostic, self address, weather proof | B11: 2 | C11: Ea | D11: 339.5 | E11: =D11*0.9 -> 305.55 | F11: 0 | G11: 2 | H11: =F11+G11 -> 2 | I11: 0 | J11: =D11*G11 -> 679 | K11: =I11+J11 -> 679 | L11: =H11/B11 -> 1 | M11: 120 | N11: 80 | O11: =B11*(M11+N11) -> 400 | P11: =K11-O11 -> 279
A12: Addressable manual fire alarm pull station, weather proof | B12: 1 | C12: Ea | D12: 291 | E12: =D12*0.9 -> 261.9 | F12: 0 | G12: 1 | H12: =F12+G12 -> 1 | I12: 0 | J12: =D12*G12 -> 291 | K12: =I12+J12 -> 291 | L12: =H12/B12 -> 1 | M12: 160 | N12: 80 | O12: =B12*(M12+N12) -> 240 | P12: =K12-O12 -> 51
A13: Fire alarm cables - fire resistant cable, 300V/500V, red sheath with low emission of smoke, halogen free, thermoplastic material
A14: To include for the procurement, supply, factory testing, delivery to Site, installation, testing and commissioning of the cables, termination materials and all cable support and wiring, identification accessories.
A15: 2C x 2.5 mm², Stranded plain copper wire or solid conductor, overall shield with drain wire for NAC Loop | B15: 80 | C15: m | D15: 24.25 | E15: =D15*0.9 -> 21.825 | F15: 0 | G15: 80 | H15: =F15+G15 -> 80 | I15: =E15*F15 -> 0 | J15: =D15*G15 -> 1940 | K15: =I15+J15 -> 1940 | L15: =H15/B15 -> 1 | M15: 8 | N15: 0 | O15: =B15*(M15+N15) -> 640 | P15: =K15-O15 -> 1300
A16: Fire alarm cable conduit, all JB boxes, fittings and accessories for cable installations
A17: To include for the procurement, supply, installation of PVC conduits and flexible metallic conduits for fire cables, junction boxes, fittings, accessories and all other relevant items or Works to complete fully Fire alarm detection system installations.
A18: 20 mm diameter, PVC conduits | B18: 0 | C18: m | D18: 24.25 | E18: =D18*0.9 -> 21.825 | F18: 0 | G18: 0 | H18: 0 | I18: 0 | J18: 0 | K18: =I18+J18 -> 0 | M18: 0 | N18: 0 | O18: =B18*(M18+N18) -> 0 | P18: =K18-O18 -> 0
A19: SUB-TOTAL ITEM NO. B13-28 00 00 | B19: xxx | C19: xxx | I19: 0 | J19: =SUM(J11:J18) -> 2910 | K19: =SUM(K11:K18) -> 2910 | O19: =SUM(O11:O18) -> 1280 | P19: =SUM(P11:P18) -> 1630
A20: (TO BE CARRIED TO COMPOSITE SUMMARY)
A22: OWNER | D22: CONSULTANT | I22: CONTRACTOR

Sheet PUMP-R3-EXT
C5: PUMP03
A6: SECTION 2- SCHEDULE OF QUANTITIES AND PRICES | C6: B O Q | F6: THE ACTUAL QTY | I6: AMOUNT (SR) | L6: Percentage
A7: PAY ITEM NO. | B7: DESCRIPTION OF ITEM | C7: ESTIMATED QUANTITY | D7: UNIT | E7: UNIT PRICE(SR) EXCL. VAT | F7: Previous QTY | G7: Current QTY | H7: Cumulative QTY | I7: Previous | J7: Current | K7: Cumulative | M7: Actual price | N7: Actual Labour charge | O7: Total AP+LC | P7: Profit
B8: DIVISION 10 - SPECIALTIES
A9: 1.0 | B9: Fire Extinguishers
A10: a. | B10: Multipurpose dry chemical type, UL rated ABC
B11: Includes mounting brackets, fasteners, service tags, fully charged and ready to use extinguishers.
A12: a.1 | B12: FE-1, 6 kg, Multi-purpose fire extinguisher | C12: 1 | D12: Ea | E12: 242.5 | F12: 0.75 | G12: =C12-F12 -> 0.25 | H12: =F12+G12 -> 1 | I12: =E12*F12 -> 181.875 | J12: =G12*E12 -> 60.625 | K12: =I12+J12 -> 242.5 | L12: =H12/C12 -> 1 | M12: 240 | N12: 10 | O12: =C12*(M12+N12) -> 250 | P12: =K12-O12 -> -7.5
A13: a.2 | B13: FE-2, 6 kg, carbon dioxide fire extinguisher | C13: 1 | D13: Ea | E13: 388 | F13: 0.65 | G13: =C13-F13 -> 0.35 | H13: =F13+G13 -> 1 | I13: =E13*F13 -> 252.2 | J13: =G13*E13 -> 135.8 | K13: =I13+J13 -> 388 | L13: =H13/C13 -> 1 | M13: 500 | N13: 10 | O13: =C13*(M13+N13) -> 510 | P13: =K13-O13 -> -122
A14: b. | B14: Automatic fire extinguisher
A15: b.1 | B15: AFE-5, 30 kg, multi purpose fire extinguisher, ceiling mounted | C15: 12 | D15: Ea | E15: 630.5 | F15: 7.8 | G15: =C15-F15 -> 4.2 | H15: =F15+G15 -> 12 | I15: =E15*F15 -> 4917.9 | J15: =G15*E15 -> 2648.1 | K15: =I15+J15 -> 7566 | L15: =H15/C15 -> 1 | M15: 435 | N15: 10 | O15: =C15*(M15+N15) -> 5340 | P15: =K15-O15 -> 2226
B16: SUB-TOTAL ITEM NO. B13-10 00 00 | C16: xxx | D16: xxx | I16: =SUM(I9:I15) -> 5351.975 | J16: =SUM(J9:J15) -> 2844.525 | K16: =SUM(K9:K15) -> 8196.5 | O16: =SUM(O10:O15) -> 6100 | P16: =SUM(P10:P15) -> 2096.5

Sheet PUMP02
C3: PUMP 02
A4: SECTION 2- SCHEDULE OF QUANTITIES AND PRICES | C4: B O Q | F4: THE ACTUAL QTY | I4: AMOUNT (SR)
A5: PAY ITEM NO. | B5: DESCRIPTION OF ITEM | C5: ESTIMATED QUANTITY | D5: UNIT | E5: UNIT PRICE(SR) EXCL. VAT | F5: Previous QTY | G5: Current QTY | H5: Cumulative QTY | I5: Previous | J5: Current | K5: Cumulative | L5: Percentage | M5: Actual price | N5: accessories | O5: Actual Labour charge | P5: Total AP+LC | Q5: Profit
B6: DIVISION 21 - FIRE SUPPRESSION
A7: 1.0 | B7: General-Duty Valves for Water-Based Fire-Suppression Piping
A8: a. | B8: Gate valve, UL and FM global approved
B9: Supply and installation of valves including all fixings, supports, all other accessories and associated Works.
A10: a.1 | B10: 200 mm diameter | C10: 10 | D10: Ea | E10: 5335 | F10: 9 | G10: =C10-F10 -> 1 | H10: =F10+G10 -> 10 | I10: =E10*F10 -> 48015 | J10: =G10*E10 -> 5335 | K10: =I10+J10 -> 53350 | L10: =H10/C10 -> 1 | M10: 4000 | N10: 300 | O10: 300 | P10: =C10*(M10+N10+O10) -> 46000 | Q10: =K10-P10 -> 7350
A11: b. | B11: Alarm check valve, UL and FM global approved
A12: b.2 | B12: 200 mm diameter | C12: 1 | D12: Ea | E12: 8245 | F12: 0.9 | G12: =C12-F12 -> 0.1 | H12: =F12+G12 -> 1 | I12: =E12*F12 -> 7420.5 | J12: =G12*E12 -> 824.5 | K12: =I12+J12 -> 8245 | L12: =H12/C12 -> 1 | M12: 1800 | N12: 200 | O12: 100 | P12: =C12*(M12+N12+O12) -> 2100 | Q12: =K12-P12 -> 6145
A13: c. | B13: Check valve, UL and FM global approved
A14: c.1 | B14: 200 mm diameter | C14: 2 | D14: Ea | E14: 4850 | F14: 1.8 | G14: =C14-F14 -> 0.2 | H14: =F14+G14 -> 2 | I14: =E14*F14 -> 8730 | J14: =G14*E14 -> 970 | K14: =I14+J14 -> 9700 | L14: =H14/C14 -> 1 | M14: 2500 | N14: 150 | O14: 100 | P14: =C14*(M14+N14+O14) -> 5500 | Q14: =K14-P14 -> 4200
A15: c.2 | B15: 50 mm diameter | C15: 1 | D15: Ea | E15: 2425 | F15: 0.9 | G15: =C15-F15 -> 0.1 | H15: =F15+G15 -> 1 | I15: =E15*F15 -> 2182.5 | J15: =G15*E15 -> 242.5 | K15: =I15+J15 -> 2425 | L15: =H15/C15 -> 1 | M15: 850 | N15: 100 | O15: 100 | P15: =C15*(M15+N15+O15) -> 1050 | Q15: =K15-P15 -> 1375
A16: d. | B16: Zone control valve assembly
A17: d.1 | B17: 65 mm diameter | C17: 1 | D17: Ea | E17: 4365 | F17: 0.8 | G17: =C17-F17 -> 0.2 | H17: =F17+G17 -> 1 | I17: =E17*F17 -> 3492 | J17: =G17*E17 -> 873 | K17: =I17+J17 -> 4365 | L17: =H17/C17 -> 1 | M17: 2800 | N17: 300 | O17: 100 | P17: =C17*(M17+N17+O17) -> 3200 | Q17: =K17-P17 -> 1165
A18: e. | B18: Flow meter
A19: e.1 | B19: 150 mm diameter | C19: 1 | D19: Ea | E19: 8730 | F19: 0.9 | G19: =C19-F19 -> 0.1 | H19: =F19+G19 -> 1 | I19: =E19*F19 -> 7857 | J19: =G19*E19 -> 873 | K19: =I19+J19 -> 8730 | L19: =H19/C19 -> 1 | M19: 0 | N19: 0 | O19: 0 | P19: =C19*(M19+N19+O19) -> 0 | Q19: =K19-P19 -> 8730
A20: f. | B20: Flexible pipe connection
A21: f.1 | B21: 50 mm diameter | C21: 2 | D21: Ea | E21: 1746 | F21: 0 | G21: =C21-F21 -> 2 | H21: =F21+G21 -> 2 | I21: =E21*F21 -> 0 | J21: =G21*E21 -> 3492 | K21: =I21+J21 -> 3492 | L21: =H21/C21 -> 1 | M21: 0 | N21: 0
A22: f.2 | B22: 150 mm diameter | C22: 8 | D22: Ea | E22: 2619 | F22: 0 | G22: =C22-F22 -> 8 | H22: =F22+G22 -> 8 | I22: =E22*F22 -> 0 | J22: =G22*E22 -> 20952 | K22: =I22+J22 -> 20952 | L22: =H22/C22 -> 1 | M22: 0 | N22: 0 | O22: 0 | P22: =C22*(M22+N22+O22) -> 0 | Q22: =K22-P22 -> 20952
A23: g. | B23: Strainer, Y type | M23: 0 | N23: 0 | O23: 0 | P23: =C23*(M23+N23+O23) -> 0 | Q23: =K23-P23 -> 0
A24: g.1 | B24: 200 mm diameter | C24: 1 | D24: Ea | E24: 3589 | F24: 0 | G24: =C24-F24 -> 1 | H24: =F24+G24 -> 1 | I24: =E24*F24 -> 0 | J24: =G24*E24 -> 3589 | K24: =I24+J24 -> 3589 | L24: =H24/C24 -> 1 | M24: 0 | N24: 0 | O24: 0 | P24: =C24*(M24+N24+O24) -> 0 | Q24: =K24-P24 -> 3589
A25: g.2 | B25: 50 mm diameter | C25: 1 | D25: Ea | E25: 2134 | F25: 0 | G25: =C25-F25 -> 1 | H25: =F25+G25 -> 1 | I25: =E25*F25 -> 0 | J25: =G25*E25 -> 2134 | K25: =I25+J25 -> 2134 | L25: =H25/C25 -> 1 | M25: 0 | N25: 0 | O25: 0 | P25: =C25*(M25+N25+O25) -> 0 | Q25: =K25-P25 -> 2134
A26: 2.0 | B26: Wet-Pipe Sprinkler Systems
A27: a. | B27: Black steel fire water pipes
B28: Supply and installation of black steel pipe seamless type as per ASTM A53 including supports, hangers, fixing, fitting, all other accessories and associated Works as per Contract drawings and specifications.
A29: a.1 | B29: 25 mm diameter | C29: 5 | D29: m | E29: 53.35 | F29: 4.5 | G29: =C29-F29 -> 0.5 | H29: =F29+G29 -> 5 | I29: =E29*F29 -> 240.075 | J29: =G29*E29 -> 26.675 | K29: =I29+J29 -> 266.75 | L29: =H29/C29 -> 1 | M29: 15 | N29: 7.5 | O29: 0 | P29: =C29*(M29+N29+O29) -> 112.5 | Q29: =K29-P29 -> 154.25
A30: a.2 | B30: 32 mm diameter | C30: 5 | D30: m | E30: 63.05 | F30: 4.5 | G30: =C30-F30 -> 0.5 | H30: =F30+G30 -> 5 | I30: =E30*F30 -> 283.725 | J30: =G30*E30 -> 31.525 | K30: =I30+J30 -> 315.25 | L30: =H30/C30 -> 1 | M30: 20 | N30: 10 | O30: 0 | P30: =C30*(M30+N30+O30) -> 150 | Q30: =K30-P30 -> 165.25
A31: a.3 | B31: 40 mm diameter | C31: 5 | D31: m | E31: 77.6 | F31: 4.5 | G31: =C31-F31 -> 0.5 | H31: =F31+G31 -> 5 | I31: =E31*F31 -> 349.2 | J31: =G31*E31 -> 38.8 | K31: =I31+J31 -> 388 | L31: =H31/C31 -> 1 | M31: 24 | N31: 12 | O31: 0 | P31: =C31*(M31+N31+O31) -> 180 | Q31: =K31-P31 -> 208
A32: a.4 | B32: 50 mm diameter | C32: 15 | D32: m | E32: 95.06 | F32: 13.528 | G32: =C32-F32 -> 1.472 | H32: =F32+G32 -> 15 | I32: =E32*F32 -> 1285.9717 | J32: =G32*E32 -> 139.92832 | K32: =I32+J32 -> 1425.9 | L32: =H32/C32 -> 1 | M32: 28 | N32: 14 | O32: 0 | P32: =C32*(M32+N32+O32) -> 630 | Q32: =K32-P32 -> 795.9
A33: a.5 | B33: 150 mm diameter | C33: 15 | D33: m | E33: 344.35 | F33: 13.425 | G33: =C33-F33 -> 1.575 | H33: =F33+G33 -> 15 | I33: =E33*F33 -> 4622.8988 | J33: =G33*E33 -> 542.35125 | K33: =I33+J33 -> 5165.25 | L33: =H33/C33 -> 1 | M33: 170 | N33: 90 | O33: 0 | P33: =C33*(M33+N33+O33) -> 3900 | Q33: =K33-P33 -> 1265.25
A34: a.6 | B34: 200 mm diameter | C34: 50 | D34: m | E34: 295.85 | F34: 45 | G34: =C34-F34 -> 5 | H34: =F34+G34 -> 50 | I34: =E34*F34 -> 13313.25 | J34: =G34*E34 -> 1479.25 | K34: =I34+J34 -> 14792.5 | L34: =H34/C34 -> 1 | M34: 190 | N34: 85 | O34: 0 | P34: =C34*(M34+N34+O34) -> 13750 | Q34: =K34-P34 -> 1042.5
A35: b. | B35: Fire water sprinkler head
B36: Sprinkler Head, UL listed FM approved, chrome-plated, bronze and factory painted; Shall be of one manufacturer. (No mixing of sprinkler brands shall be permitted).
A37: b.1 | B37: Type, upright | C37: 18 | D37: Ea | E37: 33.95 | F37: 16.2 | G37: =C37-F37 -> 1.8 | H37: =F37+G37 -> 18 | I37: =E37*F37 -> 549.99 | J37: =G37*E37 -> 61.11 | K37: =I37+J37 -> 611.1 | L37: =H37/C37 -> 1 | M37: 19 | N37: 5 | O37: 100 | P37: =C37*(M37+N37+O37) -> 2232 | Q37: =K37-P37 -> -1620.9
A38: 3.0 | B38: Fire Pumps
A39: a. | B39: Electric-drive, centrifugal fire pumps
B40: Supply and installation of Electric-drive, centrifugal fire pumps including all required accessories, piping, valves, strainers, check valves, control panels and all the fittings required, instrumentation devices, dismantling joint, flow meters and other associated Works and complete pipe connections as detailed in Contract drawings. Works include testing and commissioning.
A41: a.1 | B41: 1500 GPM, 130 PSI | C41: 1 | D41: Ea | E41: 150738 | F41: 0.85 | G41: =C41*0.15 -> 0.15 | H41: =F41+G41 -> 1 | I41: =E41*F41 -> 128127.3 | J41: =G41*E41 -> 22610.7 | K41: =I41+J41 -> 150738 | L41: =H41/C41 -> 1 | M41: 100000 | N41: 10000 | O41: 5000 | P41: =C41*(M41+N41+O41) -> 115000 | Q41: =K41-P41 -> 35738
A42: b. | B42: Electric drive jockey pump
B43: Supply and installation of fire electrical jockey pump capacity 50 gpm & 130 Psi (1duty) with enclosure including all required accessories, piping, valves, strainers, check valves, control panels and all the fittings required, instrumentation devices, dismantling joint, flow meters and other associated Works and complete pipe connections as detailed in Contract drawings. Works include testing and commissioning.
A44: b.1 | B44: 50 GPM, 130 PSI | C44: 1 | D44: Ea | E44: 18333 | F44: 0.85 | G44: =C44-F44 -> 0.15 | H44: =F44+G44 -> 1 | I44: =E44*F44 -> 15583.05 | J44: =G44*E44 -> 2749.95 | K44: =I44+J44 -> 18333 | L44: =H44/C44 -> 1 | M44: 15000 | N44: 2000 | O44: 500 | P44: =C44*(M44+N44+O44) -> 17500 | Q44: =K44-P44 -> 833
A45: c. | B45: Diesel Fire pump
B46: Supply and installation of Diesel Fire pump including all required accessories, piping, valves, strainers, check valves, control panels and all the fittings required, instrumentation devices, dismantling joint, flow meters and other associated Works and complete pipe connections as detailed in Contract drawings. Works include testing and commissioning.
A47: c.1 | B47: 1500 GPM, 130 PSI | C47: 1 | D47: Ea | E47: 232800 | F47: 0.85 | G47: =C47-F47 -> 0.15 | H47: =F47+G47 -> 1 | I47: =E47*F47 -> 197880 | J47: =G47*E47 -> 34920 | K47: =I47+J47 -> 232800 | L47: =H47/C47 -> 1 | M47: 150000 | N47: 8000 | O47: 10000 | P47: =C47*(M47+N47+O47) -> 168000 | Q47: =K47-P47 -> 64800
B48: SUB-TOTAL ITEM NO. B12-21 00 00 | C48: xxx | D48: xxx | I48: =SUM(I9:I47) -> 439932.46 | J48: =SUM(J10:J47) -> 101885.29 | K48: =SUM(K9:K47) -> 541817.75 | P48: =SUM(P9:P44) -> 211304.5 | Q48: =SUM(Q9:Q47) -> 159021.25
B49: (TO BE CARRIED TO COMPOSITE SUMMARY)
B51: OWNER | C51: CONSULTANT | I51: CONTRACTOR

Sheet GUARD RM
B4: GUARD ROOM
B5: B O Q | E5: THE ACTUAL QTY | H5: AMOUNT (SR) | K5: Percentage
A6: DESCRIPTION OF ITEM | B6: ESTIMATED QUANTITY | C6: UNIT | D6: UNIT PRICE(SR) EXCL. VAT | E6: Previous QTY | F6: Current QTY | G6: Cumulative QTY | H6: Previous | I6: Current | J6: Cumulative | L6: Actual price | M6: Actual Labour charge | N6: Total AP+LC | O6: Profit
A7: DIVISION 28-ELECTRONIC SAFETY AND SECURITY
A8: Fire Detection and Alarm
A9: Fire alarm control panel (FACP)
A10: Supply, installation, testing and commissioning of a microprocessor based, addressable fire alarm control panel, complete with Chassis, 640-Character backlit LCD display, QWERTY programming and control keypad, loop cards, zone and input/output modules, supervisory devices, auxiliary relays, network capability modules, battery, battery charger, printer, internal alarm, interface contacts and all accessories and hardware as shown on the Contract drawings and specified in the Contract documents and to complete the fully functional, operable, reliable and maintainable fire alarm system.
A11: Microprocessor based, addressable FACP, 5 loop type | B11: 1 | C11: Ea | D11: 22795 | E11: 0.65 | F11: =B11-E11 -> 0.35 | G11: =E11+F11 -> 1 | H11: =E11*D11 -> 14816.75 | I11: =D11*F11 -> 7978.25 | J11: =H11+I11 -> 22795 | K11: =G11/B11 -> 1 | L11: 16900 | M11: 80 | N11: =B11*(L11+M11) -> 16980 | O11: =J11-N11 -> 5815
A12: Fire alarm repeater panel (FARP) | B12: 1 | C12: Ea | D12: 12998 | E12: 0.65 | F12: =B12-E12 -> 0.35 | G12: =E12+F12 -> 1 | H12: =E12*D12 -> 8448.7 | I12: =D12*F12 -> 4549.3 | J12: =H12+I12 -> 12998 | K12: =G12/B12 -> 1 | L12: 5800 | M12: 80 | N12: =B12*(L12+M12) -> 5880 | O12: =J12-N12 -> 7118
A13: Power supply unit, batteries and battery chargers | B13: 1 | C13: Ea | D13: 4365 | E13: 0 | F13: =B13-E13 -> 1 | G13: =E13+F13 -> 1 | H13: =E13*D13 -> 0 | I13: =D13*F13 -> 4365 | J13: =H13+I13 -> 4365 | K13: =G13/B13 -> 1
A14: Supply, selection and calculation, installation, testing and commissioning of FACP power supply unit, batteries for at least 24 hours during the normal operations and 15 mins under emergency full loaded condition. Provide separate combination of power Supply and battery enclosure when large batteries are required and not be able embedded inside FACP panel.
A15: Detection and initiation devices
A16: Supply, installation, testing and commissioning of intelligent, addressable type fire alarm detectors and initiating devices as shown on the Contract drawings and specified in the Contract documents complete with all mounting accessories including boxes, connectors and terminations.
A17: Smoke detector - photoelectric, addressable, self diagnostic, self address | B17: 2 | C17: Ea | D17: 339.5 | E17: 1.3 | F17: =B17-E17 -> 0.7 | G17: =E17+F17 -> 2 | H17: =E17*D17 -> 441.35 | I17: =D17*F17 -> 237.65 | J17: =H17+I17 -> 679 | K17: =G17/B17 -> 1 | L17: 120 | M17: 80 | N17: =B17*(L17+M17) -> 400 | O17: =J17-N17 -> 279
A18: Heat detector - rate of rise type with fix temperature | B18: 1 | C18: Ea | D18: 339.5 | E18: 0 | F18: =B18-E18 -> 1 | G18: =E18+F18 -> 1 | H18: 0 | I18: =D18*F18 -> 339.5 | J18: =H18+I18 -> 339.5 | K18: =G18/B18 -> 1 | L18: 110 | M18: 80 | N18: =B18*(L18+M18) -> 190 | O18: =J18-N18 -> 149.5
A19: Addressable manual fire alarm pull station | B19: 1 | C19: Ea | D19: 291 | E19: 0.65 | F19: =B19-E19 -> 0.35 | G19: =E19+F19 -> 1 | H19: =E19*D19 -> 189.15 | I19: =D19*F19 -> 101.85 | J19: =H19+I19 -> 291 | K19: =G19/B19 -> 1 | L19: 160 | M19: 80 | N19: =B19*(L19+M19) -> 240 | O19: =J19-N19 -> 51
A20: Notification appliances
A21: Supply, installation, testing and commissioning of visual and sound alarm devices as shown on the Contract drawings and specified in the Contract documents complete with all mounting accessories including boxes and terminations.
A22: Bells, indoor with strobe lights / beacons - red body, red lens for fire alarm | B22: 1 | C22: Ea | D22: 388 | E22: 0.65 | F22: =B22-E22 -> 0.35 | G22: =E22+F22 -> 1 | H22: =E22*D22 -> 252.2 | I22: =D22*F22 -> 135.8 | J22: =H22+I22 -> 388 | K22: =G22/B22 -> 1 | L22: 220 | M22: 80 | N22: =B22*(L22+M22) -> 300 | O22: =J22-N22 -> 88
A23: Bells, indoor with strobe lights / beacons - red body, red lens for fire alarm, weather proof | B23: 2 | C23: Ea | D23: 436.5 | E23: 0 | F23: =B23-E23 -> 2 | G23: =E23+F23 -> 2 | H23: 0 | I23: =D23*F23 -> 873 | J23: =H23+I23 -> 873 | K23: =G23/B23 -> 1 | L23: 250 | M23: 80 | N23: =B23*(L23+M23) -> 660 | O23: =J23-N23 -> 213
A24: Fire alarm cables - fire resistant cable, 300V/500V, red sheath with low emission of smoke, halogen free, thermoplastic material
A25: To include for the procurement, supply, factory testing, delivery to Site, installation, testing and commissioning of the cables, termination materials and all cable support and wiring, identification accessories.
A26: 2C x 2.5 mm², Stranded plain copper wire or solid conductor, overall shield with drain wire for SLC loop | B26: 120 | C26: m | D26: 24.25 | E26: 114 | F26: =B26-E26 -> 6 | G26: =E26+F26 -> 120 | H26: =E26*D26 -> 2764.5 | I26: =D26*F26 -> 145.5 | J26: =H26+I26 -> 2910 | K26: =G26/B26 -> 1 | L26: 8 | M26: 0 | N26: =B26*(L26+M26) -> 960 | O26: =J26-N26 -> 1950
A27: 2C x 2.5 mm², Stranded plain copper wire or solid conductor, overall shield with drain wire for NAC Loop | B27: 30 | C27: m | D27: 24.25 | E27: 28.5 | F27: =B27-E27 -> 1.5 | G27: =E27+F27 -> 30 | H27: =E27*D27 -> 691.125 | I27: =D27*F27 -> 36.375 | J27: =H27+I27 -> 727.5 | K27: =G27/B27 -> 1 | L27: 8 | M27: 0 | N27: =B27*(L27+M27) -> 240 | O27: =J27-N27 -> 487.5
A28: Fire alarm cable conduit, all JB boxes, fittings and accessories for cable installations
A29: To include for the procurement, supply, installation of PVC conduits and flexible metallic conduits for fire cables, junction boxes, fittings, accessories and all other relevant items or Works to complete fully Fire alarm detection system installations.
A30: 20 mm diameter, PVC conduits | B30: 0 | C30: m | D30: 24.25 | E30: 0 | F30: 0 | G30: 0 | H30: 0 | I30: 0 | J30: =H30+I30 -> 0
A31: SUB-TOTAL ITEM NO. B10-28 00 00 | B31: xxx | C31: xxx | H31: =SUM(H11:H30) -> 27603.775 | I31: =SUM(I11:I30) -> 18762.225 | J31: =SUM(J11:J30) -> 46366 | N31: =SUM(N11:N30) -> 25850 | O31: =SUM(O11:O30) -> 16151
A32: (TO BE CARRIED TO COMPOSITE SUMMARY)
A34: OWNER | C34: CONSULTANT | H34: CONTRACTOR

Sheet GUARD-RM-EXT
C5: GUARD
A6: SECTION 2- SCHEDULE OF QUANTITIES AND PRICES | C6: B O Q | F6: THE ACTUAL QTY | I6: AMOUNT (SR) | L6: Percentage
A7: PAY ITEM NO. | B7: DESCRIPTION OF ITEM | C7: ESTIMATED QUANTITY | D7: UNIT | E7: UNIT PRICE(SR) EXCL. VAT | F7: Previous QTY | G7: Current QTY | H7: Cumulative QTY | I7: Previous | J7: Current | K7: Cumulative | M7: Actual price | N7: Actual Labour charge | O7: Total AP+LC | P7: Profit
B8: DIVISION 10 - SPECIALTIES
A9: 1.0 | B9: Fire Extinguishers
A10: a. | B10: Multipurpose dry chemical type, UL rated ABC
B11: Includes mounting brackets, fasteners, service tags, fully charged and ready to use extinguishers.
A12: a.1 | B12: FE-1, 6 kg, Multi-purpose fire extinguisher | C12: 1 | D12: Ea | E12: 242.5 | F12: 0.75 | G12: =C12-F12 -> 0.25 | H12: =F12+G12 -> 1 | I12: =E12*F12 -> 181.875 | J12: =G12*E12 -> 60.625 | K12: =I12+J12 -> 242.5 | L12: =H12/C12 -> 1 | M12: 240 | N12: 10 | O12: =C12*(M12+N12) -> 250 | P12: =K12-O12 -> -7.5
A13: a.2 | B13: FE-2, 6 kg, carbon dioxide fire extinguisher | C13: 1 | D13: Ea | E13: 388 | F13: 0.65 | G13: =C13-F13 -> 0.35 | H13: =F13+G13 -> 1 | I13: =E13*F13 -> 252.2 | J13: =G13*E13 -> 135.8 | K13: =I13+J13 -> 388 | L13: =H13/C13 -> 1 | M13: 500 | N13: 10 | O13: =C13*(M13+N13) -> 510 | P13: =K13-O13 -> -122
B14: SUB-TOTAL ITEM NO. B10-10 00 00 | C14: xxx | D14: xxx | I14: =SUM(I9:I13) -> 434.075 | J14: =SUM(J9:J13) -> 196.425 | K14: =SUM(K9:K13) -> 630.5 | O14: =SUM(O9:O13) -> 760 | P14: =SUM(P9:P13) -> -129.5

Sheet حصر الأنابيب
G4: CONTRACT QUANTITES
C5: Pipe Dia(inch) | D5: JUN-T1 | E5: JUN-T2 | F5: SUPERVISOR | G5: ISOLATED | H5: SENIOR | I5: ADMIN | J5: RECREATION | K5: SERVICE | L5: PUMP RM-2 | P5: CONTRACT TOTAL QTY | Q5: HALF QTY | R5: PREVIOUS SUPPLIED | S5: NEW SUPPLY | T5: TOTAL SUPPLY
C6: 1 | D6: 2550 | E6: 520 | F6: 1305 | G6: 250 | H6: 1485 | J6: 1080 | K6: 2100 | L6: 5 | P6: =SUM(D6:O6) -> 9295 | Q6: =P6/2 -> 4647.5 | R6: 6864 | S6: =384*6 -> 2304 | T6: =S6+R6 -> 9168 | U6: =P6-T6 -> 127 | V6: =U6/6 -> 21.166667
C7: 1.25 | D7: 375 | E7: 120 | F7: 90 | G7: 10 | H7: 90 | J7: 325 | K7: 535 | L7: 5 | P7: =SUM(D7:O7) -> 1550 | Q7: =P7/2 -> 775 | R7: 1164 | S7: =40*6 -> 240 | T7: =S7+R7 -> 1404 | U7: =P7-T7 -> 146 | V7: =U7/6 -> 24.333333
C8: 1.5 | D8: 276 | E8: 20 | F8: 120 | G8: 40 | H8: 135 | I8: 40 | J8: 130 | K8: 285 | L8: 5 | P8: =SUM(D8:O8) -> 1051 | Q8: =P8/2 -> 525.5 | R8: 762 | S8: =41*6 -> 246 | T8: =S8+R8 -> 1008 | U8: =P8-T8 -> 43 | V8: =U8/6 -> 7.1666667
C9: 2 | D9: 90 | E9: 130 | F9: 60 | G9: 30 | H9: 90 | I9: 30 | J9: 60 | K9: 110 | L9: 15 | P9: =SUM(D9:O9) -> 615 | Q9: =P9/2 -> 307.5 | R9: 426 | S9: =24*6 -> 144 | T9: =S9+R9 -> 570 | U9: =P9-T9 -> 45 | V9: =U9/6 -> 7.5
C10: 2.5 | D10: 30 | E10: 190 | F10: 300 | G10: 70 | H10: 345 | I10: 30 | J10: 130 | K10: 130 | P10: =SUM(D10:O10) -> 1225 | Q10: =P10/2 -> 612.5 | R10: 900 | S10: 0 | T10: =S10+R10 -> 900 | U10: =P10-T10 -> 325 | V10: =U10/6 -> 54.166667
C11: 3 | D11: 30 | E11: 50 | F11: 150 | G11: 40 | H11: 180 | J11: 40 | K11: 200 | P11: =SUM(D11:O11) -> 690 | Q11: =P11/2 -> 345 | R11: 708 | S11: =29*6 -> 174 | T11: =S11+R11 -> 882 | U11: =P11-T11 -> -192 | V11: =U11/6 -> -32
C12: 4 | D12: 450 | E12: 30 | F12: 30 | G12: 10 | H12: 30 | I12: 10 | J12: 80 | K12: 180 | P12: =SUM(D12:O12) -> 820 | Q12: =P12/2 -> 410 | R12: 2442 | S12: 0 | T12: =S12+R12 -> 2442 | U12: =P12-T12 -> -1622 | V12: =U12/6 -> -270.33333
C13: 6 | D13: 120 | E13: 40 | F13: =30*3 -> 90 | G13: 40 | H13: =40*3 -> 120 | J13: 20 | K13: 40 | L13: 15 | P13: =SUM(D13:O13) -> 485 | Q13: =P13/2 -> 242.5 | R13: 354 | S13: 0 | T13: =S13+R13 -> 354 | U13: =P13-T13 -> 131 | V13: =U13/6 -> 21.833333
C14: 8 | L14: 50 | P14: =SUM(D14:O14) -> 50 | Q14: 0 | T14: =S14+R14 -> 0
C19: Pipe Dia(inch) | D19: JUN-T1 | E19: JUN-T2 | F19: SUPERVISOR | G19: ISOLATED | H19: SENIOR | I19: ADMIN | J19: RECREATION | K19: SERVICE | L19: TOTAL
C20: 1 | D20: 651 | E20: 130 | F20: 326 | G20: 62.5 | H20: 371 | J20: 275 | K20: 525 | L20: =D20+E20+F20+G20+H20+I20+J20+K20 -> 2340.5
C21: 1.25 | D21: 97 | E21: 30 | F21: 22 | G21: 2.5 | H21: 22.5 | J21: 82 | K21: 134 | L21: =D21+E21+F21+G21+H21+I21+J21+K21 -> 390
C22: 1.5 | D22: 65 | E22: 5 | F22: 30 | G22: 10 | H22: 33.5 | I22: 10 | J22: 33 | K22: 72 | L22: =D22+E22+F22+G22+H22+I22+J22+K22 -> 258.5 | O22: 369 | P22: 6KG FIRE EXTINGUISHER
C23: 2 | D23: 40 | E23: 33 | F23: 15 | G23: 7.5 | H23: 22.5 | I23: 7.5 | J23: 15 | K23: 27.5 | L23: =D23+E23+F23+G23+H23+I23+J23+K23 -> 168
C24: 2.5 | D24: 20 | E24: 48 | F24: 55 | G24: 17.5 | H24: 86.5 | I24: 7.5 | J24: 33 | K24: 33 | L24: =D24+E24+F24+G24+H24+I24+J24+K24 -> 300.5
C25: 3 | D25: 30 | E25: 45 | F25: 100 | G25: 20 | H25: 120 | I25: 0 | J25: 10 | K25: 50 | L25: =D25+E25+F25+G25+H25+I25+J25+K25 -> 375
C26: 4 | D26: 227 | E26: 15 | F26: 15 | G26: 2.5 | H26: 15 | I26: 5 | J26: 40 | K26: 90 | L26: =D26+E26+F26+G26+H26+I26+J26+K26 -> 409.5
C27: 6 | D27: 17 | E27: 20 | F27: 22.5 | G27: 10 | H27: 30 | J27: 5 | K27: 10 | L27: =D27+E27+F27+G27+H27+I27+J27+K27 -> 114.5
C28: 8 | L28: =D28+E28+F28+G28+H28+I28+J28+K28 -> 0
C33: Pipe Dia(inch) | D33: JUN-T1 | E33: JUN-T2 | F33: SUPERVISOR | G33: ISOLATED | H33: SENIOR | I33: ADMIN | J33: RECREATION | K33: SERVICE | L33: TOTAL
C34: 1 | D34: =D20-D6 -> -1899 | E34: =E20-E6 -> -390 | F34: =F20-F6 -> -979 | G34: =G20-G6 -> -187.5 | H34: =H20-H6 -> -1114 | I34: =I20-I6 -> 0 | J34: =J20-J6 -> -805 | K34: =K20-K6 -> -1575 | L34: =D34+E34+F34+G34+H34+I34+J34+K34 -> -6949.5
C35: 1.25 | D35: =D21-D7 -> -278 | E35: =E21-E7 -> -90 | F35: =F21-F7 -> -68 | G35: =G21-G7 -> -7.5 | H35: =H21-H7 -> -67.5 | I35: =I21-I7 -> 0 | J35: =J21-J7 -> -243 | K35: =K21-K7 -> -401 | L35: =D35+E35+F35+G35+H35+I35+J35+K35 -> -1155
C36: 1.5 | D36: =D22-D8 -> -211 | E36: =E22-E8 -> -15 | F36: =F22-F8 -> -90 | G36: =G22-G8 -> -30 | H36: =H22-H8 -> -101.5 | I36: =I22-I8 -> -30 | J36: =J22-J8 -> -97 | K36: =K22-K8 -> -213 | L36: =D36+E36+F36+G36+H36+I36+J36+K36 -> -787.5
C37: 2 | D37: =D23-D9 -> -50 | E37: =E23-E9 -> -97 | F37: =F23-F9 -> -45 | G37: =G23-G9 -> -22.5 | H37: =H23-H9 -> -67.5 | I37: =I23-I9 -> -22.5 | J37: =J23-J9 -> -45 | K37: =K23-K9 -> -82.5 | L37: =D37+E37+F37+G37+H37+I37+J37+K37 -> -432
C38: 2.5 | D38: =D24-D10 -> -10 | E38: =E24-E10 -> -142 | F38: =F24-F10 -> -245 | G38: =G24-G10 -> -52.5 | H38: =H24-H10 -> -258.5 | I38: =I24-I10 -> -22.5 | J38: =J24-J10 -> -97 | K38: =K24-K10 -> -97 | L38: =D38+E38+F38+G38+H38+I38+J38+K38 -> -924.5
C39: 3 | D39: =D25-D11 -> 0 | E39: =E25-E11 -> -5 | F39: =F25-F11 -> -50 | G39: =G25-G11 -> -20 | H39: =H25-H11 -> -60 | I39: =I25-I11 -> 0 | J39: =J25-J11 -> -30 | K39: =K25-K11 -> -150 | L39: =D39+E39+F39+G39+H39+I39+J39+K39 -> -315
C40: 4 | D40: =D26-D12 -> -223 | E40: =E26-E12 -> -15 | F40: =F26-F12 -> -15 | G40: =G26-G12 -> -7.5 | H40: =H26-H12 -> -15 | I40: =I26-I12 -> -5 | J40: =J26-J12 -> -40 | K40: =K26-K12 -> -90 | L40: =D40+E40+F40+G40+H40+I40+J40+K40 -> -410.5
C41: 6 | D41: =D27-D13 -> -103 | E41: =E27-E13 -> -20 | F41: =F27-F13 -> -67.5 | G41: =G27-G13 -> -30 | H41: =H27-H13 -> -90 | I41: =I27-I13 -> 0 | J41: =J27-J13 -> -15 | K41: =K27-K13 -> -30 | L41: =D41+E41+F41+G41+H41+I41+J41+K41 -> -355.5
C42: 8 | L42: =D42+E42+F42+G42+H42+I42+J42+K42 -> 0

Sheet حصر الكيبل
G9: CONTRACT QUANTITES
C10: 2.5MM CABLE | D10: JUN-T1 | E10: JUN-T2 | F10: SUPERVISOR | G10: ISOLATED | H10: SENIOR | I10: ADMIN | J10: RECREATION | K10: SERVICE | L10: GUARD RM | M10: PUMP RM-1 | N10: PUMP RM-2 | O10: PUMP RM-3 | P10: TOTAL
C11: SLC | D11: 3915 | E11: 1600 | F11: 2400 | G11: 800 | H11: 3600 | I11: 800 | J11: 2000 | K11: 2000 | L11: 120 | M11: 80 | N11: 80 | O11: 80
C12: NAC | D12: 1845 | E12: 800 | F12: 1200 | G12: 400 | H12: 1800 | I12: 400 | J12: 800 | K12: 800 | L12: 30
C13: TOTAL | D13: =SUM(D11:D12) -> 5760 | E13: =SUM(E11:E12) -> 2400 | F13: =SUM(F11:F12) -> 3600 | G13: =SUM(G11:G12) -> 1200 | H13: =SUM(H11:H12) -> 5400 | I13: =SUM(I11:I12) -> 1200 | J13: =SUM(J11:J12) -> 2800 | K13: =SUM(K11:K12) -> 2800 | ... O13: =SUM(O11:O12) -> 80 | P13: =SUM(D13:O13) -> 25550
P15: =P13/305 -> 83.770492
J16: =J13/305 -> 9.1803279
F17: ACTUAL SUPPLIED QUANTITY | I17: 50 ROLL X 305M= | K17: =50*305 -> 15250
I18: 16 ROLL X 305M= | K18: =16*305 -> 4880
I19: 04 ROLL X 305 | K19: =4*305 -> 1220
I20: 06 ROLL X 305 | K20: =6*305 -> 1830
I21: 16 ROLL X 305 | K21: =16*305 -> 4880
I22: 3 ROLL X 305 | K22: =3*305 -> 915
I23: TOTAL | K23: =SUM(K17:K22) -> 28975
C24: 2.5MM CABLE | D24: JUN-T1 | E24: JUN-T2 | F24: SUPERVISOR | G24: ISOLATED | H24: SENIOR | I24: ADMIN | J24: RECREATION | K24: SERVICE | L24: GUARD RM | M24: PUMP RM-1 | N24: PUMP RM-2 | O24: PUMP RM-3 | P24: TOTAL
C25: SLC | D25: 3915 | E25: 1600 | F25: 2400 | G25: 800 | H25: 3600 | I25: 800 | J25: 2000 | K25: 1200+800 | L25: 120 | M25: 80 | N25: 80 | O25: 80
C26: NAC | D26: 1845 | E26: 800 | F26: 1200 | G26: 400 | H26: 1800 | I26: 400 | J26: 800 | K26: 800 | L26: 30
C27: TOTAL | D27: =SUM(D25:D26) -> 5760 | E27: =SUM(E25:E26) -> 2400 | F27: =SUM(F25:F26) -> 3600 | G27: =SUM(G25:G26) -> 1200 | H27: =SUM(H25:H26) -> 5400 | I27: =SUM(I25:I26) -> 1200 | J27: =SUM(J25:J26) -> 2800 | K27: 2800 | L27: =SUM(L25:L26) -> 150 | M27: =SUM(M25:M26) -> 80 | N27: =SUM(N25:N26) -> 80 | O27: =SUM(O25:O26) -> 80 | P27: =SUM(D27:O27) -> 25550
S28: =D12-D26 -> 0
D29: 395 | J29: 2000 + 150 +80= 2230
F31: ACTUAL INSTALLED FLOOR | I31: NEW INSTALLED
I32: OLD INSTALLED
C34: BLDG. FLOOR | D34: JUN-T1 | E34: JUN-T2 | F34: SUPERVISOR | G34: ISOLATED | H34: SENIOR | I34: ADMIN | J34: RECREATION | K34: SERVICE | L34: GUARD RM | M34: PUMP RM-1 | N34: PUMP RM-2 | O34: PUMP RM-3
C35: GR | D35: X3 | E35: X2 | F35: X3 | G35: X1 | H35: X3 | I35: X1 | J35: X1 | L35: X1
C36: 1st | D36: X3 | E36: X2 | F36: X3 | G36: X1 | H36: X3 | I36: X1
C37: 2nd | D37: X3 | E37: X2 | F37: OLDX2 + NEW X1 | H37: X3
C38: ROOF | D38: X3 | E38: NEW X2 | F38: OLDX2 + NEW X1 | H38: X3
C43: DEVICE TYPE | D43: OLD.SPLYD | E43: NEW.SPLYD | F43: JN-1 | G43: JN-2 | H43: ADMIN | I43: SPRVSR | J43: SENIOR | K43: REMAIN
C44: SMOKE | D44: =650+92 -> 742 | E44: 60 | F44: 157 | G44: 244 | H44: 52 | I44: 0 | J44: 197 | K44: =D44-E44-F44-G44-H44-I44-J44 -> 32
C45: HEAT | D45: 30 | E45: 4 | F45: 15 | G45: 6 | H45: 2 | I45: 0 | J45: 7 | K45: =D45+E45-F45-G45-H45-I45-J45 -> 4
C46: MCP | D46: 45 | E46: 0 | F46: 30 | G46: 12 | H46: 3 | I46: 0 | J46: 0 | K46: =D46+E46-F46-G46-H46-I46-J46 -> 0
C47: WP-MCP | D47: 20 | E47: 7 | F47: 14 | G47: 4 | H47: 0 | I47: 2 | J47: 0 | K47: 0
C48: SIREN | D48: 15 | E48: 15 | F48: 15 | G48: =D48-F48 -> 0 | H48: 0 | I48: 0 | J48: 0 | K48: =D48+E48-F48-G48-H48-I48-J48 -> 15
C49: WP-SIREN | D49: 20 | E49: 27 | F49: 13 | G49: =D49-F49 -> 7 | H49: 0 | I49: 0 | J49: 0 | K49: =D49+E49-F49-G49-H49-I49-J49 -> 27
C50: PANELS

Sheet المصروفات الإضافية
A1: سجل المصروفات الإضافية للمشروع
A2: أدخل كل مصروف في صف مستقل. اترك خانة المبلغ فارغة إذا لم يتم تسجيل المصروف بعد.
A4: التاريخ | B4: الفئة | C4: البيان / الغرض | D4: المورد أو المستفيد | E4: رقم المستند | F4: المبلغ (ر.س) | G4: حالة الاعتماد | H4: ملاحظات | I4: الشهر | J4: كود التكلفة
A5: 1مايو 2024 | B5: مرتبات الاستاف | C5: مرتب المهندس عصام | D5: مهندس عصام | F5: 84000 | H5: حتي ابريل 2025 7000X | I5: =IF(A5="","",TEXT(A5,"mmm-yyyy")) -> 1مايو 2024
A6: 1مايو 2024 | B6: مرتبات الاستاف | C6: مرتب المهندس إبراهيم | D6: مهندس إبراهيم | F6: 94000 | H6: 12 month per 7000+2 month per 5000 | I6: =IF(A6="","",TEXT(A6,"mmm-yyyy")) -> 1مايو 2024 | O6: =12*7 -> 84
A7: 1مايو 2024 | B7: السكن | C7: سكن المهندسين | D7: المهندسين | F7: 37500 | H7: سكن شقة مفروشة لفترة 15 شهر في 2500 | I7: =IF(A7="","",TEXT(A7,"mmm-yyyy")) -> 1مايو 2024
A8: 1مارس 2025 | B8: مرتبات الاستاف | C8: مرتب مهندس عثمان | D8: م عثمان | F8: 109000 | H8: 12شهر بحساب 5000 ريال و7 شهور بحساب 7000 | I8: =IF(A8="","",TEXT(A8,"mmm-yyyy")) -> 1مارس 2025
A9: 1مارس 2025 | B9: السكن | C9: سكن المهندس عثمان | D9: م عثمان | F9: 30000 | H9: سكن شقة مفروشة لفترة 12 شهر في 2500 | I9: =IF(A9="","",TEXT(A9,"mmm-yyyy")) -> 1مارس 2025
A10: 1مايو 2024 | B10: الترحيل والنقل | C10: م إبراهيم وعثمان | D10: إبراهيم وعثمان | F10: =3000*30 -> 90000 | H10: نقل المهندسين | I10: =IF(A10="","",TEXT(A10,"mmm-yyyy")) -> 1مايو 2024
A11: 1مايو 2024 | B11: السكن | C11: سكن العمال شقتين | D11: عمال المشروع | F11: 60000 | H11: سكن عمال | I11: =IF(A11="","",TEXT(A11,"mmm-yyyy")) -> 1مايو 2024
A12: 1مايو 2024 | B12: معدات وأدوات | C12: ترحيل مواد وايجار معدات | D12: مصاريف المشروع | F12: 25000 | H12: مصاريف المشروع | I12: =IF(A12="","",TEXT(A12,"mmm-yyyy")) -> 1مايو 2024
A13: 1مايو 2024 | B13: مصاريف مكتبية | C13: مصاريف المكتب | D13: مصاريف مكتبية | F13: 20000 | H13: طباعة وضيافة ومواد مكتبية | I13: =IF(A13="","",TEXT(A13,"mmm-yyyy")) -> 1مايو 2024
I14: =IF(A14="","",TEXT(A14,"mmm-yyyy"))
I15: =IF(A15="","",TEXT(A15,"mmm-yyyy"))
I16: =IF(A16="","",TEXT(A16,"mmm-yyyy"))
I17: =IF(A17="","",TEXT(A17,"mmm-yyyy"))
I18: =IF(A18="","",TEXT(A18,"mmm-yyyy"))
I19: =IF(A19="","",TEXT(A19,"mmm-yyyy"))
I20: =IF(A20="","",TEXT(A20,"mmm-yyyy"))
I21: =IF(A21="","",TEXT(A21,"mmm-yyyy"))
I22: =IF(A22="","",TEXT(A22,"mmm-yyyy"))
I23: =IF(A23="","",TEXT(A23,"mmm-yyyy"))
I24: =IF(A24="","",TEXT(A24,"mmm-yyyy"))
I25: =IF(A25="","",TEXT(A25,"mmm-yyyy"))
... I204: =IF(A204="","",TEXT(A204,"mmm-yyyy"))

Sheet ملخص التكاليف
A1: ملخص تكاليف مشروع سبارك
A3: مصدر التكلفة | B3: المواد (ر.س) | C3: العمالة (ر.س) | D3: إجمالي التكلفة المباشرة (ر.س) | E3: الربح الحسابي قبل المصروفات (ر.س) | F3: هامش الربح الحسابي | G3: Profit الفعلي من الورقة (ر.س) | I3: المبلغ الكلي للمبني | J3: التكلفة الكلية عمالة ومواد | K3: الربح الاسمي
A4: JUN-T1 E | B4: 389778 | C4: 83280 | D4: =B4+C4 -> 473058 | E4: 822424.2 | F4: =D4/E4 -> 0.57519951 | G4: 349366.2 | I4: ='JUN-T1 E'!J36 -> 822424.2 | J4: ='JUN-T1 E'!N36 -> 473058 | K4: =I4-J4 -> 349366.2
A5: JUN-T1-EXT | B5: 49728 | C5: 2160 | D5: =B5+C5 -> 51888 | E5: 76242 | F5: =D5/E5 -> 0.68056976 | G5: 24354 | I5: ='JUN-T1-EXT'!K20 -> 76242 | J5: ='JUN-T1-EXT'!O20 -> 51888 | K5: =I5-J5 -> 24354
A6: JUN-T1 | B6: 413250 | C6: 147900 | D6: =B6+C6 -> 561150 | E6: 759495.45 | F6: =D6/E6 -> 0.73884577 | G6: 110628.45 | I6: ='JUN-T1'!K39 -> 759495.45 | J6: ='JUN-T1'!P39 -> 648867 | K6: =I6-J6 -> 110628.45
A7: JUN-T2 E | B7: 92788 | C7: 24480 | D7: =B7+C7 -> 117268 | E7: 218269.4 | F7: =D7/E7 -> 0.53726267 | G7: 101001.4 | I7: ='JUN-T2 E'!J35 -> 218269.4 | J7: ='JUN-T2 E'!N35 -> 117268 | K7: =I7-J7 -> 101001.4
A8: JUN-T2-EXT | B8: 11168 | C8: 480 | D8: =B8+C8 -> 11648 | E8: 15617 | F8: =D8/E8 -> 0.74585388 | G8: 3969 | I8: ='JUN-T2-EXT'!K20 -> 15617 | J8: ='JUN-T2-EXT'!O20 -> 11648 | K8: =I8-J8 -> 3969
